Workbook

Sheet ع1-ن18
B1: =[1]البيانات!D1 -> شركة حصاد الجحاز للتجارة العامة والمقاولات القابضة | J1: =[1]البيانات!B9 -> التوقيع المعتمد | N1: فريق العمل | O1: =[1]البيانات!D9 -> أ مسعود الرفيدي | T1: الوظيفة والتوقيع | U1: =[1]البيانات!N9 -> الشريك المسؤول | AC1: المعيار الدولي | AD1: IFRS | AE1: IAS | AH1: وفقا لمعيار التدقيق الدولي رقم (500) هنالك عدة إجراءات يستخدمها المدقق للحصول على أدلة تدقيق، وهي
B2: =[1]البيانات!D2 -> شركة ذات مسؤولية محدودة | J2: =[1]البيانات!B10 -> المدقق المباشر | O2: =[1]البيانات!D10 -> أ.اسلام الأشقر | U2: =[1]البيانات!N10 -> مدقق حسابات
B3: =[1]البيانات!D3 -> للسنة المالية المنتهية في | J3: =[1]البيانات!B11 -> مدير المراجعة | O3: =[1]البيانات!D11 -> أ. طاهر عبد الغفور | U3: =[1]البيانات!N11 -> مدير المراجعة
B4: =[1]البيانات!D4 -> 45657 | J4: =[1]البيانات!B12 -> الإدارة | O4: =[1]البيانات!D12 -> أ. طاهر عبد الغفور | U4: =[1]البيانات!N12 -> المدير الإداري
A5: المستوي | AF5: كود المرحلة | AG5: مراحل الملف | AH5: الاجراء | AI5: نطاق الإجراء | AJ5: طريقة الاختيار | AK5: امثلة الاستخدام | AN5: اعمال | BE5: نعم=3/لا=1/لا ينطبق=2
B6: فاصل | F6: ورقة عمل رقم | G6: فهرس الملــــــــــــــــــــــــــــــــــــف | AN6: البرنامج | AP6: السكرتارية | AR6: مدير المراجعة | AT6: المدقق الفني | AV6: المدقق حسابات | AX6: وزارة التجارة | AZ6: الهيئة العامة للزكاة والدخل | BB6: الجودة | BC6: الشريك الإداري | BD6: الأرشيف | BE6: نعم=3/لا=1/لا ينطبق=2
B7: 1 | C7: 2 | D7: 3 | E7: 4 | G7: بيان
A8: الأول | B8: ع | C8: ع | D8: ع | E8: ع | F8: ع | G8: ملف عموميات | AB8: نوع الإجابة | AF8: 1
A9: الثاني | B9: =B8 -> ع | C9: ع1 | D9: ع1 | E9: ع1 | F9: ع1 | G9: الملف الدائم (مرحلة استكمال المتطلبات الأساسية | AF9: 1.1 | AH9: الاستفسار | AI9: حقائق معينة
A10: الثالث | B10: =B9 -> ع | C10: =C9 -> ع1 | D10: ع1-1 | E10: ع1-1 | F10: ع1-1 | G10: المستندات من المنشأة | AF10: 1.1.1 | AG10: مرحلة قبول العميل | AH10: الاستفسار | AI10: حقائق معينة | AJ10: 1
A11: الرابع | B11: =B10 -> ع | C11: =C10 -> ع1 | D11: =D10 -> ع1-1 | E11: ع1-1-1 | F11: ع1-1-1 | G11: صورمن المستندات الرسمية الرسمية للمنشأة | AF11: B.16.01 | AG11: مرحلة قبول العميل | AH11: الاستفسار | AI11: حقائق معينة
A12: الخامس | B12: =B11 -> ع | C12: =C11 -> ع1 | D12: =D11 -> ع1-1 | F12: ع1-1-1-1 | G12: السجل التجــــــــــــــــــــــــــــاري وفروع السجل التجاري | AB12: PDF | AF12: B.160101 | AH12: الاستفسار | AI12: حقائق معينة
A13: الخامس | B13: =B12 -> ع | C13: =C12 -> ع1 | D13: =D12 -> ع1-1 | F13: ع1-1-1-2 | G13: عقد تأسيس المنشأة وتعديلاتة وصور من محاضر اجتماعات مجلس الإدارة | AB13: PDF | AF13: B.160102 | AG13: مرحلة قبول العميل | AH13: الاستفسار | AI13: حقائق معينة
A14: الخامس | B14: =B13 -> ع | C14: =C13 -> ع1 | D14: =D13 -> ع1-1 | F14: ع1-1-1-3 | G14: ترخيص المزاولة مختـــــــــــــــــــــــــــــــــــــــــــــــوم | AB14: PDF | AF14: B.160103 | AH14: الاستفسار | AI14: حقائق معينة
A15: الخامس | B15: =B14 -> ع | C15: =C14 -> ع1 | D15: =D14 -> ع1-1 | F15: ع1-1-1-4 | G15: صور هويات الشركاء / صاحب المنشأة | AB15: PDF | AF15: B.160104 | AG15: مرحلة قبول العميل | AH15: الاستفسار | AI15: حقائق معينة
A16: الخامس | B16: =B15 -> ع | C16: =C15 -> ع1 | D16: =D15 -> ع1-1 | F16: ع1-1-1-5 | G16: صورة آخر شهادة زكاة شرعية (شركة / مؤسســـــــة) | AB16: PDF | AF16: B.160105 | AH16: الاستفسار | AI16: حقائق معينة
A17: الخامس | B17: =B16 -> ع | C17: =C16 -> ع1 | D17: =D16 -> ع1-1 | F17: ع1-1-1-6 | G17: شهادة التامينات باجمالى الرواتب قيمة وعــــــــــــــدد | AB17: PDF | AF17: B.160106 | AH17: الاستفسار | AI17: حقائق معينة
A18: الخامس | B18: =B17 -> ع | C18: =C17 -> ع1 | D18: =D17 -> ع1-1 | F18: ع1-1-1-7 | G18: بيان الاستيراد من الجمارك (في حالة وجود استيراد من الخارج) | AB18: PDF | AF18: B.160107 | AH18: الاستفسار | AI18: حقائق معينة
A19: الخامس | B19: =B18 -> ع | C19: =C18 -> ع1 | D19: =D18 -> ع1-1 | F19: ع1-1-1-8 | G19: خلفية عن نشاط المنشأة وفروعـــــــــــــــــــــــــــــــــه | AB19: نموذج/ PDF | AF19: B.160108 | AG19: مرحلة قبول العميل | AH19: الاستفسار | AI19: حقائق معينة
A20: الخامس | B20: =B19 -> ع | C20: =C19 -> ع1 | D20: =D19 -> ع1-1 | F20: ع1-1-1-9 | G20: تفويض برفع القوائم المالية عبر الموقع الالكترونى بوزارة التجارة | AB20: نموذج/ PDF | AF20: B.160109 | AH20: الاستفسار | AI20: حقائق معينة
A21: الخامس | B21: =B20 -> ع | C21: =C20 -> ع1 | D21: =D20 -> ع1-1 | F21: ع1-1-1-10 | G21: خطاب عدم مزاولة النشـــــــــــــــــــــــــــــــــــــــــاط ان كانت لم تمارس النشاط | AB21: نموذج/ PDF | AF21: B.160110 | AH21: الاستفسار | AI21: حقائق معينة
B22: =B21 -> ع | C22: =C21 -> ع1 | D22: =D21 -> ع1-1 | AF22: B.160111 | AH22: الاستفسار | AI22: حقائق معينة
B23: =B22 -> ع | C23: =C22 -> ع1 | D23: =D22 -> ع1-1 | AF23: B.160112 | AH23: الاستفسار | AI23: حقائق معينة
B24: =B23 -> ع | C24: =C23 -> ع1 | D24: =D23 -> ع1-1 | AF24: B.160113 | AH24: الاستفسار | AI24: حقائق معينة
A25: الثاني | B25: =B24 -> ع | C25: ع2 | D25: ع2 | E25: ع2 | F25: ع2 | G25: قوائم الاستبيان والاستقصاء والتقييم والاختبار (المرحلة الاولي لقبول المنشأة والموافقة على الارتباط) | AF25: 1.2 | AG25: مرحلة قبول العميل | AH25: الاستفسار | AI25: حقائق معينة | AJ25: 1
A26: الثالث | B26: =B25 -> ع | C26: =C25 -> ع2 | D26: ع2-1 | E26: ع2-1 | F26: ع2-1 | G26: قوائم استبيان الرقابة الداخلية | AF26: 1.2.1 | AG26: مرحلة تقييم الرقابة الداخلية | AH26: الاستفسار | AI26: حقائق معينة | AJ26: 1
A27: الرابع | B27: =B26 -> ع | C27: =C26 -> ع2 | D27: =D26 -> ع2-1 | E27: ع2-1-1 | F27: ع2-1-1 | G27: تقييم الجهاز التنظيمي والمحاسبة العامة | AB27: نعم=3/لا=1/لا ينطبق=2 | AF27: A7.01 | AH27: الاستفسار | AI27: حقائق معينة
A28: الخامس | B28: =B27 -> ع | C28: =C27 -> ع2 | D28: =D27 -> ع2-1 | E28: =E27 -> ع2-1-1 | F28: ع2-1-1-1 | G28: هل يوجد رسما للهيكل التنظيمي للمنشأة | AB28: 3 | AF28: A.7 | AG28: مرحلة قبول العميل | AH28: الاستفسار | AI28: حقائق معينة
A29: الخامس | B29: =B28 -> ع | C29: =C28 -> ع2 | D29: =D28 -> ع2-1 | E29: =E28 -> ع2-1-1 | F29: ع2-1-1-2 | G29: هل لدى المنشأة لوائح معتمدة بالسياسات والاجراءات المحاسبية | AB29: 3 | AF29: A.7 | AG29: مرحلة قبول العميل | AH29: الاستفسار | AI29: حقائق معينة
A30: الخامس | B30: =B29 -> ع | C30: =C29 -> ع2 | D30: =D29 -> ع2-1 | E30: =E29 -> ع2-1-1 | F30: ع2-1-1-3 | G30: هل يوجد وصف للوظائف ولوائح للقائمين عليها حتى لاتتم الازدواجية في العمل . | AB30: 3 | AF30: A.7 | AH30: الاستفسار | AI30: حقائق معينة
A31: الخامس | B31: =B30 -> ع | C31: =C30 -> ع2 | D31: =D30 -> ع2-1 | E31: =E30 -> ع2-1-1 | F31: ع2-1-1-4 | G31: هل ترفع تقارير دورية للادارة . | AB31: 3 | AF31: A.7 | AH31: الاستفسار | AI31: حقائق معينة
A32: الخامس | B32: =B31 -> ع | C32: =C31 -> ع2 | D32: =D31 -> ع2-1 | E32: =E31 -> ع2-1-1 | F32: ع2-1-1-5 | G32: هل يجري التحري عن المسؤولين عن النقد قبل ترشيحهم ويتم التأمين عليهم ضد سوء الامانة والنقد في الطريق | AB32: 3 | AF32: A.7 | AH32: الاستفسار | AI32: حقائق معينة
A33: الخامس | B33: =B32 -> ع | C33: =C32 -> ع2 | D33: =D32 -> ع2-1 | E33: =E32 -> ع2-1-1 | F33: ع2-1-1-6 | G33: هل من يقوم بتحرير سندات الصرف اشخاص غير امين الخزينة . | AB33: 3 | AF33: A.7 | AH33: الاستفسار | AI33: حقائق معينة
A34: الخامس | B34: =B33 -> ع | C34: =C33 -> ع2 | D34: =D33 -> ع2-1 | E34: =E33 -> ع2-1-1 | F34: ع2-1-1-7 | G34: هل يتم حفظ دفاتر الشيكات والدفاتر المحاسبية في مكان امن . | AB34: 3 | AF34: A.7 | AH34: الاستفسار | AI34: حقائق معينة
A35: الخامس | B35: =B34 -> ع | C35: =C34 -> ع2 | D35: =D34 -> ع2-1 | E35: =E34 -> ع2-1-1 | F35: ع2-1-1-8 | G35: هل يوجد شخص يقوم بمراجعة قيود التسوية غير الشخص الذي يقوم باعدادها . | AB35: 3 | AF35: A.7 | AH35: الاستفسار | AI35: حقائق معينة
B36: =B35 -> ع | C36: =C35 -> ع2 | D36: =D35 -> ع2-1 | E36: =E35 -> ع2-1-1 | AF36: A.7 | AH36: الاستفسار | AI36: حقائق معينة
A37: الرابع | B37: =B36 -> ع | C37: =C36 -> ع2 | D37: =D36 -> ع2-1 | E37: ع2-1-2 | F37: ع2-1-2 | G37: الرقابة الداخلية على إدارة المقبوضات والمدفوعات | AB37: نعم=3/لا=1/لا ينطبق=2 | AF37: A.7.02 | AG37: مرحلة تقييم الرقابة الداخلية | AH37: الاستفسار | AI37: حقائق معينة
A38: الخامس | B38: =B37 -> ع | C38: =C37 -> ع2 | D38: =D37 -> ع2-1 | E38: =E37 -> ع2-1-2 | F38: ع2-1-2-1 | G38: هل يتم تدريب امناء الصندوق والعهد | AB38: 3 | AF38: A.7 | AH38: الاستفسار | AI38: حقائق معينة
A39: الخامس | B39: =B38 -> ع | C39: =C38 -> ع2 | D39: =D38 -> ع2-1 | E39: =E38 -> ع2-1-2 | F39: ع2-1-2-2 | G39: هل سندات الصرف والقبض مرقمة ويتم مراجعة التسلسل | AB39: 3 | AF39: A.7 | AH39: الاستفسار | AI39: حقائق معينة
A40: الخامس | B40: =B39 -> ع | C40: =C39 -> ع2 | D40: =D39 -> ع2-1 | E40: =E39 -> ع2-1-2 | F40: ع2-1-2-3 | G40: هل يتم مراجعة مرفقات سندات الصرف والقبض قبل اعتمادها | AB40: 3 | AF40: A.7 | AH40: الاستفسار | AI40: حقائق معينة
A41: الخامس | B41: =B40 -> ع | C41: =C40 -> ع2 | D41: =D40 -> ع2-1 | E41: =E40 -> ع2-1-2 | F41: ع2-1-2-4 | G41: هل يتم التحقق من المستلم قبل تسليمه الشيكات او النقدية | AB41: 3 | AF41: A.7 | AH41: الاستفسار | AI41: حقائق معينة
B42: =B41 -> ع | C42: =C41 -> ع2 | D42: =D41 -> ع2-1 | E42: =E41 -> ع2-1-2 | AF42: A.7 | AH42: الاستفسار | AI42: حقائق معينة
A43: الرابع | B43: =B42 -> ع | C43: =C42 -> ع2 | D43: =D42 -> ع2-1 | E43: ع2-1-3 | F43: ع2-1-3 | G43: النقدية بالصندوق | AB43: نعم=3/لا=1/لا ينطبق=2 | AF43: A.7.03 | AH43: الاستفسار | AI43: حقائق معينة
A44: الخامس | B44: =B43 -> ع | C44: =C43 -> ع2 | D44: =D43 -> ع2-1 | E44: =E43 -> ع2-1-3 | F44: ع2-1-3-1 | G44: هل يتم الفصل بين معتمد الصرف وامين الخزينة والقائم بتسجيل الصرف | AB44: 3 | AF44: A.7 | AH44: الاستفسار | AI44: حقائق معينة
A45: الخامس | B45: =B44 -> ع | C45: =C44 -> ع2 | D45: =D44 -> ع2-1 | E45: =E44 -> ع2-1-3 | F45: ع2-1-3-2 | G45: هل يتم التأمين على أمين الخزينة . | AB45: 3 | AF45: A.7 | AH45: الاستفسار | AI45: حقائق معينة
A46: الخامس | B46: =B45 -> ع | C46: =C45 -> ع2 | D46: =D45 -> ع2-1 | E46: =E45 -> ع2-1-3 | F46: ع2-1-3-3 | G46: هل للمنشأة سياسة محاسبية تبلغ بها الادارة المالية وهل السجلات مقصور الاطلاع عليها على الادارة المالية . | AB46: 3 | AF46: A.7 | AG46: مرحلة قبول العميل | AH46: الاستفسار | AI46: حقائق معينة
A47: الخامس | B47: =B46 -> ع | C47: =C46 -> ع2 | D47: =D46 -> ع2-1 | E47: =E46 -> ع2-1-3 | F47: ع2-1-3-4 | G47: هل يتم جرد الخزينة جردا فجائياً | AB47: 3 | AF47: A.7 | AH47: الاستفسار | AI47: حقائق معينة
A48: الخامس | B48: =B47 -> ع | C48: =C47 -> ع2 | D48: =D47 -> ع2-1 | E48: =E47 -> ع2-1-3 | F48: ع2-1-3-5 | G48: هل تشمل القيود اليومية وسندات الصرف والقبض كافة معاملات المنشأة المالية . | AB48: 3 | AF48: A.7 | AG48: مرحلة قبول العميل | AH48: الاستفسار | AI48: حقائق معينة
A49: الخامس | B49: =B48 -> ع | C49: =C48 -> ع2 | D49: =D48 -> ع2-1 | E49: =E48 -> ع2-1-3 | F49: ع2-1-3-6 | G49: هل تتضمن القوائم المالية قائمة التدفقات النقدية . | AB49: 3 | AF49: A.7 | AH49: الاستفسار | AI49: حقائق معينة
A50: الخامس | B50: =B49 -> ع | C50: =C49 -> ع2 | D50: =D49 -> ع2-1 | E50: =E49 -> ع2-1-3 | F50: ع2-1-3-7 | G50: هل يتم مراجعة مرفقات استعاضة السلفة من قبل الادارة المالية قبل صرف الاستعاضة . | AB50: 3 | AF50: A.7 | AH50: الاستفسار | AI50: حقائق معينة
A51: الخامس | B51: =B50 -> ع | C51: =C50 -> ع2 | D51: =D50 -> ع2-1 | E51: =E50 -> ع2-1-3 | F51: ع2-1-3-8 | G51: هل تحتفظ الخزينة بصور سندات الصرف والقبض وكعوب الشيكات وهل يتم جردها بصفة دورية . | AB51: 3 | AF51: A.7 | AH51: الاستفسار | AI51: حقائق معينة
A52: الخامس | B52: =B51 -> ع | C52: =C51 -> ع2 | D52: =D51 -> ع2-1 | E52: =E51 -> ع2-1-3 | F52: ع2-1-3-9 | G52: هل يتم الاحتفاظ بدفاتر الشيكات غير المستعملة وكعوب الشيكات المستعملة منها بالخزينة . | AB52: 3 | AF52: A.7 | AG52: مرحلة الاغلاق والارشفة | AH52: الاستفسار | AI52: حقائق معينة
B53: =B52 -> ع | C53: =C52 -> ع2 | D53: =D52 -> ع2-1 | E53: =E52 -> ع2-1-3 | AF53: A.7 | AH53: الاستفسار | AI53: حقائق معينة
A54: الرابع | B54: =B53 -> ع | C54: =C53 -> ع2 | D54: =D53 -> ع2-1 | E54: ع2-1-4 | F54: ع2-1-4 | G54: الرقابة على المبيعات / الإيرادات والمديونية | AB54: نعم=3/لا=1/لا ينطبق=2 | AF54: A.7.04 | AG54: مرحلة تقييم الرقابة الداخلية | AH54: الاستفسار | AI54: حقائق معينة
A55: الخامس | B55: =B54 -> ع | C55: =C54 -> ع2 | D55: =D54 -> ع2-1 | E55: =E54 -> ع2-1-4 | F55: ع2-1-4-1 | G55: هل يتم تحرير الفواتير بناء على طلبات شراء من العملاء . | AB55: 3 | AF55: A.7 | AG55: مرحلة قبول العميل | AH55: الاستفسار | AI55: حقائق معينة
A56: الخامس | B56: =B55 -> ع | C56: =C55 -> ع2 | D56: =D55 -> ع2-1 | E56: =E55 -> ع2-1-4 | F56: ع2-1-4-2 | G56: هل لا يسمح بخروج البضاعة الا بموجب سند اخراج بضاعة صادر من المبيعات مرفق صورة المبيعات المعتمدة | AB56: 3 | AF56: A.7 | AH56: الاستفسار | AI56: حقائق معينة
A57: الخامس | B57: =B56 -> ع | C57: =C56 -> ع2 | D57: =D56 -> ع2-1 | E57: =E56 -> ع2-1-4 | F57: ع2-1-4-3 | G57: هل يتم الفصل بين من يقوم باعتماد فاتورة المبيعات ومن يقوم بتسليم البضاعة ومن يقوم بتسجيل البيع محاسبيا | AB57: 3 | AF57: A.7 | AH57: الاستفسار | AI57: حقائق معينة
A58: الخامس | B58: =B57 -> ع | C58: =C57 -> ع2 | D58: =D57 -> ع2-1 | E58: =E57 -> ع2-1-4 | F58: ع2-1-4-4 | G58: هل يتم فحص المرتجعات وهل هي بحالة جيدة في الحدود المسموح بها | AB58: 3 | AF58: A.7 | AH58: الاستفسار | AI58: حقائق معينة
A59: الخامس | B59: =B58 -> ع | C59: =C58 -> ع2 | D59: =D58 -> ع2-1 | E59: =E58 -> ع2-1-4 | F59: ع2-1-4-5 | G59: هل يتم مراجعة اعمار الديون للعملاء وتكوين مخصص ديون مشكوك فيها مناسب . | AB59: 3 | AF59: A.7 | AH59: الاستفسار | AI59: حقائق معينة
A60: الخامس | B60: =B59 -> ع | C60: =C59 -> ع2 | D60: =D59 -> ع2-1 | E60: =E59 -> ع2-1-4 | F60: ع2-1-4-6 | G60: هل يتم الزام المندوبين والمحصلين بتحصيل الديون من العملاء . | AB60: 3 | AF60: A.7 | AG60: مرحلة قبول العميل | AH60: الاستفسار | AI60: حقائق معينة
A61: الخامس | B61: =B60 -> ع | C61: =C60 -> ع2 | D61: =D60 -> ع2-1 | E61: =E60 -> ع2-1-4 | F61: ع2-1-4-7 | G61: هل يتم عمل عقود مع كبار العملاء لتحديد الحد الاعلى للمبيعات ومدة السداد . | AB61: 3 | AF61: A.7 | AG61: مرحلة قبول العميل | AH61: الاستفسار | AI61: حقائق معينة
B62: =B61 -> ع | C62: =C61 -> ع2 | D62: =D61 -> ع2-1 | E62: =E61 -> ع2-1-4 | AF62: A.7 | AH62: الاستفسار | AI62: حقائق معينة
A63: الرابع | B63: =B62 -> ع | C63: =C62 -> ع2 | D63: =D62 -> ع2-1 | E63: ع2-1-5 | F63: ع2-1-5 | G63: تقييم الرقابة للموجودات الثابتة | AB63: نعم=3/لا=1/لا ينطبق=2 | AF63: A.7.05 | AG63: مرحلة تقييم الرقابة الداخلية | AH63: الاستفسار | AI63: حقائق معينة
A64: الخامس | B64: =B63 -> ع | C64: =C63 -> ع2 | D64: =D63 -> ع2-1 | E64: =E63 -> ع2-1-5 | F64: ع2-1-5-1 | G64: هل تحتفظ المنشأة بسجل للموجودات الثابنة | AB64: 3 | AF64: A.7 | AG64: مرحلة قبول العميل | AH64: الاستفسار | AI64: حقائق معينة
A65: الخامس | B65: =B64 -> ع | C65: =C64 -> ع2 | D65: =D64 -> ع2-1 | E65: =E64 -> ع2-1-5 | F65: ع2-1-5-2 | G65: هل تسجل الاصول بتاريخ الشراء وتاريخ العمل | AB65: 3 | AF65: A.7 | AH65: الاستفسار | AI65: حقائق معينة
A66: الخامس | B66: =B65 -> ع | C66: =C65 -> ع2 | D66: =D65 -> ع2-1 | E66: =E65 -> ع2-1-5 | F66: ع2-1-5-3 | G66: هل يتم ترقيم الموجدودات الثابتة | AB66: 3 | AF66: A.7 | AH66: الاستفسار | AI66: حقائق معينة
A67: الخامس | B67: =B66 -> ع | C67: =C66 -> ع2 | D67: =D66 -> ع2-1 | E67: =E66 -> ع2-1-5 | F67: ع2-1-5-4 | G67: هل توجد سياسة لرسملة المصروفات. | AB67: 3 | AF67: A.7 | AH67: الاستفسار | AI67: حقائق معينة
A68: الخامس | B68: =B67 -> ع | C68: =C67 -> ع2 | D68: =D67 -> ع2-1 | E68: =E67 -> ع2-1-5 | F68: ع2-1-5-5 | G68: هل يتم اضافة الاصول المشتراة لسجل الاصول. | AB68: 3 | AF68: A.7 | AH68: الاستفسار | AI68: حقائق معينة
A69: الخامس | B69: =B68 -> ع | C69: =C68 -> ع2 | D69: =D68 -> ع2-1 | E69: =E68 -> ع2-1-5 | F69: ع2-1-5-6 | G69: هل يتم استبعاد الاصول بناء على موافقة واعتماد الادارة . | AB69: 3 | AF69: A.7 | AH69: الاستفسار | AI69: حقائق معينة
B70: =B69 -> ع | C70: =C69 -> ع2 | D70: =D69 -> ع2-1 | E70: =E69 -> ع2-1-5 | AF70: A.7 | AH70: الاستفسار | AI70: حقائق معينة
A71: الرابع | B71: =B70 -> ع | C71: =C70 -> ع2 | D71: =D70 -> ع2-1 | E71: ع2-1-6 | F71: ع2-1-6 | G71: الرقابة الداخلية للرواتب والأجور | AB71: نعم=3/لا=1/لا ينطبق=2 | AF71: A.7.06 | AG71: مرحلة تقييم الرقابة الداخلية | AH71: الاستفسار | AI71: حقائق معينة
A72: الخامس | B72: =B71 -> ع | C72: =C71 -> ع2 | D72: =D71 -> ع2-1 | E72: =E71 -> ع2-1-6 | F72: ع2-1-6-1 | G72: هل توجد لوائح ثابتة للرواتب | AB72: 3 | AF72: A.7 | AH72: الاستفسار | AI72: حقائق معينة
A73: الخامس | B73: =B72 -> ع | C73: =C72 -> ع2 | D73: =D72 -> ع2-1 | E73: =E72 -> ع2-1-6 | F73: ع2-1-6-2 | G73: هل يتم عمل عقود للعمال والموظفين | AB73: 3 | AF73: A.7 | AH73: الاستفسار | AI73: حقائق معينة
A74: الخامس | B74: =B73 -> ع | C74: =C73 -> ع2 | D74: =D73 -> ع2-1 | E74: =E73 -> ع2-1-6 | F74: ع2-1-6-3 | G74: هل تعتمد الرواتب من الرؤساء المباشرين والادارة | AB74: 3 | AF74: A.7 | AH74: الاستفسار | AI74: حقائق معينة
A75: الخامس | B75: =B74 -> ع | C75: =C74 -> ع2 | D75: =D74 -> ع2-1 | E75: =E74 -> ع2-1-6 | F75: ع2-1-6-4 | G75: هل توجد سياسة ثابتة لمنح الموظفين والعمال السلف | AB75: 3 | AF75: A.7 | AH75: الاستفسار | AI75: حقائق معينة
B76: =B75 -> ع | C76: =C75 -> ع2 | D76: =D75 -> ع2-1 | E76: =E75 -> ع2-1-6 | AF76: A.7 | AH76: الاستفسار | AI76: حقائق معينة
B77: =B76 -> ع | C77: =C76 -> ع2 | D77: =D76 -> ع2-1 | E77: =E76 -> ع2-1-6 | AF77: A.7 | AH77: الاستفسار | AI77: حقائق معينة
A78: الثالث | B78: =B77 -> ع | C78: =C77 -> ع2 | D78: ع2-2 | E78: ع2-2 | F78: ع2-2 | G78: قائمة الاستقصاء | AF78: 1.2.2 | AH78: الاستفسار | AI78: حقائق معينة | AJ78: 1
A79: الرابع | B79: =B78 -> ع | C79: =C78 -> ع2 | D79: =D78 -> ع2-2 | E79: ع2-2-1 | F79: ع2-2-1 | G79: معرفة المنشأة وتوثيق الفهم | AB79: نعم=3/لا=1/لا ينطبق=2 | AF79: A.4.01 | AG79: مرحلة قبول العميل | AH79: الاستفسار | AI79: حقائق معينة
A80: الخامس | B80: =B79 -> ع | C80: =C79 -> ع2 | D80: =D79 -> ع2-2 | E80: =E79 -> ع2-2-1 | F80: ع2-2-1-1 | G80: هل أجري تعديل على عقد التأسيس خلال العام ؟ (في حالة الشركات) | AB80: 1 | AF80: A.4 | AH80: الاستفسار | AI80: حقائق معينة
A81: الخامس | B81: =B80 -> ع | C81: =C80 -> ع2 | D81: =D80 -> ع2-2 | E81: =E80 -> ع2-2-1 | F81: ع2-2-1-2 | G81: هل تم الانتهاء من الإجراءات النظامية المتعلقة بهذا التعديل ؟ ((ترفق صور الوثائق المتعلقة بذلك )) | AB81: 2 | AF81: A.4 | AH81: الاستفسار | AI81: حقائق معينة
A82: الخامس | B82: =B81 -> ع | C82: =C81 -> ع2 | D82: =D81 -> ع2-2 | E82: =E81 -> ع2-2-1 | F82: ع2-2-1-3 | G82: هل قامت المنشأة بفتح فروع جديدة أو إضافة أنشطة جديدة خلال العام ؟ | AB82: 1 | AF82: A.4 | AG82: مرحلة قبول العميل | AH82: الاستفسار | AI82: حقائق معينة
A83: الخامس | B83: =B82 -> ع | C83: =C82 -> ع2 | D83: =D82 -> ع2-2 | E83: =E82 -> ع2-2-1 | F83: ع2-2-1-4 | G83: هل تم توضيح فروع المنشأة بالسياسات في القوائم ؟ | AB83: 2 | AF83: A.4 | AG83: مرحلة قبول العميل | AH83: الاستفسار | AI83: حقائق معينة
A84: الخامس | B84: =B83 -> ع | C84: =C83 -> ع2 | D84: =D83 -> ع2-2 | E84: =E83 -> ع2-2-1 | F84: ع2-2-1-5 | G84: هل تم توضيح الموقف الزكوي بايضاحات القوائم المالية | AB84: 3 | AF84: A.4 | AH84: الاستفسار | AI84: حقائق معينة
A85: الخامس | B85: =B84 -> ع | C85: =C84 -> ع2 | D85: =D84 -> ع2-2 | E85: =E84 -> ع2-2-1 | F85: ع2-2-1-6 | G85: هل هناك قضايا لا زالت معلقة مع المصلحة ؟ | AB85: 1 | AF85: A.4 | AH85: الاستفسار | AI85: حقائق معينة
A86: الخامس | B86: =B85 -> ع | C86: =C85 -> ع2 | D86: =D85 -> ع2-2 | E86: =E85 -> ع2-2-1 | F86: ع2-2-1-7 | G86: هل تم تجديد التراخيص الممنوحة للمنشأة لمزاولة نشاطها ؟ (( ترفق صورة التراخيص )) | AB86: 3 | AF86: A.4 | AG86: مرحلة قبول العميل | AH86: الاستفسار | AI86: حقائق معينة
A87: الخامس | B87: =B86 -> ع | C87: =C86 -> ع2 | D87: =D86 -> ع2-2 | E87: =E86 -> ع2-2-1 | F87: ع2-2-1-8 | G87: هل تم تجديد السجلات التجارية ؟ (( ترفق صورة التراخيص )) | AB87: 3 | AF87: A.4 | AH87: الاستفسار | AI87: حقائق معينة
A88: الخامس | B88: =B87 -> ع | C88: =C87 -> ع2 | D88: =D87 -> ع2-2 | E88: =E87 -> ع2-2-1 | F88: ع2-2-1-9 | G88: هل عقد مجلس الإدارة أو الجمعية العمومية اجتماعات خلال العام ؟ (في حالة الشركات) ((ترفق صور محاضر الاجتماعات )) | AB88: 33 | AF88: A.4 | AH88: الاستفسار | AI88: حقائق معينة
A89: الخامس | B89: =B88 -> ع | C89: =C88 -> ع2 | D89: =D88 -> ع2-2 | E89: =E88 -> ع2-2-1 | F89: ع2-2-1-10 | G89: هل توجد قضايا قائمة مرفوعة من قبل المنشأة أو ضدها ؟ تذكر مبالغ المطالبات والموقف في نهاية العام | AB89: 3 | AF89: A.4 | AG89: مرحلة قبول العميل | AH89: الاستفسار | AI89: حقائق معينة
A90: الخامس | B90: =B89 -> ع | C90: =C89 -> ع2 | D90: =D89 -> ع2-2 | E90: =E89 -> ع2-2-1 | F90: ع2-2-1-11 | G90: هل حصل خلال العام أية معاملات يمكن أن تؤثر بشكل مادي على المركز المالي للمنشأة ولم تنعكس بعد على حساباتها ؟ | AB90: 3 | AF90: A.4 | AG90: مرحلة قبول العميل | AH90: الاستفسار | AI90: حقائق معينة
A91: الخامس | B91: =B90 -> ع | C91: =C90 -> ع2 | D91: =D90 -> ع2-2 | E91: =E90 -> ع2-2-1 | F91: ع2-2-1-12 | G91: هل جميع الموجودات التي تخص المنشأة مسجلة في الدفاتر المحاسبية وفقا لأصول المحاسبة المتعارف عليها ؟ | AB91: 3 | AF91: A.4 | AG91: مرحلة قبول العميل | AH91: الاستفسار | AI91: حقائق معينة
A92: الخامس | B92: =B91 -> ع | C92: =C91 -> ع2 | D92: =D91 -> ع2-2 | E92: =E91 -> ع2-2-1 | F92: ع2-2-1-13 | G92: هل جرى أية تعديلات على السياسات المحاسبية التي اتبعتها المنشأة خلال العام المالي السابق ؟ (( تذكر التعديلات ومبرراتها (إن وجدت) )) | AB92: 3 | AF92: A.4 | AG92: مرحلة قبول العميل | AH92: الاستفسار | AI92: حقائق معينة
A93: الخامس | B93: =B92 -> ع | C93: =C92 -> ع2 | D93: =D92 -> ع2-2 | E93: =E92 -> ع2-2-1 | F93: ع2-2-1-14 | G93: هل يوجد أي رهنيات أو حجوزات على موجودات المنشأة ؟ | AB93: 3 | AF93: A.4 | AG93: مرحلة قبول العميل | AH93: الاستفسار | AI93: حقائق معينة
A94: الخامس | B94: =B93 -> ع | C94: =C93 -> ع2 | D94: =D93 -> ع2-2 | E94: =E93 -> ع2-2-1 | F94: ع2-2-1-15 | G94: هل تم تكوين المخصصات الكافية لمقابلة الالتزامات المحتملة الحدوث ؟ | AB94: 3 | AF94: A.4 | AH94: الاستفسار | AI94: حقائق معينة
A95: الخامس | B95: =B94 -> ع | C95: =C94 -> ع2 | D95: =D94 -> ع2-2 | E95: =E94 -> ع2-2-1 | F95: ع2-2-1-16 | G95: هل تم اصدار وارسال خطاب المحاسب السابق ؟ | AB95: 3 | AF95: A.4 | AH95: الاستفسار | AI95: حقائق معينة
B96: =B95 -> ع | C96: =C95 -> ع2 | D96: =D95 -> ع2-2 | E96: =E95 -> ع2-2-1 | AF96: A.4 | AH96: الاستفسار | AI96: حقائق معينة
B97: =B96 -> ع | C97: =C96 -> ع2 | D97: =D96 -> ع2-2 | E97: =E96 -> ع2-2-1 | AF97: A.4 | AH97: الاستفسار | AI97: حقائق معينة
A98: الثالث | B98: =B97 -> ع | C98: =C97 -> ع2 | D98: ع2-3 | E98: ع2-3 | F98: ع2-3 | G98: قائمة إستبيان مكافحة غسيل الاموال | AF98: 1.2.3 | AH98: الاستفسار | AI98: حقائق معينة | AJ98: 1
A99: الرابع | B99: =B98 -> ع | C99: =C98 -> ع2 | D99: =D98 -> ع2-3 | E99: ع2-3-1 | F99: ع2-3-1 | G99: توثيق الفهم بنموذج غسيل الأموال | AB99: نعم=3/لا=1/لا ينطبق=2 | AF99: A.7.07 | AH99: الاستفسار | AI99: حقائق معينة
A100: الخامس | B100: =B99 -> ع | C100: =C99 -> ع2 | D100: =D99 -> ع2-3 | E100: =E99 -> ع2-3-1 | F100: ع2-3-1-1 | G100: هل تلتزم المنشأة بالتعليمات والقوانين الصادرة عن وزارة التجارة فيما يخص مكافحة غسل الاموال وتمويل الإرهاب؟ | AB100: 3 | AF100: A.7 | AG100: مرحلة قبول العميل | AH100: الاستفسار | AI100: حقائق معينة
...

Sheet Sheet6

Sheet Sheet2
A1: المستوى | B1: فاصل | C1: 1 | D1: 2 | E1: 3 | F1: 4 | G1: 5 | H1: بيان
A2: 0 | D2: الرجاء كتابة الدليل المرفق هنا | E2: فاصل | I2: ورقة عمل رقم | J2: فهرس الملــــــــــــــــــــــــــــــــــــف
A3: 0 | E3: 1 | F3: 2 | G3: 3 | H3: 4 | J3: بيان
A4: 1 | B4: ع | C4: ع | D4: ع | E4: ع | F4: ع | G4: ملف عموميات
A5: 2 | B5: ع | C5: ع1 | D5: ع1 | E5: ع1 | F5: ع1 | G5: الملف الدائم (مرحلة استكمال المتطلبات الأساسية
A6: 3 | B6: ع | C6: ع1 | D6: ع1-1 | E6: ع1-1 | F6: ع1-1 | G6: المستندات من المنشأة
A7: 4 | B7: ع | C7: ع1 | D7: ع1-1 | E7: ع1-1-1 | F7: ع1-1-1 | G7: صورمن المستندات الرسمية الرسمية للمنشأة
A8: 5 | B8: ع | C8: ع1 | D8: ع1-1 | F8: ع1-1-1-1 | G8: السجل التجــــــــــــــــــــــــــــاري وفروع السجل التجاري
A9: 5 | B9: ع | C9: ع1 | D9: ع1-1 | F9: ع1-1-1-2 | G9: عقد تأسيس المنشأة وتعديلاتة وصور من محاضر اجتماعات مجلس الإدارة
A10: 5 | B10: ع | C10: ع1 | D10: ع1-1 | F10: ع1-1-1-3 | G10: ترخيص المزاولة مختـــــــــــــــــــــــــــــــــــــــــــــــوم
A11: 5 | B11: ع | C11: ع1 | D11: ع1-1 | F11: ع1-1-1-4 | G11: صور هويات الشركاء / صاحب المنشأة
A12: 5 | B12: ع | C12: ع1 | D12: ع1-1 | F12: ع1-1-1-5 | G12: صورة آخر شهادة زكاة شرعية (شركة / مؤسســـــــة)
A13: 5 | B13: ع | C13: ع1 | D13: ع1-1 | F13: ع1-1-1-6 | G13: شهادة التامينات باجمالى الرواتب قيمة وعــــــــــــــدد
A14: 5 | B14: ع | C14: ع1 | D14: ع1-1 | F14: ع1-1-1-7 | G14: بيان الاستيراد من الجمارك (في حالة وجود استيراد من الخارج)
A15: 5 | B15: ع | C15: ع1 | D15: ع1-1 | F15: ع1-1-1-8 | G15: خلفية عن نشاط المنشأة وفروعـــــــــــــــــــــــــــــــــه
A16: 5 | B16: ع | C16: ع1 | D16: ع1-1 | F16: ع1-1-1-9 | G16: تفويض برفع القوائم المالية عبر الموقع الالكترونى بوزارة التجارة
A17: 5 | B17: ع | C17: ع1 | D17: ع1-1 | F17: ع1-1-1-10 | G17: خطاب عدم مزاولة النشـــــــــــــــــــــــــــــــــــــــــاط ان كانت لم تمارس النشاط
A18: 3 | B18: ع | C18: ع1 | D18: ع1-1
A19: 3 | B19: ع | C19: ع1 | D19: ع1-1
A20: 3 | B20: ع | C20: ع1 | D20: ع1-1
A21: 2 | B21: ع | C21: ع2 | D21: ع2 | E21: ع2 | F21: ع2 | G21: قوائم الاستبيان والاستقصاء والتقييم والاختبار (المرحلة الاولي لقبول المنشأة والموافقة على الارتباط)
A22: 3 | B22: ع | C22: ع2 | D22: ع2-1 | E22: ع2-1 | F22: ع2-1 | G22: قوائم استبيان الرقابة الداخلية
A23: 4 | B23: ع | C23: ع2 | D23: ع2-1 | E23: ع2-1-1 | F23: ع2-1-1 | G23: تقييم الجهاز التنظيمي والمحاسبة العامة
A24: 5 | B24: ع | C24: ع2 | D24: ع2-1 | E24: ع2-1-1 | F24: ع2-1-1-1 | G24: هل يوجد رسما للهيكل التنظيمي للمنشأة
A25: 5 | B25: ع | C25: ع2 | D25: ع2-1 | E25: ع2-1-1 | F25: ع2-1-1-2 | G25: هل لدى المنشأة لوائح معتمدة بالسياسات والاجراءات المحاسبية
A26: 5 | B26: ع | C26: ع2 | D26: ع2-1 | E26: ع2-1-1 | F26: ع2-1-1-3 | G26: هل يوجد وصف للوظائف ولوائح للقائمين عليها حتى لاتتم الازدواجية في العمل .
A27: 5 | B27: ع | C27: ع2 | D27: ع2-1 | E27: ع2-1-1 | F27: ع2-1-1-4 | G27: هل ترفع تقارير دورية للادارة .
A28: 5 | B28: ع | C28: ع2 | D28: ع2-1 | E28: ع2-1-1 | F28: ع2-1-1-5 | G28: هل يجري التحري عن المسؤولين عن النقد قبل ترشيحهم ويتم التأمين عليهم ضد سوء الامانة والنقد في الطريق
A29: 5 | B29: ع | C29: ع2 | D29: ع2-1 | E29: ع2-1-1 | F29: ع2-1-1-6 | G29: هل من يقوم بتحرير سندات الصرف اشخاص غير امين الخزينة .
A30: 5 | B30: ع | C30: ع2 | D30: ع2-1 | E30: ع2-1-1 | F30: ع2-1-1-7 | G30: هل يتم حفظ دفاتر الشيكات والدفاتر المحاسبية في مكان امن .
A31: 5 | B31: ع | C31: ع2 | D31: ع2-1 | E31: ع2-1-1 | F31: ع2-1-1-8 | G31: هل يوجد شخص يقوم بمراجعة قيود التسوية غير الشخص الذي يقوم باعدادها .
A32: 4 | B32: ع | C32: ع2 | D32: ع2-1 | E32: ع2-1-1
A33: 4 | B33: ع | C33: ع2 | D33: ع2-1 | E33: ع2-1-2 | F33: ع2-1-2 | G33: الرقابة الداخلية على إدارة المقبوضات والمدفوعات
A34: 5 | B34: ع | C34: ع2 | D34: ع2-1 | E34: ع2-1-2 | F34: ع2-1-2-1 | G34: هل يتم تدريب امناء الصندوق والعهد
A35: 5 | B35: ع | C35: ع2 | D35: ع2-1 | E35: ع2-1-2 | F35: ع2-1-2-2 | G35: هل سندات الصرف والقبض مرقمة ويتم مراجعة التسلسل
A36: 5 | B36: ع | C36: ع2 | D36: ع2-1 | E36: ع2-1-2 | F36: ع2-1-2-3 | G36: هل يتم مراجعة مرفقات سندات الصرف والقبض قبل اعتمادها
A37: 5 | B37: ع | C37: ع2 | D37: ع2-1 | E37: ع2-1-2 | F37: ع2-1-2-4 | G37: هل يتم التحقق من المستلم قبل تسليمه الشيكات او النقدية
A38: 4 | B38: ع | C38: ع2 | D38: ع2-1 | E38: ع2-1-2
A39: 4 | B39: ع | C39: ع2 | D39: ع2-1 | E39: ع2-1-3 | F39: ع2-1-3 | G39: النقدية بالصندوق
A40: 5 | B40: ع | C40: ع2 | D40: ع2-1 | E40: ع2-1-3 | F40: ع2-1-3-1 | G40: هل يتم الفصل بين معتمد الصرف وامين الخزينة والقائم بتسجيل الصرف
A41: 5 | B41: ع | C41: ع2 | D41: ع2-1 | E41: ع2-1-3 | F41: ع2-1-3-2 | G41: هل يتم التأمين على أمين الخزينة .
A42: 5 | B42: ع | C42: ع2 | D42: ع2-1 | E42: ع2-1-3 | F42: ع2-1-3-3 | G42: هل للمنشأة سياسة محاسبية تبلغ بها الادارة المالية وهل السجلات مقصور الاطلاع عليها على الادارة المالية .
A43: 5 | B43: ع | C43: ع2 | D43: ع2-1 | E43: ع2-1-3 | F43: ع2-1-3-4 | G43: هل يتم جرد الخزينة جردا فجائياً
A44: 5 | B44: ع | C44: ع2 | D44: ع2-1 | E44: ع2-1-3 | F44: ع2-1-3-5 | G44: هل تشمل القيود اليومية وسندات الصرف والقبض كافة معاملات المنشأة المالية .
A45: 5 | B45: ع | C45: ع2 | D45: ع2-1 | E45: ع2-1-3 | F45: ع2-1-3-6 | G45: هل تتضمن القوائم المالية قائمة التدفقات النقدية .
A46: 5 | B46: ع | C46: ع2 | D46: ع2-1 | E46: ع2-1-3 | F46: ع2-1-3-7 | G46: هل يتم مراجعة مرفقات استعاضة السلفة من قبل الادارة المالية قبل صرف الاستعاضة .
A47: 5 | B47: ع | C47: ع2 | D47: ع2-1 | E47: ع2-1-3 | F47: ع2-1-3-8 | G47: هل تحتفظ الخزينة بصور سندات الصرف والقبض وكعوب الشيكات وهل يتم جردها بصفة دورية .
A48: 5 | B48: ع | C48: ع2 | D48: ع2-1 | E48: ع2-1-3 | F48: ع2-1-3-9 | G48: هل يتم الاحتفاظ بدفاتر الشيكات غير المستعملة وكعوب الشيكات المستعملة منها بالخزينة .
A49: 4 | B49: ع | C49: ع2 | D49: ع2-1 | E49: ع2-1-3
A50: 4 | B50: ع | C50: ع2 | D50: ع2-1 | E50: ع2-1-4 | F50: ع2-1-4 | G50: الرقابة على المبيعات / الإيرادات والمديونية
A51: 5 | B51: ع | C51: ع2 | D51: ع2-1 | E51: ع2-1-4 | F51: ع2-1-4-1 | G51: هل يتم تحرير الفواتير بناء على طلبات شراء من العملاء .
A52: 5 | B52: ع | C52: ع2 | D52: ع2-1 | E52: ع2-1-4 | F52: ع2-1-4-2 | G52: هل لا يسمح بخروج البضاعة الا بموجب سند اخراج بضاعة صادر من المبيعات مرفق صورة المبيعات المعتمدة
A53: 5 | B53: ع | C53: ع2 | D53: ع2-1 | E53: ع2-1-4 | F53: ع2-1-4-3 | G53: هل يتم الفصل بين من يقوم باعتماد فاتورة المبيعات ومن يقوم بتسليم البضاعة ومن يقوم بتسجيل البيع محاسبيا
A54: 5 | B54: ع | C54: ع2 | D54: ع2-1 | E54: ع2-1-4 | F54: ع2-1-4-4 | G54: هل يتم فحص المرتجعات وهل هي بحالة جيدة في الحدود المسموح بها
A55: 5 | B55: ع | C55: ع2 | D55: ع2-1 | E55: ع2-1-4 | F55: ع2-1-4-5 | G55: هل يتم مراجعة اعمار الديون للعملاء وتكوين مخصص ديون مشكوك فيها مناسب .
A56: 5 | B56: ع | C56: ع2 | D56: ع2-1 | E56: ع2-1-4 | F56: ع2-1-4-6 | G56: هل يتم الزام المندوبين والمحصلين بتحصيل الديون من العملاء .
A57: 5 | B57: ع | C57: ع2 | D57: ع2-1 | E57: ع2-1-4 | F57: ع2-1-4-7 | G57: هل يتم عمل عقود مع كبار العملاء لتحديد الحد الاعلى للمبيعات ومدة السداد .
A58: 4 | B58: ع | C58: ع2 | D58: ع2-1 | E58: ع2-1-4
A59: 4 | B59: ع | C59: ع2 | D59: ع2-1 | E59: ع2-1-5 | F59: ع2-1-5 | G59: تقييم الرقابة للموجودات الثابتة
A60: 5 | B60: ع | C60: ع2 | D60: ع2-1 | E60: ع2-1-5 | F60: ع2-1-5-1 | G60: هل تحتفظ المنشأة بسجل للموجودات الثابنة
A61: 5 | B61: ع | C61: ع2 | D61: ع2-1 | E61: ع2-1-5 | F61: ع2-1-5-2 | G61: هل تسجل الاصول بتاريخ الشراء وتاريخ العمل
A62: 5 | B62: ع | C62: ع2 | D62: ع2-1 | E62: ع2-1-5 | F62: ع2-1-5-3 | G62: هل يتم ترقيم الموجدودات الثابتة
A63: 5 | B63: ع | C63: ع2 | D63: ع2-1 | E63: ع2-1-5 | F63: ع2-1-5-4 | G63: هل توجد سياسة لرسملة المصروفات.
A64: 5 | B64: ع | C64: ع2 | D64: ع2-1 | E64: ع2-1-5 | F64: ع2-1-5-5 | G64: هل يتم اضافة الاصول المشتراة لسجل الاصول.
A65: 5 | B65: ع | C65: ع2 | D65: ع2-1 | E65: ع2-1-5 | F65: ع2-1-5-6 | G65: هل يتم استبعاد الاصول بناء على موافقة واعتماد الادارة .
A66: 4 | B66: ع | C66: ع2 | D66: ع2-1 | E66: ع2-1-5
A67: 4 | B67: ع | C67: ع2 | D67: ع2-1 | E67: ع2-1-6 | F67: ع2-1-6 | G67: الرقابة الداخلية للرواتب والأجور
A68: 5 | B68: ع | C68: ع2 | D68: ع2-1 | E68: ع2-1-6 | F68: ع2-1-6-1 | G68: هل توجد لوائح ثابتة للرواتب
A69: 5 | B69: ع | C69: ع2 | D69: ع2-1 | E69: ع2-1-6 | F69: ع2-1-6-2 | G69: هل يتم عمل عقود للعمال والموظفين
A70: 5 | B70: ع | C70: ع2 | D70: ع2-1 | E70: ع2-1-6 | F70: ع2-1-6-3 | G70: هل تعتمد الرواتب من الرؤساء المباشرين والادارة
A71: 5 | B71: ع | C71: ع2 | D71: ع2-1 | E71: ع2-1-6 | F71: ع2-1-6-4 | G71: هل توجد سياسة ثابتة لمنح الموظفين والعمال السلف
A72: 4 | B72: ع | C72: ع2 | D72: ع2-1 | E72: ع2-1-6
A73: 4 | B73: ع | C73: ع2 | D73: ع2-1 | E73: ع2-1-6
A74: 3 | B74: ع | C74: ع2 | D74: ع2-2 | E74: ع2-2 | F74: ع2-2 | G74: قائمة الاستقصاء
A75: 4 | B75: ع | C75: ع2 | D75: ع2-2 | E75: ع2-2-1 | F75: ع2-2-1 | G75: معرفة المنشأة وتوثيق الفهم
A76: 5 | B76: ع | C76: ع2 | D76: ع2-2 | E76: ع2-2-1 | F76: ع2-2-1-1 | G76: هل أجري تعديل على عقد التأسيس خلال العام ؟ (في حالة الشركات)
A77: 5 | B77: ع | C77: ع2 | D77: ع2-2 | E77: ع2-2-1 | F77: ع2-2-1-2 | G77: هل تم الانتهاء من الإجراءات النظامية المتعلقة بهذا التعديل ؟ ((ترفق صور الوثائق المتعلقة بذلك ))
A78: 5 | B78: ع | C78: ع2 | D78: ع2-2 | E78: ع2-2-1 | F78: ع2-2-1-3 | G78: هل قامت المنشأة بفتح فروع جديدة أو إضافة أنشطة جديدة خلال العام ؟
A79: 5 | B79: ع | C79: ع2 | D79: ع2-2 | E79: ع2-2-1 | F79: ع2-2-1-4 | G79: هل تم توضيح فروع المنشأة بالسياسات في القوائم ؟
A80: 5 | B80: ع | C80: ع2 | D80: ع2-2 | E80: ع2-2-1 | F80: ع2-2-1-5 | G80: هل تم توضيح الموقف الزكوي بايضاحات القوائم المالية
A81: 5 | B81: ع | C81: ع2 | D81: ع2-2 | E81: ع2-2-1 | F81: ع2-2-1-6 | G81: هل هناك قضايا لا زالت معلقة مع المصلحة ؟
A82: 5 | B82: ع | C82: ع2 | D82: ع2-2 | E82: ع2-2-1 | F82: ع2-2-1-7 | G82: هل تم تجديد التراخيص الممنوحة للمنشأة لمزاولة نشاطها ؟ (( ترفق صورة التراخيص ))
A83: 5 | B83: ع | C83: ع2 | D83: ع2-2 | E83: ع2-2-1 | F83: ع2-2-1-8 | G83: هل تم تجديد السجلات التجارية ؟ (( ترفق صورة التراخيص ))
A84: 5 | B84: ع | C84: ع2 | D84: ع2-2 | E84: ع2-2-1 | F84: ع2-2-1-9 | G84: هل عقد مجلس الإدارة أو الجمعية العمومية اجتماعات خلال العام ؟ (في حالة الشركات) ((ترفق صور محاضر الاجتماعات ))
A85: 5 | B85: ع | C85: ع2 | D85: ع2-2 | E85: ع2-2-1 | F85: ع2-2-1-10 | G85: هل توجد قضايا قائمة مرفوعة من قبل المنشأة أو ضدها ؟ تذكر مبالغ المطالبات والموقف في نهاية العام
... A91: 5 | B91: ع | C91: ع2 | D91: ع2-2 | E91: ع2-2-1 | F91: ع2-2-1-16 | G91: هل تم اصدار وارسال خطاب المحاسب السابق ؟
A92: 4 | B92: ع | C92: ع2 | D92: ع2-2 | E92: ع2-2-1
A93: 4 | B93: ع | C93: ع2 | D93: ع2-2 | E93: ع2-2-1
A94: 3 | B94: ع | C94: ع2 | D94: ع2-3 | E94: ع2-3 | F94: ع2-3 | G94: قائمة إستبيان مكافحة غسيل الاموال
A95: 4 | B95: ع | C95: ع2 | D95: ع2-3 | E95: ع2-3-1 | F95: ع2-3-1 | G95: توثيق الفهم بنموذج غسيل الأموال
A96: 5 | B96: ع | C96: ع2 | D96: ع2-3 | E96: ع2-3-1 | F96: ع2-3-1-1 | G96: هل تلتزم المنشأة بالتعليمات والقوانين الصادرة عن وزارة التجارة فيما يخص مكافحة غسل الاموال وتمويل الإرهاب؟
A97: 5 | B97: ع | C97: ع2 | D97: ع2-3 | E97: ع2-3-1 | F97: ع2-3-1-2 | G97: هل تتعامل المنشأة مع شركات الدَمي (شركات أجنبية مستترة) ؟
A98: 5 | B98: ع | C98: ع2 | D98: ع2-3 | E98: ع2-3-1 | F98: ع2-3-1-3 | G98: هل قامت المنشأة بإبرام اتفاقات اقتراض من بنوك أجنبية ؟
A99: 5 | B99: ع | C99: ع2 | D99: ع2-3 | E99: ع2-3-1 | F99: ع2-3-1-4 | G99: هل للمنشأة أية تعاملات في المجوهرات والأحجار الكريمة ذات القيمة العالية ؟
A100: 5 | B100: ع | C100: ع2 | D100: ع2-3 | E100: ع2-3-1 | F100: ع2-3-1-5 | G100: هل للمنشأة أية تعاملات مع مكاتب الصرافة في مجال تحويل العملات بمبالغ كبيرة خارج المملكة ؟
A101: 5 | B101: ع | C101: ع2 | D101: ع2-3 | E101: ع2-3-1 | F101: ع2-3-1-6 | G101: هل توجد عمليات غير اعتيادية لدى المنشأة ؟
A102: 4 | B102: ع | C102: ع2 | D102: ع2-3 | E102: ع2-3-1
A103: 4 | B103: ع | C103: ع2 | D103: ع2-3 | E103: ع2-3-2 | F103: ع2-3-2 | G103: راي المراجع المباشر
A104: 5 | B104: ع | C104: ع2 | D104: ع2-3 | E104: ع2-3-2 | F104: ع2-3-2-1 | G104: الرأي : نظيف ولا يوجد شك لدينا بأمور تجعلنا نتوقع حدوث عمليات غسيل أموال
A105: 4 | B105: ع | C105: ع2 | D105: ع2-3 | E105: ع2-3-2
...

Sheet برنامج الملاك
A1: الأول | M1: وظائف مالك النظام 1
A2: الثاني | M2: 1.1 ادارة الملف الشخصي
B3: اسم التابة | C3: السمات / الوصف | D3: البيانات المدخلة | E3: نوع البيانات المدخلة | F3: البيانات المخرجة | G3: شرط ملء البيان | H3: الوثائق المرفوعة | I3: التحقق والتوثيق | J3: المهام | K3: ملاحظات | L3: ملاحظات إضافية
A4: * | C4: وظيفة تسجيل دخول أدمن ملاك البرنامج | D4: يجب ان يسمح النظام لآدمن الملاك بتسجيل الدخول بشكل آمن باستخدام البريد الالكتروني وكلمة المرور | L4: اول مرة كيف يفتح برنامج الملاك هل سيتم إضافة الايميلات وأرقام الجولات في كود البرنامج ام سيتم إعطاء فرصة عند الدخول اول مرة بكتابة الايميل والرقم السري
A5: الرابع | B5: تسجيل الدخول | C5: دخول المستخدمين الملاك / والمطور / وموظفين الدعم الفني للمطور وموظفين الدعم المهني للمدقق ملاك البرنامج | D5: اسم المستخدم | E5: TEXT | F5: يتم السماح بالدخول علي الموقع | H5: لا يوجد | I5: تسجيل دخول بتحقق ثنائي
A6: الرابع | D6: كلمة المرور | E6: TEXT | K6: في حال تم نسيان او فقدان كلمة المرور يتم إعادة ارسالها مرة اخري في الايميل الخاص بملاك الشركة
A7: الرابع | D7: نسيت كلمة المرور | E7: TEXT + number | K7: مجرد قبول الدخول يتم الانتقال الي واجهة المشترك
A8: الرابع
A9: الثاني | M9: 1.2 اعدادات النظام
A10: الثالث | M10: 1.1.1 وظيفة تسجيل دخول الادمن
A11: * | C11: اعدادات برنامج الملاك (النظام) | D11: يجب ان يتيح نظام المشرف إمكانية تكوين وإدارة إعدادات نظاق النظام وتشمل هذه الاعدادات بيانات يتم قراءتها واختيارها من قائمة منسدلة عند إضافة مشترك
A12: الرابع | B12: إعدادات النظام | C12: اعدادات أساسية لنافذة ملاك البرنامج | D12: قائمة بلاد العالم | E12: قائمة من مواقع الكترونية | F12: كل بلد علي حدة | H12: لا يوجد وثائق مرفقة | I12: لا يوجد تحقق مطلوب | L12: هل سيتم تحديد الدول والمدن والمناطق داخل كود البرنامج حتي يتم قرأئتها اثناء إضافة مشترك ام سيكون هناك إعدادات والأفضل الاولي | M12: فيما يتعلق باعدادات البلد والمدينة والمنطقة والمواقع الوزارية وفي برنامج المشتركين لا يوجد حوجة لوضعها في اعدادات برنامج الملاك لان استعمالها عمليا يكون عند إضافة مشترك وكل مشترك لة بلدة الخاص لذلك اقترح ان تكون في الكود وليس في النوافذ وعند إضافة مشترك توجد الخانة كقائمة منسدلة يتم التحديد ديناميكيا
A13: الرابع | D13: قائمة بمدن العالم | E13: قائمة من مواقع الكترونية | F13: كل مدينة خاصة بالبلد المحددة أعلاه
A14: الرابع | D14: قائمة بمناطق العالم | E14: قائمة من مواقع الكترونية | F14: المناطق المرتبطة بالمدن أعلاه
A15: الرابع | D15: موقع هيئة المحاسبين القانونيين | E15: قائمة من مواقع الكترونية | F15: مواقع الهيئة المرتبطة بالبلد والمدينة أعلاه | K15: يتحدد ليتم اختيارة عند ادخال بيانات المشترك
A16: الرابع | D16: موقع وزارة التجارة | E16: قائمة من مواقع الكترونية | F16: مواقع وزارة التجارة المرتبطة بالبلد أعلاه
A17: الرابع | D17: موقع مصلحة الضرائب والزكاة | E17: قائمة من مواقع الكترونية | F17: مواقع هيئة الزكاة والدخل المرتبطة بالبلد أعلاه
A18: الرابع | D18: مستخدمين الدعم الفني | E18: يتم الإضافة في اعدادات البرنامج | H18: عقد الدعم الفني | I18: لا يوجد تحقق مطلوب | M18: يجب إضافة المستخدمين وعلي أسس علمية وضوابط وهذا للملاك والشركة الدعم الفني ومستخدمين الدعم المهني
A19: الرابع | D19: مستخدمين الدعم المهني | E19: يتم الإضافة في اعدادات البرنامج | H19: عقد الدعم المهني
A20: الرابع | D20: مستخدمين الملاك | E20: يتم الإضافة في اعدادات البرنامج | H20: عقد تأسيس الشركة
A21: الرابع | D21: أنواع الاشتراك | E21: مراجع قانوني / مكتب استشاري / فرد
A22: الثاني | M22: 1.3 إدارة لوحة تحكم المشتركين
A23: الثالث | M23: 1.2.1 إضافة مشترك
A24: * | B24: إضافة مشترك | C24: إضافة مشترك | D24: يجب ان يتيح النظام للمسؤول للمسؤول " احد الملاك " إمكانية إضافة مشترك جديد مع ادخال البيانات الأساسية الكاملة للمشترك والمعلومات القانونية والمالية والتقنية | L24: البيانات المظللة بالتنقيط من نفس اللون يعني التظليل ان تلك البيانات ستنتقل الي نافذة الURLللمشترك ولا يمكن التعديل عليها فقط في نافذة الURL (نافذة المشترك) وتكون للاطلاع فقط وتعديلها يلزم الرجوع الي المالك علي ان يكون نفس التنقيط بيانات يمكن تعديلها في نافذة المشترك
A25: الرابع | C25: معلومات الموقع بيانات الزامية | D25: البلد | E25: TEXT | F25: البلد التي يتم اختيارها | G25: شرط أساسي | H25: العنوان الوطني | I25: لا يوجد تحقق مطلوب | K25: عند تحديد البلد في واجهة إضافة المشترك يجب ان تكون ديناميكية بحيث علي أساس البلد تنحصر المعلومات عند إضافة المشترك بحيث يتم الاختيار من مدن هذه البلد
A26: الرابع | D26: المدينة | E26: TEXT | F26: المدينة التي تم اختيارها | G26: شرط أساسي | H26: العنوان الوطني | I26: لا يوجد تحقق مطلوب | K26: وهكذا عند تحديد المدينة تتلخص القائمة المنسدلة في مناطق تلك المدينة
A27: الرابع | D27: المنطقة | E27: TEXT | F27: المنطقة التي تم اختيارها | G27: شرط أساسي | H27: العنوان الوطني | I27: لايود تحقق مطلوب | K27: وهكذا عند تحديد المنطقة تتلخص القائمة المنسدلة في مناطق تلك المدينة
A28: الرابع | C28: معلومات الترخيص بيانات الزامية | D28: نوع الترخيص | E28: Number | F28: النوع الذي تم اختيارة | G28: شرط أساسي | H28: شهادة الترخيص | I28: يتم التحقق من موقع الهيئة
A29: الرابع | D29: رقم الترخيص | E29: Number | F29: الرقم الذي يتم كتابتة | G29: شرط أساسي
A30: الرابع | D30: تاريخ الترخيص | E30: DATE | F30: التاريخ الذي يتم كتابتة | G30: شرط أساسي | K30: يتوفر الميلادي والهجري
A31: الرابع | D31: اسم الترخيص | E31: TEXT | F31: الاسم حسب ما موضح بالترخيص | G31: شرط أساسي | K31: قد يكون اسم الترخيص طويلا او معقدا لذلك يجب ان تكون هناك آلية لاختيار اسم محدد كاسم العائلة او الاسم التجاري مثال (مكتب مسعود الرفيدي محاسبون ومراجعون قانونيون واستشاريون يمكن اختصارها في اسم الURL الي الرفيدي فقط
A32: الرابع | C32: معلومات الكيان القانوني الزامي | D32: الكيان القانوني للمنشأة | E32: TEXT | F32: شرط | G32: شرط أساسي | H32: عقد التاسيس ان وجد في حالة الشركات و السجل التجاري | I32: يتم التحقق من موقع وزارة التجارة | K32: يتم الاختيار من قائمة منسدلة الكيان القانوني حسب الدولة (شركة/ مؤسسة/الخخخخ)
A33: الرابع | D33: نوع الكيان القانوني | E33: TEXT | F33: شرط | G33: شرط أساسي | K33: يتم الاختيار من قائمة منسدلة نوع الكيان القانوني فردية / شخص واحد / ذات مسؤولية محدودة/ مساهمة عامة / تضامنية / الخخخخخخ
A34: الرابع | D34: جنسية الكيان القانوني | E34: TEXT | F34: شرط | G34: شرط أساسي | K34: يتم الاختيار من قائمة منسدلة ( البلد المحدد أعلاه / مختلطة / اجنبية )
A35: الرابع | D35: اسم صاحب صاحب / أصحاب المنشأة | E35: TEXT | F35: شرط | G35: شرط أساسي
A36: الرابع | D36: رقم السجل التجاري | E36: Number | F36: شرط | G36: شرط أساسي | K36: مثال 1010515969
A37: الرابع | D37: الرقم الضريبي | E37: Number | F37: شرط | G37: شرط أساسي | H37: شهادة التسجيل في القيمة المضافة | I37: يتم التحقق من موقع الزكاة والدخل
A38: الرابع | D38: الرقم الموحد | E38: Number | F38: شرط | G38: شرط أساسي | H38: شهادة الرقم الموحد | K38: 700123456مثال
A39: الرابع | D39: نشاط السجل التجاري | E39: TEXT | F39: شرط | G39: شرط أساسي | H39: ملخص نشاط السجل االتجاي
A40: الرابع | D40: تاريخ السجل التجاري | E40: DATE | F40: شرط | G40: شرط أساسي | H40: لا يوجد | I40: يتم التحقق من موقع وزارة التجارة | K40: يتوفر الميلادي والهجري
A41: الرابع | D41: السنة المالية للمشترك | E41: DATE | F41: شرط | G41: شرط أساسي | H41: لا يوجد | I41: لا يوجد تحقق مطلوب | K41: يتوفر الميلادي والهجري
A42: الرابع | C42: بيانات امنية وإدارية | D42: البريد الالكتروني للمشترك | E42: E.M | F42: شرط | G42: شرط أساسي | H42: لا يوجد | I42: يتم التحقق | K42: لربط الحسابات وارسال التنبيهات او استعادة كلمات المرور وستقبال الرسائل من والي المشترك
A43: الرابع | D43: رقم جوال المشترك الأساسي | E43: Number | F43: شرط | G43: شرط أساسي | H43: لا يوجد | I43: يتم التحقق | K43: للتواصل او التحقق الثنائي
A44: الرابع | D44: حالة المشترك | E44: TEXT | F44: تقرير إضافي | G44: ديناميكي وحسب تاريخ | H44: لايوجد | I44: لايوجد | K44: نشط-غير نشط-موقوف مؤقتا - تحت التجربة
A45: الرابع | D45: تاريخ الاشتراك | E45: DATE | F45: تقرير إضافي | H45: لايوجد | I45: لايوجد | K45: لتتبع وقت التسجيل (المتبقي من الاشتراك / منتهي الاشتراك
A46: الرابع | D46: آخر دخول للنظام | E46: DATE | F46: تقرير إضافي | H46: لايوجد | I46: لايوجد | K46: لمتابعة التفاعل
A47: الرابع | D47: ملاحظات داخلية | E47: TEXT + number | F47: تقرير إضافي | H47: لايوجد | I47: لايوجد | K47: لادخال تعليقات إدارية لا يراها المشترك
A48: الرابع | C48: بيانات الاشتراك والفوترة | D48: نوع الاشتراك | E48: قائمة منسدلة للاختيار منها | F48: تقرير إضافي | H48: لايوجد | I48: لايوجد | K48: تحتوي القائمة المنسدلة علي نوع الاشتراك والمؤسس بواسطة الادمن في الاعدادات علي (مراجع قانوني / مستشار مالي / خدمات محاسبية / الخخخ من الوظائف المالية المتارف عليها
A49: الرابع | D49: تاريخ بداية آخر تجديد للاشتراك | E49: تاريخ هجري وميلادي | F49: تقرير إضافي | H49: لايوجد | I49: لايوجد
A50: الرابع | D50: تاريخ نهاية اخر تجديد للاشتراك | E50: تاريخ هجري وميلادي | F50: تقرير إضافي | H50: لايوجد | I50: لايوجد
A51: الرابع | D51: الباقة المختارة | E51: يجب الاختيار من الباقات المتوفرة بالبرنامج | K51: البرنامج عند تاسيسة جديد اول مرة يعمل لمدة شهر مجانا بعدها يبدء في التوقفحتي يجدد بأحد الباقات المتوفرة وعند انتهاء التجديد يتوقف البرنامج من الادخال ولكن يمكن قراءة ماتم ادخالة من قبل
A52: الرابع | D52: الرسوم المدفوعة | F52: تقرير إضافي | H52: لايوجد | I52: لايوجد
A53: الرابع | D53: طريقة الدفع | F53: تقرير إضافي | H53: لايوجد | I53: لايوجد
A54: الرابع | D54: عدد المستخدمين | F54: تقرير إضافي | H54: لايوجد | I54: لايوجد
A55: الرابع | D55: عدد العملاء (الملفات) | F55: تقرير إضافي | H55: لايوجد | I55: لايوجد
A56: الرابع | C56: بيانات التخصيص الفني | D56: رابط خاص بالمنشأة | F56: رابط المنشأة بعد الاشتراك | H56: لايوجد | I56: لايوجد
A57: الرابع | D57: شعار المنشأة | F57: ايكونة لاضافة شعار المشأة | H57: لايوجد | I57: لايوجد | K57: خانة متوفرة اذا وجد للمشترك شعار
A58: الرابع | D58: اعدادات اللغة | F58: عربي / انجليزي | H58: لايوجد | I58: لايوجد | K58: يجب ان يكون هناك تعدد لللغات
A59: الرابع | D59: اعدادات العملة | F59: عدة عملات | H59: لايوجد | I59: لايوجد | K59: يجب ان يكون هناك تعدد عملات
A60: الثالث | M60: التقارير والمؤشرات 1.3.1
A61: * | B61: تقارير | C61: عرضعقود الارتباط | D61: يجب ان يتيح النظام لصاحب الصلاحية إمكانية عرض قائمة عقود الارتباط لجميع البيانات المدخلة في عققد الارتباط مع خيارات البحث والتصفية في رؤوس الاعمدة وذلك لجميع البيانات المدخلة والتعديل والطباعة والتصدير الي اكسل وPDF
A62: الرابع | C62: مؤشر حالة المشترك | D62: مؤشر يوضح حالة المشترك من بين الحالات التالية (نشط / غير نشط / موقوف مؤقتا / فترة التشغيل المجاني
A63: الرابع | C63: سجل النشاطات | D63: سجل يوم بتسجل كل الحركات ببرنامج الملاك فقط ولا علاقة لة بترصد أي حركة ب URL الخاص بالمشترك
A64: الرابع | C64: الفواتير | D64: جميع الفواتير الصادرة سدادا للاشتراكات بالبرنامج من المشتركين علي ان يكون لكل مشترك كشف حساب بالفواتير المسددة والمستحقة
A65: الرابع
A66: الرابع | B66: مؤشرات | C66: إدارة الأداء والتحكم | D66: عدد الملفات المنشأة | E66: لاتوجد بيانات مدخلة
A67: الرابع | D67: حجم الملفات | E67: لاتوجد بيانات مدخلة
A68: الرابع | D68: عدد المستخدمين | E68: لاتوجد بيانات مدخلة
A69: الرابع | D69: الدعم الفني | E69: تذاكر مفتوحة / مغلقة / قيد الانتظار
A71: الثالث | C71: المتطلبات غير الوظيفية | D71: المتطلبات غير الوظيفية (NFRs) هي التي تضمن ان النظام يعمل من الناحية الوظيفية بكفأة وامان وجودة عالية وتتمثل فيما يلي | M71: المتطلبات غير الوظيفية 1.4.1
A72: الرابع | C72: الأداء (Performance)
A73: الرابع | C73: زمن الاستجابة (Response Time) لأي عملية أساسية يجب ألا يتجاوز 2 ثانية.
A74: الرابع | C74: توليد التقارير الكبيرة (≥ 1000 سجل) يجب أن يتم خلال ≤ 5 ثوانٍ.
A75: الرابع | C75: دعم على الأقل 5000 مستخدم متزامن دون التأثير على الأداء.
A76: الرابع | C76: تحسين استعلامات قاعدة البيانات (Query Optimization).
A77: الرابع | C77: التوافر والاعتمادية (Availability & Reliability)
A78: الرابع | C78: النظام يجب أن يعمل بنسبة توفر Uptime ≥ 99.9%.
A79: الرابع | C79: وجود خطة استمرارية الأعمال (BCP) للتعامل مع الكوارث.
A80: الرابع | C80: النظام يجب أن يكون قادرًا على استعادة العمل خلال ≤ 4 ساعات بعد أي توقف (RTO).
A81: الرابع | C81: البيانات يجب ألا يُفقد منها أكثر من 15 دقيقة عند حدوث عطل (RPO).
A82: الرابع | C82: الأمان (Security)
A83: الرابع | C83: تشفير البيانات في قواعد البيانات باستخدام AES-256.
... A130: الرابع | C130: توثيق لما يحدث عند: فقدان الاتصال بالموقع الرسمي للتحقق، انتهاء صلاحية الترخيص، أو إدخال بيانات غير صحيحة.
C132: عند الانتهاء من إضافة مشترك بنجاح يتم توليد الرابط الخاص بة مع نسخة من كل البيانات الواردة عند إضافة المشترك بالإضافة الي واجهة برنامج مكاتب المراجعة المعروفة باسم المشترك

Sheet برنامج المشترك
A1: الأول | T1: وظائف مالك النظام 1
A2: الثاني | K2: https://www.google.com/ | T2: 1.1 ادارة الملف الشخصي
B3: اسم التابة | C3: السمات / الوصف | D3: البيانات المدخلة | E3: نوع البيانات المدخلة | F3: البيانات المخرجة | G3: شرط ملء البيان | H3: الوثائق المرفوعة | I3: التحقق والتوثيق | J3: المهام | K3: ملاحظات | L3: ملاحظات إضافية
A4: * | C4: وظيفة تسجيل دخول أدمن المشتركين البرنامج | D4: يجب ان يسمح النظام لآدمن المشتركين بتسجيل الدخول بشكل آمن باستخدام البريد الالكتروني وكلمة المرور بعد انشاء الURL الخاص بالمشترك
A5: الرابع | B5: تسجيل الدخول | C5: دخول المستخدمين المشتركين | D5: اسم المستخدم | E5: TEXT | F5: يتم السماح بالدخول علي الموقع | H5: لا يوجد | I5: تسجيل دخول بتحقق ثنائي | J5: ادمن المشتركين
A6: الرابع | D6: كلمة المرور | E6: TEXT | J6: ادمن المشتركين | K6: في حال تم نسيان او فقدان كلمة المرور يتم إعادة ارسالها مرة اخري في الايميل الخاص بالمشتركين الشركة
A7: الرابع | D7: نسيت كلمة المرور | E7: TEXT + number | J7: ادمن المشتركين | K7: مجرد قبول الدخول يتم الانتقال الي واجهة المشترك
A8: الرابع | B8: اول مرة يتم دخول في الURL بواسطة الادمن المعين عند تسجيل الاشنراك وذلك اول تغيير كلمة المرور التي أرسلت لة ثم عمل الاعدادات للبرنامج كما موضح ادناه علما بان تغيير كلمة المرور تكون من نافذة اعدادات المستخدمين وليس نافذة لحالة
A9: الثاني | T9: 1.2 اعدادات النظام
A10: الثالث | T10: 1.1.1 وظيفة تسجيل دخول الادمن
D11: يجب ان يتيح النظام للادمن إمكانية تكوين وإدارة إعدادات البرنامج والمتمثلة في
B12: اعــــــــــــــــــــــــــــــــــــــــــــــــــــــــــــــــــــــــــــــــــــــــــــــــــــــــــــــــدادات النـــــــــــــــــــــــــــــــــــــــــــــــــــــــــــــــــــــــــــــــــــــــــــــــــــــــــظام | C12: اعدادات أساسية لنافذة المشتركين البرنامج | K12: بيانات منقولة من نافذة ملاك البرنامج وخاصة بهذا المشترك ويمكن التعديل علي بعض البيانات والمحددة بالتنقيط باللون الأحمر في الخلية في نسخة المشترك وباقي البيانات بدون تنقيط لا يمكن تعديلها ولا تاثر علي باقي المشتركين
C13: معلومات الموقع | D13: البلد | E13: منقول من نافذة الملاك | F13: منقول من نافذة الملاك | G13: منقول من نافذة الملاك ويمكن التعديل | H13: لا يوجد وثائق مرفوعة | I13: لا يوجد وثائق مرفوعة
D14: المدينة | E14: منقول من نافذة الملاك | F14: منقول من نافذة الملاك | G14: منقول من نافذة الملاك ويمكن التعديل | H14: لا يوجد وثائق مرفوعة | I14: لا يوجد وثائق مرفوعة
D15: المنطقة | E15: منقول من نافذة الملاك | F15: منقول من نافذة الملاك | G15: منقول من نافذة الملاك ويمكن التعديل | H15: لا يوجد وثائق مرفوعة | I15: لا يوجد وثائق مرفوعة
D16: نوع الترخيص | E16: منقول من نافذة الملاك | F16: منقول من نافذة الملاك | G16: منقول من نافذة الملاك ويمكن التعديل | H16: لا يوجد وثائق مرفوعة | I16: لا يوجد وثائق مرفوعة
D17: رقم الترخيص | E17: منقول من نافذة الملاك | F17: منقول من نافذة الملاك | G17: منقول من نافذة الملاك ويمكن التعديل | H17: لا يوجد وثائق مرفوعة | I17: لا يوجد وثائق مرفوعة
D18: تاريخ الترخيص | E18: منقول من نافذة الملاك | F18: منقول من نافذة الملاك | G18: منقول من نافذة الملاك ويمكن التعديل | H18: لا يوجد وثائق مرفوعة | I18: لا يوجد وثائق مرفوعة
D19: اسم المرخص لة | E19: منقول من نافذة الملاك | F19: منقول من نافذة الملاك | G19: منقول من نافذة الملاك ويمكن التعديل | H19: لا يوجد وثائق مرفوعة | I19: لا يوجد وثائق مرفوعة
A20: الرابع | D20: موقع هيئة المحاسبين القانونيين | E20: قائمة من مواقع الكترونية | F20: مواقع الهيئة المرتبطة بالبلد والمدينة أعلاه | G20: منقول من نافذة الملاك ويمكن التعديل | H20: لا يوجد وثائق مرفوعة | I20: لا يوجد وثائق مرفوعة | J20: ادمن المشتركين
A21: الرابع | D21: موقع وزارة التجارة | E21: قائمة من مواقع الكترونية | F21: مواقع وزارة التجارة المرتبطة بالبلد أعلاه | G21: منقول من نافذة الملاك ويمكن التعديل | J21: ادمن المشتركين
A22: الرابع | D22: موقع مصلحة الضرائب والزكاة | E22: قائمة من مواقع الكترونية | F22: مواقع هيئة الزكاة والدخل المرتبطة بالبلد أعلاه | G22: منقول من نافذة الملاك ويمكن التعديل | J22: ادمن المشتركين
A23: الرابع | D23: مستخدمين برنامج المشتركين | E23: حسب صفحة المستخدمين المرفقة يتم تعبئتها | F23: يجب تحديد المسؤوليات والمسميات الوظيفية | G23: يتم ادخالة حسب نافذة تضمن تووزيع الصلاحيات | H23: بيانات الموظفين | I23: التحقق بارسال رسائل التأكيد للجوالات | J23: ادمن المشتركين | T23: اضافة مستخدمين المشترك يكون من خلال نافذة متخصصة فيها يمكن تحديد الصلاحيات / الفرع التابع لة المستخدم / المهام التي يتم تحديدها في دليل المراجعة
A24: الرابع
A25: الرابع | C25: دليل الحسابات | D25: دليل شجري مفتوح المستوي ويمكن التعديل علية | E25: منقول من برنامج الملاك | F25: منقول من برنامج الملاك | G25: منقول من نافذة الملاك ويمكن التعديل | H25: دليل الحسابات | J25: ادمن المشتركين | K25: الأدلة التي يعمل بها البرنامج وتنقل بآخر صورة تم اعدادها في برنامج الملاك مع الURL الخاص بالمشترك والبيانات الأخرى المنقولة وبعد انتقالها الي الURL الخاص بالمشترك تنفصل عن نسخة ملاك البرنامج ولا يوجد أي ارتباط بينهما لذلك يستطيع المشترك ان يغير في تلك البيانات دون التاثير علي نسخة ملاك البرنامج او المشتركين الآخرين
A26: الرابع | C26: دليل المراجعة | D26: دليل شجري مفتوح المستوي ويمكن التعديل علية | E26: منقول من برنامج الملاك | F26: منقول من برنامج الملاك | G26: منقول من نافذة الملاك ويمكن التعديل | H26: دليل المراجعة | J26: ادمن المشتركين
A27: الرابع | C27: دليل الإجراءات | D27: دليل شجري مفتوح المستوي ويمكن التعديل علية | E27: منقول من برنامج الملاك | F27: منقول من برنامج الملاك | G27: منقول من نافذة الملاك ويمكن التعديل | H27: دليل الإجراءات | J27: ادمن المشتركين
C28: فهرس علامات المراجعة | D28: قائمة بالعلامات المستخدة تظهر في أوراق العمل كقائمة منسدلة يقوم المدقق الفني ومساعدية ومدير التدق باستعمالها | E28: اختيار من قائمة منسدلة | F28: العلامة المختارة في مكان ظاهر بورقة العمل | G28: اختياري ويدل علي انة تم فحص البند
A29: * | C29: اعدادات برنامج المشتركين (النظام) | D29: يجب ان يتيح النظام للادمن إمكانية تكوين وإدارة إعدادات البرنامج والمتمثلة في
A30: الرابع | C30: بيانات الاشتراك | J30: ادمن المشتركين | K30: بيانات منقولة من نافذة ملاك البرنامج وخاصة فقط بهذا المشترك وهي ثابتة لا يمكن تعديلها الا بالرجوع لملاك البرنامج لضمان وحدة معلومات المشترك الواحد
A31: الرابع | C31: معلومات الموقع بيانات الزامية | D31: البلد | E31: TEXT | F31: منقول من نافذة الملاك | G31: لا يوجد تعبئة بيانات | H31: العنوان الوطني | I31: يتم التحقق من بيانات العنوان الوطني | J31: ادمن المشتركين
A32: الرابع | D32: المدينة | E32: TEXT | F32: منقول من نافذة الملاك | G32: لا يوجد تعبئة بيانات | J32: ادمن المشتركين
A33: الرابع | D33: المنطقة | E33: TEXT | F33: منقول من نافذة الملاك | G33: لا يوجد تعبئة بيانات | J33: ادمن المشتركين
A34: الرابع | C34: معلومات الترخيص بيانات الزامية | D34: نوع الترخيص | E34: Number | F34: منقول من نافذة الملاك | G34: لا يوجد تعبئة بيانات | H34: شهادة الترخيص | I34: يتم التحقق من موقع الهيئة | J34: ادمن المشتركين
A35: الرابع | D35: رقم الترخيص | E35: Number | F35: منقول من نافذة الملاك | G35: لا يوجد تعبئة بيانات | J35: ادمن المشتركين
A36: الرابع | D36: تاريخ الترخيص | E36: DATE | F36: منقول من نافذة الملاك | G36: لا يوجد تعبئة بيانات | J36: ادمن المشتركين
A37: الرابع | D37: اسم الترخيص | E37: TEXT | F37: منقول من نافذة الملاك | G37: لا يوجد تعبئة بيانات | J37: ادمن المشتركين
A38: الرابع | C38: اعدادات أساسية لنافذة المشترك بالبرنامج | D38: =-9876 -> -9876 | E38: قائمة من مواقع الكترونية | F38: مواقع الهيئة المرتبطة بالبلد والمدينة أعلاه | G38: منقول من نافذة الملاك ويمكن التعديل | H38: لا يوجد وثائق مرفوعة | I38: لا يوجد وثائق مرفوعة | J38: ادمن المشتركين | K38: بيانات منقولة من نافذة ملاك البرنامج وخاصة بهذا المشترك ويمكن التعديل عليها في نسخة المشترك ولا تاثر علي باقي المشتركين
A39: الرابع | D39: موقع وزارة التجارة | E39: قائمة من مواقع الكترونية | F39: مواقع وزارة التجارة المرتبطة بالبلد أعلاه | G39: منقول من نافذة الملاك ويمكن التعديل | J39: ادمن المشتركين
A40: الرابع | D40: موقع مصلحة الضرائب والزكاة | E40: قائمة من مواقع الكترونية | F40: مواقع هيئة الزكاة والدخل المرتبطة بالبلد أعلاه | G40: منقول من نافذة الملاك ويمكن التعديل | J40: ادمن المشتركين
A41: الرابع | C41: إضافة المستخدمين | D41: مستخدمين البرنامج | E41: يتم الإضافة في اعدادات البرنامج | F41: يجب تحديد المسؤوليات والمسميات الوظيفية | G41: منقول من نافذة الملاك ويمكن التعديل | H41: بيانات الموظفين | I41: التحقق بارسال رسائل التأكيد للجوالات | J41: ادمن المشتركين
C42: إضافة فرع
A43: الرابع | C43: دليل اهداف المراجعة | D43: دليل شجري مفتوح المستوي ويمكن التعديل علية | F43: منقول من برنامج الملاك | G43: شرط أساسي | H43: بيانات إضافية | I43: لا يوجد تحقق | J43: ادمن المشتركين | K43: الأدلة التي يعمل بها البرنامج وتنقل بآخر صورة تم اعدادها في برنامج الملاك مع الURL الخاص بالمشترك والبيانات الأخرى المنقولة وبعد انتقالها الي الURL الخاص بالمشترك تنفصل عن نسخة ملاك البرنامج ولا يوجد أي ارتباط بينهما لذلك يستطيع المشترك ان يغير في تلك البيانات دون التاثير علي المشترك
C44: دليل مراحل الملف | D44: دليل شجري مفتوح المستوي ويمكن التعديل علية | E44: منقول من برنامج الملاك | F44: منقول من برنامج الملاك | G44: شرط أساسي | H44: بيانات إضافية | I44: لا يوجد تحقق | J44: ادمن المشتركين
C45: دليل الحسابات | D45: دليل شجري مفتوح المستوي ويمكن التعديل علية | E45: منقول من برنامج الملاك | F45: منقول من برنامج الملاك | G45: شرط أساسي | H45: بيانات إضافية | I45: لا يوجد تحقق | J45: ادمن المشتركين
A46: الرابع | C46: دليل المراجعة | D46: دليل شجري مفتوح المستوي ويمكن التعديل علية | E46: منقول من برنامج الملاك | F46: منقول من برنامج الملاك | G46: شرط أساسي | H46: بيانات إضافية | I46: لا يوجد تحقق | J46: ادمن المشتركين
A47: الرابع | C47: دليل الإجراءات | D47: دليل شجري مفتوح المستوي ويمكن التعديل علية | E47: منقول من برنامج الملاك | F47: منقول من برنامج الملاك | G47: شرط أساسي | H47: بيانات إضافية | I47: لا يوجد تحقق | J47: ادمن المشتركين
A48: الثالث | T48: 1.2.1 إضافة مشترك
A49: * | B49: إضافة عقد ارتباط | C49: مهام السكرتارية ( يوجد ملاحظات في الخلية ) | L49: البيانات المظللة بالتنقيط من نفس اللون يعني التظليل ان تلك البيانات ستنتقل الي نافذة الURLللمشترك ولا يمكن التعديل عليها فقط للاطلاع علي ان يكون نفس التنقيط بيانات يمكن تعديلها في نافذة المشترك
A50: الرابع | C50: كل عقد ارتباط يمثل ملف شركة ولة رقم لا يمكن ان يتكرر في نفس السنة او أي سنة لاحقة يمثل هذا الرقم رقم ال700 للشركة + سنة موسم القوائم المالية + سنة القوائم المالية +مسلسل مثال(7000530741/2023/015) وفي العام القادم يكون الرقم (7000530741/2024/087) | D50: يتم كتابة رقم السجل التجاري او الرقم المميز للشركة والسنة المالية المراد التعاقد عليها لاصدار القوائم المالية | E50: Number / Date | F50: حسب البيانات الموضحة في عامود M | G50: شرط أساسي | H50: لا يوجد وثائق مرفوعة | J50: السكرتارية | K50: كل عقد ارتباط يحجز لسجل تجاري واسم شركة معينة يظل محجوز لها بمعني اذا تم انشاء عقد ارتباط لشركة برقم سجل تجاري 1010515969 للعام 2023 وتم اصدار القوائم المالية هنا لا يمكن اصدار قوائم مالية لنفس السجل ولنفس السنة
A51: الرابع | C51: إضافة عقد ارتباط | D51: الاختيار من قائمة منسدلة الكيان القانوني للمنشأة | E51: TEXT | F51: شرط | G51: شرط أساسي | H51: عقد التاسيس ان وجد في حالة الشركات و السجل التجاري | I51: يتم التحقق من موقع وزارة التجارة | J51: السكرتارية | K51: يتم الاختيار من قائمة منسدلة الكيان القانوني حسب الدولة (شركة/ مؤسسة/الخخخخ)
A52: الرابع | C52: الإفصاح عن معلومات المنشأة تحت التدقيق | D52: الاختيار من قائمة منسدلة نوع الكيان القانوني | E52: TEXT | F52: شرط | G52: شرط أساسي | J52: السكرتارية | K52: يتم الاختيار من قائمة منسدلة نوع الكيان القانوني فردية / شخص واحد / ذات مسؤولية محدودة/ مساهمة عامة / تضامنية / الخخخخخخ
A53: الرابع | D53: الاختيار من قائمة منسدلة جنسية الكيان القانوني | E53: TEXT | F53: شرط | G53: شرط أساسي | J53: السكرتارية | K53: يتم الاختيار من قائمة منسدلة ( البلد المحدد أعلاه / مختلطة / اجنبية )
A54: الرابع | D54: كتابة اسم منشأة العميل | E54: TEXT | F54: شرط | G54: شرط أساسي | J54: السكرتارية
A55: الرابع | D55: كتابة رقم السجل التجاري | E55: Number | F55: شرط | G55: شرط أساسي | J55: السكرتارية | K55: مثال 1010515969
A56: الرابع | D56: كتابة الرقم الضريبي | E56: Number | F56: شرط | G56: شرط أساسي | H56: شهادة التسجيل في القيمة المضافة | I56: يتم التحقق من موقع الزكاة والدخل | J56: السكرتارية
A57: الرابع | D57: كتابة الرقم الموحد | E57: Number | F57: شرط | G57: شرط أساسي | H57: شهادة الرقم الموحد | J57: السكرتارية | K57: 700123456مثال
A58: الرابع | D58: كتابة نشاط السجل التجاري | E58: TEXT | F58: شرط | G58: شرط أساسي | H58: ملخص نشاط السجل االتجاي | J58: السكرتارية
A59: الرابع | D59: تحديد تاريخ السجل التجاري هجري وميلادي | E59: DATE | F59: شرط | G59: شرط أساسي | H59: لا يوجد | I59: يتم التحقق من موقع وزارة التجارة | J59: السكرتارية | K59: يتوفر الميلادي والهجري
A60: الرابع | D60: تاريخ عقد الارتباط | E60: DATE | F60: تقرير إضافي | G60: شرط أساسي | H60: لايوجد | I60: لايوجد | J60: السكرتارية | K60: لتتبع الفترة الزمنية للملف كعقد ارتباط
A61: الرابع | C61: عنوان المنشأة تحت التدقيق | D61: الرمز البريدي | E61: E.M | F61: الرمز البريدي | G61: شرط أساسي | H61: لا يوجد | I61: يتم التحقق | J61: السكرتارية | K61: لربط الحسابات وارسال التنبيهات او استعادة كلمات المرور وستقبال الرسائل من والي المشترك
A62: الرابع | C62: بيانات أمنية وإدارية | D62: العنوان | E62: Number | F62: العنوان | G62: شرط أساسي | H62: لا يوجد | I62: يتم التحقق | J62: السكرتارية | K62: للتواصل او التحقق الثنائي
A63: الرابع | D63: البريد الالكتروني | E63: TEXT | F63: تاريخ | G63: ديناميكي وحسب تاريخ | H63: لايوجد | I63: لايوجد | J63: السكرتارية | K63: نشط-غير نشط-موقوف مؤقتا - تحت التجربة
A64: الرابع | D64: المنطقة | E64: TEXT | F64: المنظقة | G64: شرط اساسي | H64: لايوجد | I64: لايوجد | J64: السكرتارية
A65: الرابع | C65: بوابة العميل | D65: اسم ضابط اتصال المنشأة | E65: TEXT | F65: شرط | H65: لايوجد | I65: لايوجد | J65: السكرتارية | K65: تحتوي القائمة المنسدلة علي نوع الاشتراك والمؤسس بواسطة الادمن في الاعدادات علي (مراجع قانوني / مستشار مالي / خدمات محاسبية / الخخخ من الوظائف المالية المتارف عليها
A66: الرابع | H66: لايوجد | I66: لايوجد | J66: السكرتارية
A67: الرابع | D67: جوال التواصل | E67: تاريخ هجري وميلادي | F67: تقرير إضافي | H67: لايوجد | I67: لايوجد | J67: السكرتارية
A68: الرابع | D68: جوال الواتس | E68: يجب الاختيار من الباقات المتوفرة بالبرنامج | F68: برنامج الباقات | G68: شرط أساسي | J68: السكرتارية | K68: البرنامج عند تاسيسة جديد اول مرة يعمل لمدة شهر مجانا بعدها يبدء في التوقفحتي يجدد بأحد الباقات المتوفرة وعند انتهاء التجديد يتوقف البرنامج من الادخال ولكن يمكن قراءة ماتم ادخالة من قبل
A69: الرابع | C69: بيانات التخصيص الفني | D69: رابط خاص بالمنشأة | F69: رابط المنشأة بعد الاشتراك | H69: لايوجد | I69: لايوجد
A70: الرابع | D70: شعار المنشأة | F70: ايكونة لاضافة شعار المشأة | H70: لايوجد | I70: لايوجد | K70: خانة متوفرة اذا وجد للمشترك شعار
A71: الرابع | D71: اعدادات اللغة | F71: عربي / انجليزي | H71: لايوجد | I71: لايوجد | K71: يجب ان يكون هناك تعدد لللغات
A72: الرابع | D72: اعدادات العملة | F72: عدة عملات | H72: لايوجد | I72: لايوجد | K72: يجب ان يكون هناك تعدد عملات
A73: الثالث | T73: التقارير والمؤشرات 1.3.1
C74: مهام مدير التدقيق | K74: يظهر فة نافذة مدير التدقيق كل عقود الارتباط التي قام السكرتارية بانشائها ويتم التعامل معها بالضغط علي العقد المعني وفتح دليل الإجراءات الخاص بالعقد للموافقة او التاشير علي ما يخصة من مهام في دليل المراجعة
C75: اعتماد النماذج التي تخصة من دليل المراجعة | D75: تظهر هنا جميع عقود الارتباط المدخلة بالسكرتارية وفى نهاية كل عقد يوجد زر دليل المراجعة يقوم بالضغط علي فتظهر فقط المهام المحددة لمدير المراجعة فيقوم باعتمادها او رفضها | E75: عند الضغط علي العقد المصدر من السكرتارية تظهر جميع بيانات العقد / او عند الضغط علي ايقونة مضافة بالعقد مكتوب عليها دليل المراجعة تفتح نافذة بها المهام المكلف بها مدير المراجعة | I75: لا يوجد تحقق | J75: اعتماد النماذج المعيرة بدليل المراجعة انها تخصة | K75: جميع عقود الارتباط المصدرة من السكرتارية عقد 1 عقد 2 وهكذا بجميع تفاصيل العقد كما بالسكرتارية
D76: تظهر هنا قائمة بجميع عقود الارتباط المصدرة للمراجعين الفنيين من السكرتارية
C80: مهام المدقق الفني
C81: استيراد ميزان المراجعة من العميل تحت المراجعة وربطة بدليل الحسابات الخاص بالبرنامج | D81: يستلم جميع عقود الارتباط المصدرة لة خصيصا من السكرتارية ولا يكون العقد نشط مالم تتم الموافقة علية من مدير المراجعة | F81: عند الضغط علي العقد المصدر من السكرتارية والموافق علية من مدير المراجعة تظهر جميع بيانات العقد او عند الضغط علي ايقونة مضافة بالعقد مكتوب عليها دليل المراجعة تفتح نافذة بها المهام المكلف بها مدير المراجعة | G81: ولا يمكن التعديل علية وفى حالة وجود تعديل يتم ارجاعة الي السكرتارية فيما يخصة او الي مدير المراجعة فيما يخصة / | H81: مرفق عقد الارتباط المرفوع بدليل المراجعة من السكرتارية | I81: لا يوجد تحقق
T85: يشمل ملف المراجعة التابات التالية
C86: استيراد البيانات | D86: يتم استيراد بيانات العميل محل التعاقد علي احد الاشكال الموضحة من عامود L الي عامود N | L86: استيراد قيود اليومية | M86: استيراد ميزان المراجعة | N86: استيراد دفاتر الأستاذ
O87: ربط البيانات المستورة بالدليل المحاسبي
P88: اجراء المعالجات
C89: القوائم المالية | L89: تقرير المراجع القانوني
M90: قائمة المركز المالي
N91: قائمة الدخل والدخل الشامل
O92: قائمة حقوق الملاك
P93: قائمة التدفقات النقدية
Q94: السياسات المحاسبية
R95: الأثر المالي
S96: إيضاحات عن القوائم المالية
C102: مهام المدقق الميداني
C103: الزيارات الميدانية للعملاء محل التعاقد والمكلف بها من المدقق الفني | D103: يعمل وفق جدول يقوم باعدادة المدقق الفني لزيارة العملاء المحددين من قبلة
C107: مهام مساعدي التدقيق | D107: لا يوجد بيانات مدخلة ولكن يقوم المدقق باختيار من تم تعيينة في فريق المراجعة
C108: المهام المكلف بها من المدقق الفني كل عقد منفصل
C112: مهام ضابط الجودة
C113: مراجعة القوائم المالية الصادرة والتقارير عنها لارسالها للشريك الإداري | D113: يقوم بالاطلاع علي القوائم المالية وتسجيل الملاح
C116: مهام الشريك الإداري
C117: توقيع تقرير الحسابات
C122: البيانات النظامية ذات العلاقة
C123: الافصاح عن بيانات تقرير المراجع القانوني
...

Sheet دليل الحسابات
A1: المستوى | B1: رقم الحساب | C1: اسم الحساب | D1: التعريف المحاسبي | E1: السياسات المحاسبية | F1: IFRS | G1: IAS | H1: المعايير المحلية (SOCPA) | I1: معايير المراجعة (ISA) | J1: إجراءات المراجعة | K1: اللوائح والنُظم (السعودية) | L1: ملاحظات الإفصاح | O1: رمز الهدف | V1: الأهداف المرتبطة
A2: المستوى الأول | B2: 1 | C2: الموجودات | D2: موارد خاضعة لسيطرة المنشأة ينتج عنها منافع اقتصادية مستقبلية | E2: تصنيف متداول وغير متداول | F2: — | G2: IAS 1 | H2: إطار العرض العام SOCPA | I2: ISA 315 / 330 | J2: مراجعة هيكلية فقط دون أرصدة | K2: نظام الشركات السعودي | L2: لا توجد إفصاحات منفصلة | O2: E,C,R,V,P | Q2: E | R2: C | S2: R | T2: V | U2: P | V2: (خارجي) جميع أهداف المراجعة / (داخلي) حماية الأصول – سلامة التصنيف – دقة القياس
A3: المستوى الثاني | B3: 11 | C3: الموجودات المتداولة | D3: أصول يتوقع بيعها أو استخدامها خلال 12 شهر | E3: قياس بالتكلفة أو صافي القيمة القابلة للتحقق | F3: — | G3: IAS 1 / IAS 2 | H3: إطار العرض العام SOCPA | I3: ISA 315 / 330 | J3: مطابقة دورية وتحليل دورة التشغيل | K3: زكاة القيمة المضافة | L3: الإفصاح عن السياسات التصنيفية | O3: E,V,P | V3: (خارجي) Existence – Valuation – Presentation / (داخلي) حماية الأصول المتداولة – دقة التصنيف – المطابقة الدورية
A4: المستوى الثالث | B4: 1101 | C4: النقد وما في حكمه | D4: أرصدة نقدية ومعادلات نقدية عالية السيولة تستحق خلال 3 أشهر | E4: إثبات بالقيمة الاسمية، ضوابط جرد وصرف | F4: IFRS 7 | G4: IAS 7 | H4: SOCPA للتقارير النقدية | I4: ISA 240 / 505 | J4: مطابقة كشوف البنك، جرد مفاجئ للصندوق | K4: تعليمات البنك المركزي السعودي | L4: الإفصاح عن الأرصدة المقيدة | O4: E,V,C | V4: (خارجي) Existence – Valuation – Completeness / (داخلي) حماية النقدية – الرقابة على العهد – دقة الجرد والتسوية
A5: المستوى الرابع | B5: 1101001 | C5: صندوق رئيسي | D5: نقدية فعلية بالمنشأة | E5: حدود عهدة، جرد مفاجئ، فصل العهد الشخصية | F5: IFRS 7 | G5: IAS 7 | H5: سياسات SOCPA للنقدية | I5: ISA 240 / 505 | J5: فحص سندات الصرف، عد فعلي، مطابقة الرصيد | K5: لائحة الصرف النقدي | L5: الإفصاح عن العجز أو الفروقات | O5: E,V,C | V5: (خارجي) Existence – Valuation – Completeness / (داخلي) حماية النقدية – الالتزام بسياسات الصرف – دقة التسجيل
A6: المستوى الرابع | B6: 1101002 | C6: بنك الراجحي | D6: ودائع جارية تحت الطلب | E6: مطابقة شهرية، صلاحيات توقيع مزدوج | F6: IFRS 7 | G6: IAS 7 | H6: سياسات البنوك SOCPA | I6: ISA 505 | J6: مطابقة كشف البنك، مراجعة التسويات البنكية | K6: تعليمات البنك المركزي | L6: الإفصاح عن قيود السحب أو التسهيلات | O6: E,V,P | V6: (خارجي) Existence – Valuation – Presentation / (داخلي) دقة الرصيد البنكي – التوافق مع كشوف البنك – الالتزام بالتفويضات
A7: المستوى الرابع | B7: 1101003 | C7: بنك الأهلي | D7: ودائع جارية بالبنك الأهلي | E7: مطابقة وتسويات بنكية شهرية | F7: IFRS 7 | G7: IAS 7 | H7: تعليمات البنك المركزي السعودي | I7: ISA 505 | J7: مطابقة كشوف البنك، فحص التفويضات | K7: تعليمات البنك المركزي | L7: الإفصاح عن التسهيلات البنكية | O7: E,V,P | V7: (خارجي) Existence – Valuation – Presentation / (داخلي) دقة الرصيد البنكي – التوافق مع كشوف البنك – الالتزام بالتفويضات
A8: المستوى الثالث | B8: 1102 | C8: أعمال تحت التنفيذ | D8: تكاليف مشاريع قيد الإنجاز قصيرة الأجل | E8: إثبات التكاليف وتحميل نسبة الإنجاز | F8: IFRS 15 | G8: IAS 2 | H8: عقود الإنشاء والخدمات SOCPA | I8: ISA 540 | J8: فحص أوامر التشغيل، اعتماد نسب الإنجاز | K8: نظام المنافسات والمشتريات | L8: شرح منهج القياس المستخدم | O8: E,V,P | V8: (خارجي) Existence – Valuation – Presentation / (داخلي) دقة نسب الإنجاز – مطابقة العقود – كفاءة إدارة المشاريع
A9: المستوى الرابع | B9: 1102001 | C9: مشروع إنشاءات الرياض | D9: تكاليف مشروع إنشاءات | E9: نسبة إنجاز، تقييم بالتكلفة حتى الإنجاز | F9: IFRS 15 | G9: — | H9: سياسات عقود الإنشاء | I9: ISA 540 | J9: مطابقة العقود والفواتير وأوامر التشغيل | K9: نظام المنافسات | L9: الإفصاح عن نسب الإنجاز | O9: E,V,P | V9: (خارجي) Existence – Valuation – Presentation / (داخلي) دقة نسب الإنجاز – مطابقة العقود – كفاءة إدارة المشاريع
A10: المستوى الرابع | B10: 1102002 | C10: مشروع صيانة جدة | D10: تكاليف مشروع صيانة | E10: الاعتراف بالتكاليف الفعلية فقط حتى الإنجاز | F10: IFRS 15 | G10: — | H10: سياسات عقود الخدمات | I10: ISA 540 | J10: فحص تقارير الإنجاز والفواتير | K10: نظام المنافسات | L10: الإفصاح عن العقود الجارية | O10: E,V,P | V10: (خارجي) Existence – Valuation – Presentation / (داخلي) دقة نسب الإنجاز – مطابقة العقود – كفاءة إدارة المشاريع
A11: المستوى الثالث | B11: 1103 | C11: ذمم وأرصدة مدينة تجارية | D11: مطالبات على العملاء مقابل مبيعات | E11: قياس بالقيمة المطفأة واحتساب خسائر ائتمانية متوقعة | F11: IFRS 9 | G11: IAS 1 / IAS 32 | H11: SOCPA للذمم التجارية | I11: ISA 505 / 540 | J11: مصادقات العملاء، تحليل تقادم الذمم | K11: نظام الفوترة الإلكترونية (ZATCA) | L11: الإفصاح عن الذمم الجوهرية | O11: E,V,C | V11: (خارجي) Existence – Valuation – Completeness / (داخلي) دقة تسجيل الذمم – الالتزام بسياسات الائتمان – مراقبة التحصيل
A12: المستوى الرابع | B12: 1103001 | C12: العميل أحمد | D12: ذمة عميل محدد | E12: متابعة التحصيل ضمن دورة الائتمان | F12: IFRS 9 | G12: — | H12: سياسات التحصيل | I12: ISA 505 | J12: مصادقة الرصيد ومراجعة العقود | K12: النظام التجاري | L12: الإفصاح عن الذمم المتعثرة | O12: E,V,P | V12: (خارجي) Existence – Valuation – Presentation / (داخلي) دقة تسجيل الذمم – الالتزام بسياسات الائتمان – مراقبة التحصيل
A13: المستوى الرابع | B13: 1103002 | C13: العميل محمد | D13: ذمة عميل محدد | E13: قياس بالقيمة المطفأة ومخصص ECL | F13: IFRS 9 | G13: — | H13: قواعد الائتمان | I13: ISA 505 | J13: مصادقات وتحليل تقادم | K13: النظام التجاري | L13: الإفصاح عن الذمم الجوهرية | O13: E,V,P | V13: (خارجي) Existence – Valuation – Presentation / (داخلي) دقة تسجيل الذمم – الالتزام بسياسات الائتمان – مراقبة التحصيل
A14: المستوى الثالث | B14: 1104 | C14: المخزون السلعي (البضاعة) | D14: مخزون محتفظ به للبيع ضمن النشاط العادي | E14: القياس بالتكلفة أو صافي القيمة القابلة للتحقق أيهما أقل | F14: — | G14: IAS 2 | H14: SOCPA للمخزون | I14: ISA 501 | J14: حضور الجرد، اختبار القطع والتسعير | K14: لوائح الجرد | L14: ZATCA | M14: الإفصاح عن طريقة التسعير | O14: E,V,C | V14: (خارجي) Existence – Valuation – Completeness / (داخلي) حماية المخزون – كفاءة إدارة المخزون – دقة الجرد
A15: المستوى الرابع | B15: 1104001 | C15: مخزن الرياض | D15: مخزون بضاعة في موقع الرياض | E15: تطبيق FIFO أو المتوسط المرجح | F15: — | G15: IAS 2 | H15: سياسات المخزون | I15: ISA 501 | J15: حضور جرد الموقع، مطابقة البطاقات | K15: لوائح الجرد | L15: ZATCA | M15: الإفصاح عن المخزون المرهون
A16: المستوى الرابع | B16: 1104002 | C16: مخزن جدة | D16: مخزون بضاعة في موقع جدة | E16: تقييم بالتكلفة أو NRV | F16: — | G16: IAS 2 | H16: سياسات المخزون | I16: ISA 501 | J16: اختبار القصاصات والجرد الدوري | K16: لوائح الجرد | L16: ZATCA | M16: الإفصاح عن طرق التسعير | O16: E,V,C | V16: (خارجي) Existence – Valuation – Completeness / (داخلي) حماية المخزون – كفاءة إدارة المخزون – دقة الجرد
O17: E,V,C | V17: (خارجي) Existence – Valuation – Completeness / (داخلي) حماية المخزون – كفاءة إدارة المخزون – دقة الجرد
O18: E,V,P | V18: (خارجي) Existence – Valuation – Presentation / (داخلي) دقة التسجيل – متابعة التحصيل – الامتثال للسياسات
O19: E,R,V | V19: (خارجي) Existence – Rights & Obligations – Valuation / (داخلي) دقة إثبات العمليات – الالتزام بالإفصاح – تسوية دورية
O20: E,V,P | V20: (خارجي) Existence – Valuation – Presentation / (داخلي) دقة الرسملة – الترحيل حسب الفترات – المطابقة الدورية
O21: V,P | V21: (خارجي) Valuation – Presentation / (داخلي) دقة الرسملة – مطابقة عقود القروض – مراجعة جداول الإطفاء
O22: E,V,P | V22: (خارجي) Existence – Valuation – Presentation / (داخلي) إثبات الحقوق – دقة التقييم – الإفصاح عن البنود الجوهرية
O23: E,V,C | V23: (خارجي) Existence – Valuation – Completeness / (داخلي) دقة التحصيل – متابعة الاستحقاقات – مطابقة القيود
O24: E,R,V | V24: (خارجي) Existence – Rights & Obligations – Valuation / (داخلي) سلامة الضمانات – الإفصاح عن الالتزامات – مطابقة البنوك
O25: E,V,P | V25: (خارجي) Existence – Valuation – Presentation / (داخلي) دقة التصنيف – حماية المخزون – منع الاستخدام غير المصرح
O26: E,V,C | V26: (خارجي) Existence – Valuation – Completeness / (داخلي) دقة القطع – ربط بالإيرادات الفعلية – مراقبة الترحيل
O27: E,V,P | V27: (خارجي) Existence – Valuation – Presentation / (داخلي) متابعة التوزيعات – مطابقة الإشعارات – الترحيل الصحيح
A28: المستوى الثالث | B28: 1115 | C28: مواد خام ومهمات | D28: مواد أولية ومهمات تشغيلية | E28: قياس بالتكلفة أو NRV | F28: — | G28: IAS 2 | H28: SOCPA للمخزون | I28: ISA 501 | J28: حضور الجرد وتتبع الصرف | K28: نظام التصنيع | L28: الإفصاح عن الفاقد والهالك
A29: المستوى الرابع | B29: 1115001 | C29: مخزون مواد خام | D29: مخزون مواد خام بالمخزن | E29: تطبيق FIFO أو المتوسط المرجح | F29: — | G29: IAS 2 | H29: سياسات المخزون | I29: ISA 501 | J29: مطابقة أرصدة المخزون | K29: نظام التصنيع | L29: الإفصاح عن انخفاض القيمة
A30: المستوى الرابع | B30: 1115002 | C30: مهمات تشغيل | D30: أدوات ومهمات تستخدم في التشغيل | E30: تحميل كمخزون مستهلك عند الاستخدام | F30: — | G30: IAS 2 | H30: سياسات المخزون | I30: ISA 501 | J30: فحص الاستهلاك الفعلي | K30: نظام التصنيع | L30: الإفصاح عن الفاقد
A31: المستوى الثالث | B31: 1116 | C31: إنتاج تحت التشغيل | D31: منتجات لم تكتمل بعد | E31: تحميل المواد والأجور والتكاليف الصناعية | F31: — | G31: IAS 2 | H31: SOCPA للتكاليف | I31: ISA 540 | J31: مطابقة أوامر الإنتاج | K31: نظام العمل الصناعي | L31: الإفصاح عن نسب الإتمام
A32: المستوى الرابع | B32: 1116001 | C32: إنتاج تحت التشغيل خط 1 | D32: منتجات جارية بخط الإنتاج الأول | E32: تحميل فعلي للمواد والأجور والتكاليف الصناعية | F32: — | G32: IAS 2 | H32: سياسات التكاليف | I32: ISA 540 | J32: مطابقة التكاليف مع الإنتاج الفعلي | K32: نظام العمل الصناعي | L32: الإفصاح عن الفاقد الطبيعي
A33: المستوى الرابع | B33: 1116002 | C33: إنتاج تحت التشغيل خط 2 | D33: منتجات جارية بخط الإنتاج الثاني | E33: تحميل فعلي للمواد والأجور والتكاليف الصناعية | F33: — | G33: IAS 2 | H33: سياسات التكاليف | I33: ISA 540 | J33: مطابقة التكاليف مع الإنتاج الفعلي | K33: نظام العمل الصناعي | L33: الإفصاح عن الفاقد الطبيعي
A34: المستوى الثالث | B34: 1117 | C34: إنتاج تام | D34: منتجات مكتملة غير مباعة | E34: القياس بالتكلفة أو NRV أيهما أقل | F34: — | G34: IAS 2 | H34: سياسات المخزون | I34: ISA 501 | J34: اختبارات القطع والقصاصات | K34: نظام التصنيع | L34: الإفصاح عن طريقة التقييم
A35: المستوى الرابع | B35: 1117001 | C35: مخزون إنتاج تام | D35: منتجات مكتملة جاهزة للبيع | E35: التكلفة أو NRV أيهما أقل | F35: — | G35: IAS 2 | H35: سياسات المخزون | I35: ISA 501 | J35: حضور الجرد واختبار التسعير | K35: نظام التصنيع | L35: الإفصاح عن NRV
A36: المستوى الثاني | B36: 12 | C36: الموجودات غير المتداولة | D36: أصول يُتوقع استخدامها أو الاحتفاظ بها لأكثر من 12 شهر | E36: نموذج التكلفة أو إعادة التقييم | F36: IFRS 13 | G36: IAS 1 | H36: إطار العرض العام SOCPA | I36: ISA 315 / 330 | J36: فحص وجود وتصنيف الأصول طويلة الأجل | K36: نظام الشركات | L36: الإفصاح عن أسس التصنيف وطبيعة الأصول | O36: E,C,R,V,P | V36: (خارجي) جميع أهداف المراجعة / (داخلي) حماية الأصول الثابتة – دقة التقييم – متابعة الإهلاك
A37: المستوى الثالث | B37: 1201 | C37: أصول غير ملموسة | D37: أصول ليس لها جوهر مادي وتُستخدم لفترات طويلة | E37: رسملة عند توافر المعايير ثم إطفاء أو اختبار هبوط | F37: — | G37: IAS 38 | H37: سياسات رسملة وتقييم الأصول غير الملموسة | I37: SOCPA | J37: ISA 540 | K37: مراجعة عقود الملكية الفكرية؛ اختبار الهبوط | L37: نظام الملكية الفكرية | M37: الإفصاح عن أعمار الإطفاء والمنهج | O37: E,R,V,P | V37: (خارجي) Existence – Rights & Obligations – Valuation – Presentation / (داخلي) حماية الملكية الفكرية – دقة الإطفاء – مراجعة القيود القانونية
A38: المستوى الرابع | B38: 1201001 | C38: برامج حاسوبية | D38: أصول برمجية تُستخدم في التشغيل والإدارة | E38: رسملة التكاليف المباشرة وإطفاء على العمر النافع | F38: — | G38: IAS 38 | H38: سياسات الرسملة والإطفاء | I38: SOCPA | J38: ISA 540 | K38: مراجعة فواتير الترخيص وجدولة الإطفاء | L38: نظام حماية حقوق المؤلف | M38: الإفصاح عن العمر الإنتاجي وطريقة الإطفاء | O38: E,V,P | V38: (خارجي) Existence – Valuation – Presentation / (داخلي) حماية الأصول – دقة الإطفاء – التحقق من الرخص
A39: المستوى الرابع | B39: 1201002 | C39: براءات اختراع | D39: حقوق ملكية فكرية مسجلة قانوناً | E39: رسملة عند الشراء وإطفاء على العمر النافع | F39: — | G39: IAS 38 | H39: سياسات الملكية الفكرية | I39: SOCPA | J39: ISA 540 | K39: فحص عقود الملكية وسندات التسجيل | L39: نظام الملكية الفكرية | M39: الإفصاح عن القيود القانونية أو الرهون | O39: E,R,V | V39: (خارجي) Existence – Rights & Obligations – Valuation / (داخلي) حماية الملكية الفكرية – دقة الإطفاء – مراجعة القيود القانونية
A40: المستوى الثالث | B40: 1202 | C40: أصول بموجب عقود إيجار تمويلي | D40: أصول ثابتة مستأجرة طويلة الأجل | E40: إثبات أصل حق الاستخدام والتزام إيجار | F40: IFRS 16 | G40: — | H40: سياسات عقود الإيجار | I40: SOCPA | J40: ISA 540 | K40: فحص عقود الإيجار وحساب الفوائد الضمنية | L40: نظام الإيجارات | M40: الإفصاح عن آجال الاستحقاق والضمانات | O40: E,R,V | V40: (خارجي) Existence – Rights & Obligations – Valuation / (داخلي) سلامة الأصول المؤجرة – دقة قيود الإيجار – مطابقة جداول السداد
A41: المستوى الرابع | B41: 1202001 | C41: سيارات إيجار تمويلي | D41: أصول سيارات مؤجرة بعقود تمويلية | E41: إثبات أصل ROU واستهلاكه وإثبات الالتزام | F41: IFRS 16 | G41: — | H41: سياسات الإيجار | I41: SOCPA | J41: ISA 540 | K41: فحص عقود السيارات والتأكد من مدة العقد | L41: نظام المرور | M41: الإفصاح عن الاستحقاقات قصيرة وطويلة الأجل | O41: E,R,V | V41: (خارجي) Existence – Rights & Obligations – Valuation / (داخلي) سلامة الأصول المؤجرة – دقة قيود الإيجار – مطابقة جداول السداد
A42: المستوى الثالث | B42: 1203 | C42: استثمارات طويلة الأجل | D42: استثمارات مالية وملكية في شركات أخرى | E42: قياس وفق التصنيف (FVOCI/FVTPL أو طريقة حقوق الملكية) | F42: IFRS 9 | G42: IAS 28 | H42: سياسات الاستثمار | I42: SOCPA | J42: ISA 540 / 500 | K42: فحص تقييمات القيمة العادلة ومصادقات أمناء الحفظ | L42: لوائح هيئة السوق المالية | M42: الإفصاح عن طبيعة الاستثمار ومستوى القياس | O42: E,R,V,P | V42: (خارجي) Existence – Rights & Obligations – Valuation – Presentation / (داخلي) دقة التقييم – مطابقة الحافظين – الإفصاح عن المخاطر
A43: المستوى الرابع | B43: 1203001 | C43: أسهم شركات مدرجة | D43: استثمارات في أدوات حقوق ملكية مدرجة | E43: القياس بالقيمة العادلة من خلال الدخل الشامل الآخر (FVOCI) | F43: IFRS 9 | G43: — | H43: سياسات الاستثمار | I43: SOCPA | J43: ISA 540 | K43: فحص أسعار السوق وإشعارات التملك | L43: لوائح هيئة السوق المالية | M43: الإفصاح عن التغيرات في القيمة العادلة | O43: E,V,P | V43: (خارجي) Existence – Valuation – Presentation / (داخلي) دقة تقييم الاستثمارات – مطابقة إشعارات الحفظ – الإفصاح عن المخاطر
A44: المستوى الرابع | B44: 1203002 | C44: سندات حكومية | D44: أدوات دين محتفظ بها حتى الاستحقاق | E44: القياس بالتكلفة المطفأة واحتساب الفوائد الفعلية | F44: IFRS 9 | G44: — | H44: سياسات الاستثمار | I44: SOCPA | J44: ISA 540 | K44: إعادة احتساب الفوائد ومطابقة العقود | L44: لوائح البنك المركزي | M44: الإفصاح عن آجال الاستحقاق والعوائد | O44: E,V,P | V44: (خارجي) Existence – Valuation – Presentation / (داخلي) دقة احتساب الفوائد – مطابقة العقود – الالتزام بسياسات الاستثمار
A45: المستوى الرابع | B45: 1203003 | C45: استثمارات في شركات تابعة | D45: ملكية تحقق السيطرة على الشركة المستثمر بها | E45: طريقة حقوق الملكية عند العرض في القوائم المنفصلة | F45: — | G45: IAS 28 | H45: سياسات الشركات التابعة | I45: SOCPA | J45: ISA 600 | K45: فحص القوائم المالية للتابعة وتوحيد البيانات | L45: نظام الشركات | M45: الإفصاح عن نسب الملكية وطبيعة السيطرة | O45: E,R,V,P | V45: (خارجي) Existence – Rights & Obligations – Valuation – Presentation / (داخلي) دقة التوحيد – متابعة القوائم – الإفصاح عن السيطرة
A46: المستوى الرابع | B46: 1203004 | C46: استثمارات في شركات شقيقة | D46: ملكية تحقق تأثير جوهري دون سيطرة | E46: طريقة حقوق الملكية | F46: — | G46: IAS 28 | H46: سياسات الشركات الشقيقة | I46: SOCPA | J46: ISA 600 | K46: فحص القوائم المالية للشقيقة ومتابعة التأثير الجوھري | L46: نظام الشركات | M46: الإفصاح عن نسب الملكية وطبيعة التأثير | O46: E,R,V,P | V46: (خارجي) Existence – Rights & Obligations – Valuation – Presentation / (داخلي) دقة طريقة حقوق الملكية – متابعة القوائم – الإفصاح عن نسب الملكية
A47: المستوى الثالث | B47: 1204 | C47: استثمارات متاحة للبيع | D47: استثمارات مالية غير محتفظ بها للتداول ولا حتى الاستحقاق | E47: قياس بالقيمة العادلة من خلال الدخل الشامل الآخر (FVOCI) | F47: IFRS 9 | G47: — | H47: سياسات الاستثمار | I47: SOCPA | J47: ISA 540 | K47: فحص تقييمات القيمة العادلة ومصادقات أمناء الحفظ | L47: لوائح هيئة السوق المالية | M47: الإفصاح عن الأرباح والخسائر غير المحققة | O47: E,V,P | V47: (خارجي) Existence – Valuation – Presentation / (داخلي) دقة تقييم القيمة العادلة – مطابقة الأسعار السوقية – الإفصاح عن المخاطر
A48: المستوى الرابع | B48: 1204001 | C48: أدوات دين قابلة للبيع | D48: استثمارات قابلة للبيع في أدوات دين | E48: القياس بالقيمة العادلة من خلال الدخل الشامل الآخر (FVOCI) | F48: IFRS 9 | G48: — | H48: سياسات الاستثمار | I48: SOCPA | J48: ISA 540 | K48: مطابقة الأسعار السوقية | L48: لوائح هيئة السوق المالية | M48: الإفصاح عن مخاطر سعر الفائدة والائتمان | O48: E,V,P | V48: (خارجي) Existence – Valuation – Presentation / (داخلي) دقة تقييم القيمة العادلة – مطابقة الأسعار السوقية – الإفصاح عن المخاطر
... A63: المستوى الرابع | B63: 1210001 | C63: شهرة منشأة مدمجة | D63: شهرة ناتجة عن استحواذ | E63: اختبار هبوط سنوي أو عند مؤشرات هبوط | F63: IFRS 3 | G63: IAS 36 | H63: سياسات الشهرة | I63: SOCPA | J63: ISA 540 | K63: فحص تقارير تقييم CGU | L63: نظام الاستحواذ | M63: الإفصاح عن معدلات الخصم والنمو | O63: E,V,P | V63: (خارجي) Existence – Valuation – Presentation / (داخلي) اختبار هبوط سنوي – دقة التقييم – متابعة CGU
A64: المستوى الأول | B64: 2 | C64: المطلوبات | D64: التزامات حالية على المنشأة تنشأ من أحداث سابقة | E64: تصنيف متداولة وغير متداولة | F64: — | G64: IAS 1 | H64: إطار العرض العام SOCPA | I64: ISA 315 / 330 | J64: فحص التصنيف العام فقط | K64: نظام الشركات | L64: لا توجد إفصاحات منفصلة | O64: E,C,R,V,P | V64: (خارجي) جميع أهداف المراجعة / (داخلي) الالتزام بالسداد – دقة التسجيل – سلامة التصنيف
A65: المستوى الثاني | B65: 21 | C65: المطلوبات المتداولة | D65: التزامات تُسدد خلال 12 شهر من نهاية الفترة | E65: الاعتراف عند نشوء الالتزام وقياس بالتكلفة المطفأة | F65: IFRS 9 | G65: IAS 1 | H65: عرض الالتزامات المتداولة SOCPA | I65: ISA 315 / 330 | J65: مطابقة الالتزامات مع السداد اللاحق | K65: نظام الشركات | L65: الإفصاح عن السياسات التصنيفية | O65: E,V,P | V65: (خارجي) Existence – Valuation – Presentation / (داخلي) دقة التصنيف – الرقابة على الاستحقاقات – تسوية دورية
A66: المستوى الثالث | B66: 2101 | C66: ذمم وأرصدة دائنة تجارية | D66: التزامات للموردين عن سلع وخدمات تم استلامها | E66: الاعتراف عند الاستلام وقياس بالتكلفة المطفأة | F66: IFRS 9 | G66: — | H66: سياسات الذمم الدائنة SOCPA | I66: ISA 505 | J66: مصادقات الموردين ومطابقة الفواتير | K66: نظام الفوترة الإلكترونية | L66: ZATCA | M66: الإفصاح عن أرصدة الأطراف ذات العلاقة | O66: E,V,C | V66: (خارجي) Existence – Valuation – Completeness / (داخلي) دقة تسجيل الالتزامات – مطابقة الموردين – الالتزام بإجراءات الشراء
A67: المستوى الرابع | B67: 2101001 | C67: المورد سالم | D67: ذمة دائنة لمورد محدد | E67: قياس بالتكلفة المطفأة والدفع حسب الأجل | F67: IFRS 9 | G67: — | H67: سياسات الموردين | I67: SOCPA | J67: ISA 505 | K67: مطابقة فواتير وأوامر الشراء | L67: نظام الفوترة الإلكترونية | M67: ZATCA | N67: الإفصاح عن شروط الدفع | O67: C,V,P | V67: (خارجي) Completeness – Valuation – Presentation / (داخلي) دقة تسجيل الالتزامات – الالتزام بإجراءات الشراء – تسوية دورية
A68: المستوى الرابع | B68: 2101002 | C68: المورد خالد | D68: ذمة دائنة لمورد محدد | E68: قياس بالتكلفة المطفأة والدفع حسب الأجل | F68: IFRS 9 | G68: — | H68: سياسات الموردين | I68: SOCPA | J68: ISA 505 | K68: مطابقة فواتير وأوامر الشراء | L68: نظام الفوترة الإلكترونية | M68: ZATCA | N68: الإفصاح عن شروط الدفع | O68: C,V,P | V68: (خارجي) Completeness – Valuation – Presentation / (داخلي) دقة تسجيل الالتزامات – الالتزام بإجراءات الشراء – تسوية دورية
A69: المستوى الثالث | B69: 2102 | C69: ذمم وأرصدة دائنة أخرى | D69: التزامات متنوعة غير تجارية | E69: إثبات عند نشوء الالتزام وقياس بالتكلفة المطفأة | F69: — | G69: IAS 1 | H69: عرض الالتزامات المتداولة SOCPA | I69: ISA 315 / 330 | J69: فحص المستندات المؤيدة | K69: نظام المحاسبة المالية | L69: شرح طبيعة البنود الجوهرية | O69: E,V,P | V69: (خارجي) Existence – Valuation – Presentation / (داخلي) دقة التسجيل – صحة الاستحقاق – مطابقة المستندات المؤيدة
A70: المستوى الرابع | B70: 2102001 | C70: مستحقات حكومية | D70: مبالغ مستحقة لجهات حكومية | E70: إثبات عند نشوء الالتزام وسداده خلال الأجل | F70: — | G70: IAS 1 | H70: عرض الالتزامات SOCPA | I70: ISA 315 | J70: مطابقة المطالبات وخطابات السداد | K70: لوائح ZATCA | L70: الإفصاح عن الغرامات أو الاعتراضات | O70: E,V,P | V70: (خارجي) Existence – Valuation – Presentation / (داخلي) الالتزام بالسداد – دقة المطابقة – الإفصاح عن المطالبات
A71: المستوى الثالث | B71: 2103 | C71: مستحق لأطراف ذات علاقة | D71: التزامات قصيرة لأطراف داخل المجموعة | E71: قياس بالتكلفة المطفأة والإفصاح عن العلاقة | F71: IFRS 9 | G71: IAS 24 | H71: إفصاح الأطراف ذات العلاقة | I71: SOCPA | J71: ISA 550 | K71: فحص اتفاقيات المجموعة ومصادقات متبادلة | L71: نظام الشركات | M71: الإفصاح عن شروط السداد | O71: E,R,V | V71: (خارجي) Existence – Rights & Obligations – Valuation / (داخلي) مطابقة العقود – دقة الإثبات – الإفصاح عن الأطراف ذات العلاقة
A72: المستوى الرابع | B72: 2103001 | C72: شركة شقيقة أ | D72: مستحق لشركة شقيقة | E72: قياس بالتكلفة المطفأة | F72: IFRS 9 | G72: IAS 24 | H72: إفصاح الأطراف ذات العلاقة | I72: SOCPA | J72: ISA 550 | K72: مطابقة عقود التمويل الداخلية | L72: نظام الشركات | M72: الإفصاح عن العلاقة | O72: E,R,V | V72: (خارجي) Existence – Rights & Obligations – Valuation / (داخلي) دقة التسجيل – تسوية دورية – مطابقة العقود
A73: المستوى الرابع | B73: 2103002 | C73: شركاء | D73: مستحقات قصيرة على الشركاء | E73: قياس بالتكلفة المطفأة | F73: IFRS 9 | G73: IAS 24 | H73: إفصاح الأطراف ذات العلاقة | I73: SOCPA | J73: ISA 550 | K73: فحص السحوبات والمطابقة مع حسابات الشركاء | L73: نظام الشركات | M73: الإفصاح عن المعاملات مع الشركاء | O73: E,R,V | V73: (خارجي) Existence – Rights & Obligations – Valuation / (داخلي) دقة التسجيل – تسوية دورية – مطابقة حسابات الشركاء
A74: المستوى الثالث | B74: 2104 | C74: الجزء المتداول من التزامات إيجار تمويلي | D74: دفعات إيجار مستحقة خلال 12 شهر | E74: إثبات التزام الإيجار وفق IFRS 16 | F74: IFRS 16 | G74: — | H74: إفصاح التزامات الإيجار | I74: SOCPA | J74: ISA 540 | K74: مطابقة جداول السداد قصيرة الأجل | L74: نظام الإيجارات | M74: الإفصاح عن آجال الاستحقاق | O74: E,R,V | V74: (خارجي) Existence – Rights & Obligations – Valuation / (داخلي) دقة قيود الإيجار – مطابقة جداول السداد – الالتزام بالعقود
A75: المستوى الرابع | B75: 2104001 | C75: عقد سيارات | D75: دفعات إيجار تمويلي على سيارات | E75: تصنيف كجزء متداول من الالتزامات | F75: IFRS 16 | G75: — | H75: سياسات الإيجار | I75: SOCPA | J75: ISA 540 | K75: فحص عقود السيارات | L75: نظام المرور | M75: الإفصاح عن ضمانات الإيجار | O75: E,R,V | V75: (خارجي) Existence – Rights & Obligations – Valuation / (داخلي) مطابقة جداول السداد – صحة العقود – سلامة الأصول
A76: المستوى الثالث | B76: 2105 | C76: الجزء المتداول من قروض قصيرة الأجل | D76: قروض تستحق خلال 12 شهر | E76: قياس بالتكلفة المطفأة | F76: IFRS 9 | G76: — | H76: سياسات القروض | I76: SOCPA | J76: ISA 505 / 540 | K76: مطابقة عقود القروض وجدولة الفوائد | L76: تعليمات البنك المركزي | M76: الإفصاح عن العهود المالية | O76: E,V,P | V76: (خارجي) Existence – Valuation – Presentation / (داخلي) مطابقة جداول القروض – صحة الفوائد – الالتزام بالعهود البنكية
A77: المستوى الرابع | B77: 2105001 | C77: قرض جاري من بنك | D77: تسهيلات مصرفية قصيرة الأجل | E77: احتساب الفائدة الفعلية | F77: IFRS 9 | G77: — | H77: سياسات القروض | I77: SOCPA | J77: ISA 540 | K77: مطابقة كشوف البنك | L77: تعليمات البنك المركزي | M77: الإفصاح عن الضمانات | O77: E,V,P | V77: (خارجي) Existence – Valuation – Presentation / (داخلي) مطابقة كشوف البنك – مراجعة الفوائد – الالتزام بعقود التمويل
A78: المستوى الثالث | B78: 2106 | C78: الجزء المتداول من قروض طويلة الأجل | D78: أقساط قروض طويلة تستحق خلال 12 شهر | E78: قياس بالتكلفة المطفأة | F78: IFRS 9 | G78: — | H78: سياسات القروض | I78: SOCPA | J78: ISA 540 | K78: مطابقة جداول السداد وإعادة احتساب الفوائد | L78: تعليمات البنك المركزي | M78: الإفصاح عن العهود المالية | O78: E,V,P | V78: (خارجي) Existence – Valuation – Presentation / (داخلي) مطابقة جداول القروض – صحة الفوائد – الالتزام بالعهود البنكية
A79: المستوى الرابع | B79: 2106001 | C79: قرض طويل الأجل مستحق | D79: قسط من قرض طويل يستحق قريباً | E79: إعادة تصنيف من غير متداول إلى متداول | F79: IFRS 9 | G79: — | H79: سياسات القروض | I79: SOCPA | J79: ISA 540 | K79: فحص التعديلات البنكية | L79: تعليمات البنك المركزي | M79: الإفصاح عن آجال السداد | O79: E,V,P | V79: (خارجي) Existence – Valuation – Presentation / (داخلي) مطابقة جداول السداد – مراجعة العقود – الإفصاح عن آجال السداد
A80: المستوى الثالث | B80: 2107 | C80: مصروفات مستحقة | D80: تكاليف تخص الفترة ولم تُدفع بعد | E80: إثبات على أساس الاستحقاق | F80: — | G80: IAS 1 | H80: عرض الالتزامات SOCPA | I80: ISA 315 / 330 | J80: فحص التسويات بعد نهاية الفترة | K80: نظام المحاسبة المالية | L80: الإفصاح عن البنود الجوهرية | O80: E,V,C | V80: (خارجي) Existence – Valuation – Completeness / (داخلي) مطابقة التسويات – الترحيل الزمني – صحة الاستحقاق
A81: المستوى الرابع | B81: 2107001 | C81: رواتب مستحقة | D81: أجور مستحقة للموظفين | E81: إثبات على أساس الاستحقاق | F81: — | G81: IAS 1 | H81: سياسات الرواتب | I81: SOCPA | J81: ISA 315 | K81: مطابقة كشوف الرواتب | L81: نظام العمل والتأمينات | M81: الإفصاح عن مستحقات العاملين | O81: E,V,C | V81: (خارجي) Existence – Valuation – Completeness / (داخلي) مطابقة كشوف الرواتب – الالتزام بنظام العمل – صحة الاستحقاق
A82: المستوى الثالث | B82: 2108 | C82: أوراق دفع | D82: سندات وشيكات مستحقة الدفع | E82: قياس بالتكلفة المطفأة | F82: IFRS 9 | G82: — | H82: سياسات الأوراق التجارية | I82: SOCPA | J82: ISA 505 | K82: مصادقات الموردين والبنوك | L82: نظام الأوراق التجارية | M82: الإفصاح عن الأوراق المرهونة | O82: E,V,C | V82: (خارجي) Existence – Valuation – Completeness / (داخلي) مطابقة الأوراق التجارية – صحة الاستحقاق – الترحيل الزمني
A83: المستوى الرابع | B83: 2108001 | C83: شيكات صادرة | D83: شيكات مستحقة الدفع | E83: قياس بالتكلفة المطفأة | F83: IFRS 9 | G83: — | H83: سياسات الدفع | I83: SOCPA | J83: ISA 505 | K83: مطابقة تواريخ الاستحقاق | L83: نظام الأوراق التجارية | M83: الإفصاح عن قيود السداد | O83: E,V,C | V83: (خارجي) Existence – Valuation – Completeness / (داخلي) مطابقة الأوراق التجارية – صحة الاستحقاق – الترحيل الزمني
A84: المستوى الثالث | B84: 2109 | C84: ضريبة القيمة المضافة | D84: ضريبة مستحقة على المبيعات (مخرجات) | E84: تسوية دورية ومطابقة الإقرارات | F84: — | G84: — | H84: دليل VAT (ZATCA) | I84: SOCPA | J84: ISA 250 | K84: مطابقة تقارير VAT بالفواتير الإلكترونية | L84: لائحة ضريبة القيمة المضافة | M84: الإفصاح عن منازعات أو غرامات | O84: E,V,P | V84: (خارجي) Existence – Valuation – Presentation / (داخلي) مطابقة الإقرارات – التوافق مع الفواتير – الامتثال لأنظمة ZATCA
A85: المستوى الرابع | B85: 2109001 | C85: ضريبة مخرجات | D85: ضريبة قيمة مضافة على المبيعات | E85: تسوية دورية مع هيئة الزكاة | F85: — | G85: — | H85: دليل VAT (ZATCA) | I85: SOCPA | J85: ISA 250 | K85: مطابقة الفواتير مع تقارير ZATCA | L85: لائحة ضريبة القيمة المضافة | M85: الإفصاح عن الديون الضريبية | O85: E,V,P | V85: (خارجي) Existence – Valuation – Presentation / (داخلي) مطابقة الإقرارات – التوافق مع الفواتير – الامتثال لأنظمة ZATCA
A86: المستوى الثالث | B86: 2110 | C86: مخصص الزكاة والضريبة | D86: مخصصات للزكاة وضريبة الدخل الحالية | E86: احتساب دوري للزكاة وضريبة الدخل | F86: — | G86: IAS 12 | H86: دليل الزكاة والضريبة | I86: SOCPA | J86: ISA 540 | K86: مطابقة الإقرارات الضريبية وإعادة الاحتساب | L86: نظام الزكاة والضريبة | M86: الإفصاح عن التسويات الضريبية | O86: E,V,P | V86: (خارجي) Existence – Valuation – Presentation / (داخلي) مطابقة الإقرارات – مراجعة الوعاء – الإفصاح عن المنازعات
A87: المستوى الرابع | B87: 2110001 | C87: زكاة مستحقة | D87: مخصص للزكاة الشرعية على المنشأة | E87: احتساب وفق الوعاء الزكوي السنوي | F87: — | G87: — | H87: دليل الزكاة | I87: ZATCA | J87: ISA 540 | K87: إعادة احتساب الوعاء الزكوي | L87: نظام الزكاة | M87: الإفصاح عن المنازعات الزكوية | O87: E,V,P | V87: (خارجي) Existence – Valuation – Presentation / (داخلي) مطابقة الوعاء الزكوي – مراجعة الاحتساب – الإفصاح عن المنازعات
A89: المستوى الثاني | B89: 22 | C89: المطلوبات غير المتداولة | D89: التزامات تُسدد بعد أكثر من 12 شهر | E89: قياس بالتكلفة المطفأة | F89: IFRS 9 | G89: IAS 1 | H89: عرض الالتزامات غير المتداولة | I89: SOCPA | J89: ISA 315 / 330 | K89: فحص آجال السداد والتصنيف | L89: نظام الشركات | M89: الإفصاح عن آجال السداد | O89: E,C,R,V,P | V89: (خارجي) جميع أهداف المراجعة / (داخلي) الالتزام بالسداد – دقة التسجيل – سلامة التصنيف
A90: المستوى الثالث | B90: 2201 | C90: مخصص مكافأة ترك الخدمة | D90: التزامات طويلة الأجل للموظفين | E90: قياس اكتواري للقيمة الحالية للالتزام | F90: — | G90: IAS 19 | H90: سياسات منافع الموظفين | I90: SOCPA | J90: ISA 540 | K90: فحص الدراسات الاكتوارية | L90: نظام العمل والتأمينات | M90: الإفصاح عن الفروض المستخدمة | O90: V,P,C | V90: (خارجي) Valuation – Presentation – Completeness / (داخلي) دقة الاحتساب – الالتزام بنظام العمل – مراجعة اكتوارية
A91: المستوى الرابع | B91: 2201001 | C91: موظفي الإدارة | D91: التزامات مكافأة ترك خدمة لفئة الإدارة | E91: احتساب على الراتب الأخير وعدد سنوات الخدمة | F91: — | G91: IAS 19 | H91: سياسات الموارد البشرية | I91: SOCPA | J91: ISA 540 | K91: مطابقة كشوف الرواتب | L91: نظام العمل والتأمينات | M91: الإفصاح عن الالتزامات الاكتوارية | O91: V,P,C | V91: (خارجي) Valuation – Presentation – Completeness / (داخلي) دقة الاحتساب – الالتزام بنظام العمل – مراجعة اكتوارية
A92: المستوى الثالث | B92: 2202 | C92: مستحق لأطراف ذات علاقة | D92: التزامات طويلة الأجل لأطراف داخل المجموعة | E92: قياس بالتكلفة المطفأة | F92: IFRS 9 | G92: IAS 24 | H92: إفصاح الأطراف ذات العلاقة | I92: SOCPA | J92: ISA 550 | K92: مراجعة اتفاقيات التمويل داخل المجموعة | L92: نظام الشركات | M92: الإفصاح عن شروط التمويل | O92: E,R,V | V92: (خارجي) Existence – Rights & Obligations – Valuation / (داخلي) مطابقة العقود – دقة الإثبات – الإفصاح عن الأطراف ذات العلاقة
A93: المستوى الرابع | B93: 2202001 | C93: شركة شقيقة أ | D93: مستحق طويل الأجل لشركة شقيقة | E93: قياس بالتكلفة المطفأة | F93: IFRS 9 | G93: IAS 24 | H93: إفصاح الأطراف ذات العلاقة | I93: SOCPA | J93: ISA 550 | K93: مطابقة مصادقات التمويل | L93: نظام الشركات | M93: الإفصاح عن العلاقة | O93: E,R,V | V93: (خارجي) Existence – Rights & Obligations – Valuation / (داخلي) دقة التسجيل – تسوية دورية – مطابقة العقود
... A106: المستوى الثاني | B106: 31 | C106: رأس المال | D106: مساهمات الملاك أو الشركاء في رأس المال | E106: إثبات عند التأسيس والزيادات والنقص | F106: IFRS 2 | G106: IAS 32 | H106: سياسات رأس المال | I106: SOCPA | J106: ISA 720 | K106: مطابقة محاضر الجمعية وسندات الإيداع | L106: نظام الشركات | M106: الإفصاح عن عدد الأسهم والقيمة الاسمية | O106: E,R,V,P | V106: (خارجي) Existence – Rights & Obligations – Valuation – Presentation / (داخلي) دقة إثبات رأس المال – الالتزام بعقود التأسيس – مطابقة محاضر الجمعيات
B107: 3101 | C107: رأس المال المدفوع | O107: E,R,V,P | V107: (خارجي) Existence – Rights & Obligations – Valuation – Presentation / (داخلي) مطابقة عقود التأسيس – إثبات الدفعات – مراجعة زيادات رأس المال
A108: المستوى الرابع | B108: 3101001 | C108: الشريك خالد | D108: حصة الشريك خالد في رأس المال | E108: إثبات بالقيمة المتفق عليها في عقد التأسيس | F108: — | G108: IAS 32 | H108: سياسات رأس المال | I108: SOCPA | J108: ISA 720 | K108: مطابقة عقود التأسيس ودفعات رأس المال | L108: نظام الشركات | M108: الإفصاح عن حقوق الشركاء | O108: E,R,V,P | V108: (خارجي) Existence – Rights & Obligations – Valuation – Presentation / (داخلي) مطابقة حصة الشريك – مراجعة دفعات رأس المال – التحقق من الملكية
A109: المستوى الرابع | B109: 3101002 | C109: الشريك فهد | D109: حصة الشريك فهد في رأس المال | E109: إثبات بالقيمة المتفق عليها في عقد التأسيس | F109: — | G109: IAS 32 | H109: سياسات رأس المال | I109: SOCPA | J109: ISA 720 | K109: مطابقة عقود التأسيس ودفعات رأس المال | L109: نظام الشركات | M109: الإفصاح عن حقوق الشركاء | O109: E,R,V,P | V109: (خارجي) Existence – Rights & Obligations – Valuation – Presentation / (داخلي) مطابقة حصة الشريك – مراجعة دفعات رأس المال – التحقق من الملكية
A110: المستوى الثاني | B110: 32 | C110: الاحتياطيات | D110: مبالغ مقتطعة من الأرباح وفق النظام أو طوعاً | E110: الاقتطاع وفق النظام الأساسي والنظام التجاري | F110: — | G110: IAS 1 | H110: لوائح التوزيعات والاحتياطيات | I110: SOCPA | J110: ISA 720 | K110: فحص قرارات الجمعية ومطابقة القيود | L110: نظام الشركات | M110: الإفصاح عن القيود على التوزيع | O110: E,V,P | V110: (خارجي) Existence – Valuation – Presentation / (داخلي) دقة تكوين الاحتياطيات – الالتزام بالأنظمة – الإفصاح عن القيود على التوزيع
O111: E,V,P | V111: (خارجي) Existence – Valuation – Presentation / (داخلي) التحقق من اقتطاع النسبة النظامية – مطابقة محاضر الجمعيات – صحة الرصيد المتراكم
A112: المستوى الرابع | B112: 3201001 | C112: احتياطي نظامي عام | D112: احتياطي يُقتطع قانوناً من صافي الربح | E112: الاقتطاع بنسبة 10% حتى يبلغ 30% من رأس المال | F112: — | G112: IAS 1 | H112: لوائح الاحتياطيات | I112: SOCPA | J112: ISA 720 | K112: مراجعة محاضر الجمعية | L112: نظام الشركات | M112: الإفصاح عن الرصيد المتراكم | O112: E,V,P | V112: (خارجي) Existence – Valuation – Presentation / (داخلي) التحقق من اقتطاع النسبة النظامية – مطابقة محاضر الجمعيات – صحة الرصيد المتراكم
O113: E,V,P | V113: (خارجي) Existence – Valuation – Presentation / (داخلي) التحقق من قرار الجمعية – صحة القيود المحاسبية – الإفصاح عن سبب التكوين
A114: المستوى الرابع | B114: 3202001 | C114: احتياطي اختياري عام | D114: احتياطي يقرره الشركاء أو الجمعية | E114: الاقتطاع حسب قرار الجمعية | F114: — | G114: IAS 1 | H114: لوائح الاحتياطيات | I114: SOCPA | J114: ISA 720 | K114: مطابقة محاضر الجمعية العامة | L114: نظام الشركات | M114: الإفصاح عن سبب تكوينه | O114: E,V,P | V114: (خارجي) Existence – Valuation – Presentation / (داخلي) التحقق من قرار الجمعية – صحة القيود المحاسبية – الإفصاح عن سبب التكوين
O115: E,V,P | V115: (خارجي) Existence – Valuation – Presentation / (داخلي) مطابقة محاضر الجمعية – الإفصاح عن الاستخدامات – مراجعة القيود المحاسبية
A116: المستوى الرابع | B116: 3203001 | C116: احتياطي طوارئ | D116: احتياطي لتغطية المخاطر المستقبلية | E116: يُكوَّن بقرار من الجمعية العامة | F116: — | G116: IAS 1 | H116: لوائح الاحتياطيات | I116: SOCPA | J116: ISA 720 | K116: مراجعة قرار الجمعية | L116: نظام الشركات | M116: الإفصاح عن استخداماته وشروطه | O116: E,V,P | V116: (خارجي) Existence – Valuation – Presentation / (داخلي) مطابقة محاضر الجمعية – الإفصاح عن الاستخدامات – مراجعة القيود المحاسبية
A117: المستوى الثاني | B117: 33 | C117: رأس المال الإضافي | D117: زيادات في حقوق الملكية بخلاف رأس المال الأصلي | E117: إثبات الإصدارات أو المنح وفق الحكم المحاسبي | F117: IFRS 2 | G117: IAS 1 | H117: سياسات حقوق الملكية | I117: SOCPA | J117: ISA 720 | K117: مراجعة قرارات الإصدار والتقييم | L117: هيئة السوق المالية | M117: الإفصاح عن شروط الإصدارات | O117: E,V,P | V117: (خارجي) Existence – Valuation – Presentation / (داخلي) مطابقة قرارات الزيادة – صحة التقييم – الإفصاح عن شروط الإصدار
O118: E,V,P | V118: (خارجي) Existence – Valuation – Presentation / (داخلي) دقة احتساب العلاوة – مطابقة عقود الإصدار – الإفصاح عن شروط الزيادة
A119: المستوى الرابع | B119: 3301001 | C119: إصدار أسهم إضافي | D119: قيمة إصدار أسهم فوق القيمة الاسمية | E119: إثبات الفائض في رأس المال الإضافي | F119: IFRS 2 | G119: IAS 1 | H119: سياسات إصدار الأسهم | I119: SOCPA | J119: ISA 720 | K119: مطابقة عقود الإصدار | L119: هيئة السوق المالية | M119: الإفصاح عن علاوة الإصدار | O119: E,V,P | V119: (خارجي) Existence – Valuation – Presentation / (داخلي) دقة احتساب العلاوة – مطابقة عقود الإصدار – الإفصاح عن شروط الزيادة
A120: المستوى الثاني | B120: 34 | C120: صافي الأرباح المبقاة | D120: أرباح لم توزع ومتبقية في المنشأة | E120: ترحيل صافي الربح/الخسارة واعتمادات النظامية | F120: — | G120: IAS 1 | H120: عرض الأرباح المبقاة | I120: SOCPA | J120: ISA 710 | K120: مطابقة أرصدة بداية الفترة مع نهاية الفترة السابقة | L120: نظام الشركات | M120: الإفصاح عن القيود على التوزيع | O120: E,V,P | V120: (خارجي) Existence – Valuation – Presentation / (داخلي) مطابقة أرصدة الفترات السابقة – دقة الترحيل – الالتزام بقرارات الجمعية
O121: E,V,P | V121: (خارجي) Existence – Valuation – Presentation / (داخلي) مطابقة أرصدة الفترات السابقة – دقة الترحيل – الالتزام بقرارات الجمعية
A122: المستوى الرابع | B122: 3401001 | C122: أرباح سنوات سابقة | D122: أرباح مترحلة من فترات مالية سابقة | E122: ترحيل وفق قرارات الجمعية العامة | F122: — | G122: IAS 1 | H122: سياسات توزيع الأرباح | I122: SOCPA | J122: ISA 710 | K122: فحص محاضر الجمعية العامة السابقة | L122: نظام الشركات | M122: الإفصاح عن الرصيد المتاح للتوزيع | O122: E,V,P | V122: (خارجي) Existence – Valuation – Presentation / (داخلي) مطابقة أرصدة الفترات السابقة – دقة الترحيل – الالتزام بقرارات الجمعية
O123: E,V,P | V123: (خارجي) Existence – Valuation – Presentation / (داخلي) مطابقة محاضر الجمعية – دقة الاحتساب – الإفصاح عن البنود الجوهرية
O124: E,V,P | V124: (خارجي) Existence – Valuation – Presentation / (داخلي) مطابقة محاضر الجمعية – دقة الاحتساب – الإفصاح عن البنود الجوهرية
O125: رمز الهدف | V125: الأهداف المرتبطة
A126: المستوى الأول | B126: 4 | C126: الإيرادات | D126: الدخل المتحقق من الأنشطة العادية للمنشأة | E126: الاعتراف عند نقل السيطرة على السلع/الخدمات | F126: IFRS 15 | G126: — | H126: تطبيق IFRS 15 تحت إطار SOCPA | I126: SOCPA | J126: ISA 240 / 330 / 520 | K126: اختبارات القطع ومطابقة الفواتير والتسليم | L126: لائحة الفوترة الإلكترونية | M126: ZATCA | N126: الإفصاح عن الالتزامات التعاقدية | O126: E,C,V,P | V126: (خارجي) Existence – Completeness – Valuation – Presentation / (داخلي) دقة تسجيل الإيرادات – الالتزام بسياسات القطع – مطابقة العقود
A127: المستوى الثاني | B127: 41 | C127: إيرادات العمليات المستمرة | D127: إيرادات النشاط الرئيسي | E127: الاعتراف عند تحقق الأداء ونقل السيطرة | F127: IFRS 15 | G127: — | H127: سياسات الاعتراف بالإيراد | I127: SOCPA | J127: ISA 240 / 330 | K127: مطابقة عقود العملاء وسندات التسليم | L127: لائحة الفوترة الإلكترونية | M127: ZATCA | N127: الإفصاح عن سياسات الإرجاع والخصم | O127: E,C,V,P | V127: (خارجي) Existence – Completeness – Valuation – Presentation / (داخلي) دقة تسجيل الإيرادات – الالتزام بالفوترة – الترحيل الزمني الصحيح
...

Sheet دليل المراجعة
A1: المستوى | B1: فاصل | C1: رقم | D1: البيان | E1: الغرض | F1: المسؤول | G1: تاريخ الإعداد | H1: تاريخ المراجعة | I1: الاستنتاج | J1: مرفقات/روابط
A2: الأول | B2: ع | C2: ع | D2: ملف عموميات | E2: تعريف عام بالعميل والمستندات الرئيسية | K2: الحقل | L2: القيمة | M2: ملاحظات
A3: الأول | B3: ن | C3: ن | D3: الملف الإداري للمراجعة | E3: إدارة العملية والاتفاقيات | K3: اسم العميل | M3: اختياري
A4: الثاني | B4: ن1 | C4: ن1-1 | D4: استقلالية فريق العمل | E4: التأكد من الاستقلال وعدم التعارض | K4: نهاية السنة المالية | L4: 31/12/2024 | M4: صيغة تاريخ
A5: الثاني | B5: ن1 | C5: ن1-2 | D5: قبول العملاء واستمرارية العلاقة (Go/No-Go) | E5: قرار قبول/استمرار موثق | K5: الإطار المحاسبي | L5: IFRS
A6: الثاني | B6: ن1 | C6: ن1-3 | D6: التواصل مع المراجع السابق | E6: الامتثال للمتطلبات المهنية | K6: الإطار المهني للمراجعة | L6: ISAs
A7: الثاني | B7: ن1 | C7: ن1-4 | D7: خطاب الارتباط/محضر التعيين | E7: تحديد نطاق ومسؤوليات المراجعة | K7: المُعدّ | M7: اسم المدقق
A8: الثالث | B8: ع2 | C8: ع2-1 | D8: استبيانات الرقابة الداخلية حسب الدورات | E8: توثيق الفهم وتقييم المخاطر | K8: المراجع | M8: اسم المدير/الشريك
A9: الثالث | B9: ع2 | C9: ع2-2 | D9: قائمة الاستقصاء (Understanding & Documentation) | E9: فهم المنشأة وبيئتها | K9: (أ) اختيار المعيار (Benchmark) | L9: الربح قبل الضريبة | M9: اختر: الربح قبل الضريبة / الإيرادات / إجمالي الأصول / حقوق الملكية / متوسط ربح 3-5 سنوات / آخر
A10: الثالث | B10: ع2 | C10: ع2-3 | D10: مكافحة غسل الأموال وتمويل الإرهاب | E10: امتثال القوانين ذات العلاقة | K10: (ب) قيمة المعيار المختار | L10: 0 | M10: أدخل رقمًا
A11: الثالث | B11: ع2 | C11: ع2-4 | D11: تقييم الدفاتر والأنظمة (متطلبات اللغة العربية) | E11: امتثال تنظيمي وتقني | K11: (ج) النسبة المختارة للأهمية الشاملة (OM) | L11: 0.05 | M11: النطاقات الشائعة: PBT 5–10%، الإيرادات 0.5–2%، الأصول 1–2%، حقوق الملكية 1%
A12: الثالث | B12: ع2 | C12: ع2-5 | D12: اختبار معالجات النظام (ITAC) – مُحدَّث | E12: ضوابط مدخلات/معالجة/مخرجات | F12: متخصص نظم | K12: الأهمية الشاملة (Overall Materiality - OM) | L12: =VALUE(SUBSTITUTE(C9,"%",""))/100 * C8 -> #VALUE! | M12: حساب تلقائي = (نسبة ج × قيمة ب)
A13: الثاني | B13: ن2 | C13: ن2-1 | D13: ميزان المراجعة العام والحسابات التحليلية | E13: قاعدة بيانات الحسابات | K13: نسبة الأهمية للأداء (Performance Materiality %) | L13: 0.6 | M13: عادةً 50–75% وفقًا للمخاطر
A14: الثاني | B14: ن2 | C14: ن2-2 | D14: مذكرة التخطيط ومخاطر المراجعة (Risk-Based) | E14: استراتيجية واستجابات المراجعة | K14: الأهمية للأداء (PM) | L14: =VALUE(SUBSTITUTE(C12,"%",""))/100 * C11 -> #VALUE! | M14: حساب تلقائي = نسبة PM × OM
A15: الثاني | B15: ن2 | C15: ن2-2-ISA240 | D15: ورقة الغش (ISA 240) | E15: تقييم مخاطر الغش وإجراءات غير متوقعة | K15: نسبة حدّ التجميع (Posting/Trivial Threshold %) | L15: 0.05 | M15: عادةً 3–10% من OM
A16: الثاني | B16: ن2 | C16: ن2-2-ISA250 | D16: القوانين والأنظمة (ISA 250) | E16: تحديد وعدم الامتثال المحتمل | K16: حدّ التجميع (Posting Threshold) | L16: =VALUE(SUBSTITUTE(C14,"%",""))/100 * C11 -> #VALUE! | M16: حساب تلقائي = نسبة × OM
A17: الثاني | B17: ن2 | C17: ن2-2-ISA260 | D17: الاتصال مع الحوكمة (ISA 260) | E17: قناة اتصال ومحتوى الاجتماعات | K17: ملاحظات قرار المعيار | M17: اذكر سبب اختيار المعيار والنسبة بالرجوع لطبيعة النشاط والمخاطر
A18: الثاني | B18: ن2 | C18: ن2-2-ISA540 | D18: التقديرات المحاسبية (ISA 540 Updated) | E18: تقييم التحيز والنطاقات الحساسة
A19: الثاني | B19: ن2 | C19: ن2-2-ISA550 | D19: الأطراف ذات العلاقة (ISA 550) | E19: تعريف واختبار المعاملات غير العادية
A20: الثاني | B20: ن2 | C20: ن2-2-ISA560 | D20: الأحداث اللاحقة (ISA 560) | E20: بحث وتقييم الأثر اللاحق
A21: الثاني | B21: ن2 | C21: ن2-2-ISA570 | D21: الاستمرارية (ISA 570) | E21: مؤشرات وشواهد وخطط الإدارة
A22: الثاني | B22: ن2 | C22: ن2-8 | D22: الأهمية النسبية والأهمية للأداء | E22: تحديد المادية وحدود التجميع | F22: مدير المراجعة
A23: الثاني | B23: ن2 | C23: ن2-8-530 | D23: المعاينة الإحصائية (ISA 530) | E23: تحديد حجم العينة وتقييم النتائج
A24: الثالث | B24: ن4 | C24: ن4-AR | D24: الذمم المدينة والمبيعات | E24: تأكيدات، Cut-off، كفاية المخصصات
A25: الثالث | B25: ن4 | C25: ن4-AP | D25: الدائنون والمشتريات | E25: مطابقات، Cut-off، التزامات محتملة
A26: الثالث | B26: ن4 | C26: ن4-INV | D26: المخزون والجرد | E26: إجراءات حضور الجرد/العدّات المفاجئة
A27: الثالث | B27: ن4 | C27: ن4-CASH | D27: النقدية والبنوك | E27: مطابقات، مصادقات، ضوابط الشيكات
A28: الثالث | B28: ن4 | C28: ن4-FA | D28: الأصول الثابتة | E28: الإضافة/الاستبعاد/الإهلاك/الهبوط
A29: الثالث | B29: ن4 | C29: ن4-REVOTH | D29: إيرادات/مصروفات أخرى | E29: تحليلات ومسوغات
A30: الثالث | B30: ن4 | C30: ن4-TAX | D30: الزكاة والضريبة وVAT/ZATCA | E30: مطابقة الإقرارات والفوترة الإلكترونية
A31: الثالث | B31: ن4 | C31: ن4-FIN | D31: الأدوات المالية | E31: IFRS 9 وخسائر ائتمانية متوقعة
A32: الثالث | B32: ن4 | C32: ن4-LIAB | D32: الالتزامات والاحتياطيات | E32: قضايا وتعهدات، التزامات محتملة
A33: الثالث | B33: ن4 | C33: ن4-EQUITY | D33: حقوق الملكية والتوزيعات | E33: امتثال نظامي ومحاضر
A34: الرابع | B34: صناعة-مقاولات | C34: IND-CONTRACTS | D34: ملف عقود المشاريع (IFRS 15) | E34: الالتزامات/VOs/Retention/WIP/تكلفة لاستكمال
... A43: الثالث | B43: ن6 | C43: ن6-CONS | D43: أوراق توحيد وترحيل فروقات | E43: إزالة التعاملات البينية والسياسات
A44: الثالث | B44: IT | C44: IT-ITGC | D44: برنامج ITGC | E44: صلاحيات، فصل واجبات، تغييرات النظام، نسخ احتياطي | F44: متخصص نظم
A45: الثالث | B45: IT | C45: IT-Reports | D45: ضوابط تقارير النظام | E45: إثبات اتساق التقارير مع الأستاذ العام
A46: الثالث | B46: REP | C46: REP-TMPL | D46: نماذج تقارير المراجع (غير/معدّل، KAMs) | E46: اتساق الصياغة مع المعايير
A47: الثالث | B47: REP | C47: REP-MNG | D47: خطاب الإدارة بالملاحظات | E47: تصنيف المخاطر وخطة المعالجة
A48: الثالث | B48: FIN | C48: FIN-POST | D48: القوائم المالية بعد الاعتماد | E48: نسخة نهائية مع إفصاحات
A49: الثالث | B49: CLS | C49: CLS-COMP | D49: استكمال المراجعة واستنتاج الشريك | E49: Checklists وإقفال الملف | F49: الشريك المسؤول
A50: الثالث | B50: ARC | C50: ARC-POL | D50: سياسة الأرشفة والاحتفاظ | E50: فترات الحفظ وإقفال التعديلات | F50: مسؤول الجودة

Sheet دليل مراحل الملف
A1: كود المرحلة | B1: المرحلة | C1: نوع المنشأة | D1: القطاع الاقتصادي | E1: الإجراء | F1: نطاق الإجراء | G1: طريقة الاختيار | H1: أمثلة الاستخدام | I1: IAS | J1: IFRS | K1: ISA | L1: السياسات ذات العلاقة | M1: الشرح التفصيلي للمرحلة | N1: النماذج الواجب تعبئتها | O1: إجراءات المراجعة العملية | P1: المخاطر المرتبطة | Q1: مستوى المخاطر | R1: الجهة المسؤولة | S1: المخرجات | T1: مدة التنفيذ | U1: نقاط القوة | V1: نقاط الضعف المحتملة | W1: مؤشرات الأداء
A2: 1 | B2: قبول العميل | E2: التحقق من نزاهة الإدارة والملاك | F2: جميع الحسابات | G2: استفسار + مستند | H2: استبيان / محاضر الاجتماعات | I2: IAS 1 | J2: IFRS 10 | K2: ISA 210 | L2: سياسة قبول العميل | M2: فحص السمعة والامتثال القانوني | N2: ✔ استبيان النزاهة ✔ خطاب قبول العميل | O2: مراجعة محاضر التأسيس – التحقق من النزاعات – الحصول على تأكيدات مكتوبة | P2: قبول عميل غير مناسب، غسل الأموال | Q2: عالي | R2: الشريك المسؤول + فريق القبول | S2: خطاب قبول | T2: قبل التعاقد | U2: تعزيز الثقة وحماية السمعة | V2: الاعتماد على بيانات العميل فقط | W2: % العملاء المقبولين بعد الفحص
A3: 1.1 | B3: تحليل خلفية العميل | E3: مراجعة الوضع القانوني | F3: السجل التجاري | G3: تحليل وثائق | H3: رخصة، سجل تجاري | I3: IAS 1 | J3: IFRS 10 | K3: ISA 210 | L3: سياسة قبول العميل | M3: التحقق من سلامة الوضع القانوني | N3: ✔ استبيان الخلفية | O3: مراجعة مستندات التسجيل والتراخيص | P3: قبول عميل غير قانوني | Q3: متوسط | R3: فريق القبول | S3: ورقة تقييم خلفية | T3: يوم | U3: توثيق قانوني | V3: نقص بيانات | W3: % اكتمال بيانات العميل
A4: 1.1.1 | B4: فحص الوضع المالي | E4: تحليل القوائم المالية | F4: بيانات مالية | G4: تحليل نسبي | H4: تحليل نسب | I4: IAS 1 | J4: IFRS 10 | K4: ISA 210 | L4: سياسة قبول العميل | M4: ضمان الملاءة المالية | N4: ✔ نموذج تقييم مالي | O4: تحليل نسب السيولة والربحية | P4: قبول عميل متعثر ماليًا | Q4: مرتفع | R4: فريق القبول | S4: ورقة عمل تحليل مالي | T4: يوم | U4: كشف مبكر للمخاطر | V4: اعتماد على أرقام غير مدققة | W4: % التقييمات المالية المكتملة
A5: 1.1.2 | B5: فحص السمعة | E5: تحقق خارجي | F5: جهات تنظيمية | G5: استفسارات | H5: محاضر / تقارير | I5: IAS 1 | J5: IFRS 10 | K5: ISA 210 | L5: سياسة قبول العميل | M5: ضمان السمعة الجيدة | N5: ✔ خطاب استفسار | O5: مراسلات رسمية – بحث في قواعد بيانات | P5: سمعة سلبية | Q5: مرتفع | R5: الشريك المسؤول | S5: تقرير سمعة | T5: يوم | U5: حماية سمعة المكتب | V5: تأخر الردود الخارجية | W5: % الردود المستلمة
A6: 1.2 | B6: توثيق قبول العميل | E6: اعتماد القبول | F6: إدارة الجودة | G6: اعتماد داخلي | H6: استمارة موافقة | I6: IAS 1 | J6: IFRS 10 | K6: ISA 210 | L6: سياسة قبول العميل | M6: اعتماد رسمي قبل التعاقد | N6: ✔ نموذج موافقة | O6: اعتماد الشريك – حفظ المستندات | P6: البدء بدون موافقة | Q6: متوسط | R6: الشريك المسؤول | S6: موافقة رسمية | T6: ساعات | U6: توثيق رسمي | V6: نسيان التوقيع | W6: % وجود موافقات موثقة
A7: 1.2.1 | B7: حفظ المستندات | E7: تجهيز الملف | F7: الملف الإلكتروني | G7: إدخال يدوي | H7: مجلد عميل | I7: IAS 1 | J7: IFRS 10 | K7: ISA 210 | L7: سياسة قبول العميل | M7: سهولة الوصول للبيانات | N7: ✔ قائمة محتويات الملف | O7: رفع المستندات للنظام | P7: ضياع مستندات | Q7: منخفض | R7: مساعد إداري | S7: ملف مكتمل | T7: يوم | U7: سهولة الاسترجاع | V7: عدم تحديث المحتوى | W7: % الملفات المكتملة
A8: 1.2.2 | B8: التأكيد مع العميل | E8: إشعار قبول | F8: البريد الرسمي | G8: إرسال بريد | H8: خطاب رسمي | I8: IAS 1 | J8: IFRS 10 | K8: ISA 210 | L8: سياسة قبول العميل | M8: إبلاغ العميل ببدء المهمة | N8: ✔ خطاب قبول | O8: إرسال بريد تأكيد | P8: بدء العمل قبل إخطار العميل | Q8: منخفض | R8: مساعد إداري | S8: بريد تأكيد | T8: ساعات | U8: شفافية | V8: نسيان الإرسال | W8: % العملاء المبلغين
A9: 2 | B9: الاستقلالية | E9: تقييم استقلال فريق المراجعة | F9: عملية المراجعة | G9: استقصاء فردي | H9: نماذج إفصاح الاستقلالية | I9: — | J9: — | K9: ISA 220 | L9: سياسة الاستقلالية | M9: ضمان موضوعية الرأي والاستقلالية المهنية | N9: ✔ نموذج إفصاح الاستقلالية ✔ سجل تضارب المصالح | O9: مراجعة تضارب المصالح وتطبيق سياسة التدوير | P9: تضارب مصالح | Q9: عالي | R9: الشريك المسؤول | S9: نموذج موقع | T9: قبل المهمة | U9: شفافية | V9: مقاومة الموظفين | W9: % النماذج المكتملة
A10: 2.1 | B10: فحص تضارب المصالح | E10: استبيان استقلالية | F10: كل الأعضاء | G10: استقصاء | H10: نموذج إفصاح | I10: — | J10: — | K10: ISA 220 | L10: سياسة الاستقلالية | M10: منع تضارب المصالح | N10: ✔ نموذج إفصاح | O10: تحليل العلاقات | P10: فقد الاستقلالية | Q10: عالي | R10: كل عضو | S10: نماذج مكتملة | T10: ساعات | U10: ضمان موضوعية | V10: رفض الإفصاح | W10: % النماذج المستلمة
A11: 2.1.1 | B11: مراجعة التعيينات السابقة | E11: تحليل مهام سابقة | F11: السجلات | G11: مراجعة سجلات | H11: كشف مهام سابقة | I11: — | J11: — | K11: ISA 220 | L11: سياسة الاستقلالية | M11: التأكد من عدم استمرار عميل سابق | N11: ✔ سجل تعيينات | O11: فحص المهام السابقة | P11: استمرار علاقات سابقة | Q11: متوسط | R11: مسؤول الجودة | S11: ورقة مراجعة | T11: يوم | U11: فصل الأدوار | V11: سهو في السجلات | W11: % المهام المفصولة
A12: 2.1.2 | B12: مراجعة العلاقات الشخصية | E12: فحص علاقات شخصية | F12: الهيكل الإداري | G12: استفسارات | H12: قائمة أسماء | I12: — | J12: — | K12: ISA 220 | L12: سياسة الاستقلالية | M12: منع تأثير العلاقات الشخصية | N12: ✔ استبيان علاقات | O12: استقصاء علاقات مباشرة | P12: تأثير شخصي | Q12: متوسط | R12: الشريك المسؤول | S12: قائمة موقعة | T12: يوم | U12: حماية الحياد | V12: كتمان الموظفين | W12: % الإفصاحات الصحيحة
A13: 2.2 | B13: اعتماد الاستقلالية | E13: توثيق الاستقلالية | F13: إدارة الجودة | G13: موافقة | H13: اعتماد داخلي | I13: — | J13: — | K13: ISA 220 | L13: سياسة الاستقلالية | M13: توثيق استقلالية الفريق | N13: ✔ سجل اعتماد | O13: مراجعة توقيعات الشريك | P13: عدم وجود موافقة | Q13: منخفض | R13: الشريك المسؤول | S13: اعتماد موقع | T13: ساعات | U13: توثيق | V13: نسيان التوقيع | W13: % الموافقات المكتملة
A14: 2.2.1 | B14: حفظ النماذج | E14: حفظ نماذج الإفصاح | F14: النظام الإلكتروني | G14: إدخال يدوي | H14: مجلد مستقل | I14: — | J14: — | K14: ISA 220 | L14: سياسة الاستقلالية | M14: سهولة الوصول لاحقًا | N14: ✔ قائمة ملفات | O14: رفع المستندات للنظام | P14: ضياع نماذج | Q14: منخفض | R14: مساعد إداري | S14: ملف مكتمل | T14: يوم | U14: سهولة الاسترجاع | V14: عدم تحديث الملف | W14: % الملفات المكتملة
A15: 2.2.2 | B15: مراجعة دورية | E15: مراجعة سنوية | F15: كل الفريق | G15: مراجعة دورية | H15: جدول متابعة | I15: — | J15: — | K15: ISA 220 | L15: سياسة الاستقلالية | M15: التحقق من استمرار الاستقلالية | N15: ✔ جدول متابعة | O15: فحص علاقات سنويًا | P15: فقد الاستقلالية | Q15: متوسط | R15: مسؤول الجودة | S15: محضر مراجعة | T15: يوم | U15: استدامة الالتزام | V15: نسيان التحديث | W15: % المراجعات السنوية
A16: 3 | B16: الأهمية النسبية | E16: تحديد مستويات الأهمية النسبية | F16: بنود القوائم المالية | G16: تحليل كمي ونوعي | H16: نسب من صافي الربح/الأصول | I16: IAS 8 | J16: IFRS 8 | K16: ISA 320 | L16: سياسة التقدير المهني | M16: تركيز الفحص على البنود الجوهرية | N16: ✔ جدول الأهمية النسبية ✔ ورقة عمل تقدير | O16: احتساب نسب من الربح/الأصول – استخدام الحكم المهني | P16: إهمال بنود جوهرية | Q16: متوسط | R16: فريق التخطيط | S16: ورقة عمل | T16: يوم | U16: تركيز الجهد | V16: تقدير غير دقيق | W16: % صحة التقديرات
A17: 3.1 | B17: تحديد العتبات | E17: تحديد نسب الأهمية | F17: القوائم المالية | G17: تحليل رقمي | H17: نسب الربح/الأصول | I17: IAS 8 | J17: IFRS 8 | K17: ISA 320 | L17: سياسة التقدير المهني | M17: حساب نسب مادية معتمدة | N17: ✔ ورقة عتبات | O17: حساب العتبات لكل بند | P17: تحديد غير ملائم | Q17: متوسط | R17: المراجع الرئيسي | S17: ورقة عمل | T17: يوم | U17: وضوح المعيار | V17: تغيرات غير مبررة | W17: % مطابقة العتبات
A18: 3.1.1 | B18: تحليل المخاطر | E18: ربط المخاطر بالأهمية | F18: كل البنود | G18: تحليل نوعي | H18: مصفوفة مخاطر | I18: IAS 8 | J18: IFRS 8 | K18: ISA 320 | L18: سياسة التقدير المهني | M18: توجيه الجهد للبنود عالية المخاطر | N18: ✔ مصفوفة مخاطر | O18: ربط كل بند بمستوى خطر | P18: تجاهل عناصر عالية المخاطر | Q18: مرتفع | R18: المراجع الرئيسي | S18: ورقة تحليل | T18: يوم | U18: تركيز الجهد | V18: تقدير خاطئ | W18: ن
A19: 3.1.2 | B19: توثيق الأحكام المهنية | E19: سجل التقديرات | F19: ورقة التقديرات | G19: توثيق يدوي | H19: مذكرة مهنية | I19: IAS 8 | J19: IFRS 8 | K19: ISA 320 | L19: سياسة التقدير المهني | M19: إثبات الأحكام المتخذة | N19: ✔ مذكرة تقديرات | O19: توثيق أسباب الاختيار | P19: صعوبة المراجعة لاحقًا | Q19: متوسط | R19: المراجع الرئيسي | S19: مذكرة موقعة | T19: يوم | U19: سهولة المراجعة | V19: نقص التفاصيل | W19: % الأوراق الموقعة
A20: 3.2 | B20: اعتماد الأهمية | E20: اعتماد داخلي | F20: إدارة الجودة | G20: موافقة | H20: نموذج اعتماد | I20: IAS 8 | J20: IFRS 8 | K20: ISA 320 | L20: سياسة التقدير المهني | M20: اعتماد رسمي للعتبات | N20: ✔ نموذج اعتماد | O20: اعتماد الشريك المسؤول | P20: البدء بدون اعتماد | Q20: منخفض | R20: الشريك المسؤول | S20: اعتماد موقّع | T20: ساعات | U20: توثيق رسمي | V20: نسيان الاعتماد | W20: % النماذج المعتمدة
A21: 3.2.1 | B21: مراجعة دورية | E21: مراجعة خلال التنفيذ | F21: البنود الجوهرية | G21: مراجعة | H21: ورقة متابعة | I21: IAS 8 | J21: IFRS 8 | K21: ISA 320 | L21: سياسة التقدير المهني | M21: ضبط الخطة حسب التغيرات | N21: ✔ ورقة متابعة | O21: مقارنة بالتنفيذ الفعلي | P21: عدم التحديث | Q21: منخفض | R21: فريق التخطيط | S21: ورقة محدثة | T21: يوم | U21: مرونة | V21: تأخر التحديث | W21: % تحديثات العتبات
A22: 3.2.2 | B22: مشاركة الفريق | E22: إعلام جميع الأعضاء | F22: الفريق كامل | G22: اجتماع | H22: عرض تقديمي | I22: IAS 8 | J22: IFRS 8 | K22: ISA 320 | L22: سياسة التقدير المهني | M22: ضمان علم جميع الفريق بالحدود | N22: ✔ محضر اجتماع | O22: عرض في الاجتماع الافتتاحي | P22: سوء تطبيق | Q22: منخفض | R22: قائد المهمة | S22: محضر حضور | T22: ساعات | U22: توحيد الفهم | V22: ضعف التركيز | W22: % الحضور المطلعين
A23: 4 | B23: تقييم الرقابة الداخلية | E23: مراجعة نظام الرقابة على النقد | F23: النقدية بالصندوق | G23: استقصاء وملاحظة | H23: استبيان / جرد مفاجئ | I23: IAS 7 | J23: IFRS 9 | K23: ISA 315 | L23: سياسة الرقابة الداخلية | M23: التأكد من وجود ضوابط تحد من الأخطاء | N23: ✔ استبيان الرقابة ✔ نموذج جرد نقدية | O23: جرد مفاجئ – مراجعة التسويات البنكية | P23: ضعف الضوابط | Q23: عالي | R23: فريق المراجعة | S23: ورقة عمل | T23: يوم | U23: كشف نقاط الضعف | V23: مقاومة الموظفين | W23: % الضوابط المختبرة
A24: 4.1 | B24: تقييم التصميم | E24: مراجعة تصميم الضوابط | F24: كل الأقسام | G24: ملاحظة واستقصاء | H24: استبيان تصميم | I24: IAS 7 | J24: IFRS 9 | K24: ISA 315 | L24: سياسة الرقابة الداخلية | M24: تحديد الفجوات في التصميم | N24: ✔ استبيان تصميم | O24: مقابلات مع مسؤولي العمليات | P24: ضوابط مصممة بشكل سيئ | Q24: عالي | R24: المراجع المساعد | S24: ورقة تقييم | T24: يوم | U24: كشف العيوب | V24: ضعف المعرفة | W24: % الفجوات المحددة
A25: 4.1.1 | B25: اختبار التنفيذ | E25: فحص تشغيل الضوابط | F25: العينات المختارة | G25: اختبار عملي | H25: فحص مستندات | I25: IAS 7 | J25: IFRS 9 | K25: ISA 315 | L25: سياسة الرقابة الداخلية | M25: التحقق من تطبيق الضوابط | N25: ✔ ورقة اختبارات | O25: فحص مستندات تنفيذ | P25: عدم الالتزام بالضوابط | Q25: عالي | R25: المراجع الميداني | S25: ورقة نتائج | T25: يوم | U25: توثيق | V25: قلة أدلة | W25: % نسبة الالتزام
A26: 4.1.2 | B26: تقييم فعالية الرقابة | E26: تحليل نتائج الاختبارات | F26: الضوابط الرئيسية | G26: تحليل | H26: ورقة تحليل | I26: IAS 7 | J26: IFRS 9 | K26: ISA 315 | L26: سياسة الرقابة الداخلية | M26: تقييم فاعلية النظام | N26: ✔ ورقة تحليل | O26: تحليل انحرافات النتائج | P26: فشل النظام | Q26: متوسط | R26: المراجع الرئيسي | S26: ورقة تقييم | T26: يوم | U26: تحسين الضوابط | V26: سوء التقدير | W26: % فعالية الضوابط
A27: 4.2 | B27: توثيق النتائج | E27: توثيق الفحص | F27: نظام الأرشفة | G27: إدخال الكتروني | H27: ملف رقابة | I27: IAS 7 | J27: IFRS 9 | K27: ISA 315 | L27: سياسة الرقابة الداخلية | M27: توثيق نتائج التقييم | N27: ✔ قائمة مرفقات | O27: إدخال النتائج في النظام | P27: فقد التوثيق | Q27: منخفض | R27: مساعد إداري | S27: ملف مكتمل | T27: ساعات | U27: سهولة الرجوع | V27: نسيان الإرفاق | W27: % الملفات المكتملة
A28: 4.2.1 | B28: اعتماد النتائج | E28: اعتماد من الشريك | F28: إدارة الجودة | G28: اعتماد | H28: نموذج توقيع | I28: IAS 7 | J28: IFRS 9 | K28: ISA 315 | L28: سياسة الرقابة الداخلية | M28: اعتماد رسمي | N28: ✔ نموذج توقيع | O28: توقيع إلكتروني | P28: غياب الاعتماد | Q28: منخفض | R28: الشريك المسؤول | S28: اعتماد موقع | T28: ساعات | U28: توثيق | V28: نسيان التوقيع | W28: % النماذج المعتمدة
A29: 4.2.2 | B29: إعداد تقرير الضوابط | E29: تقرير موجز | F29: الإدارة | G29: إصدار | H29: نموذج تقرير | I29: IAS 7 | J29: IFRS 9 | K29: ISA 315 | L29: سياسة الرقابة الداخلية | M29: تقديم النتائج للإدارة | N29: ✔ تقرير رقابة | O29: إعداد التقرير النهائي | P29: عدم تسليم التقرير | Q29: منخفض | R29: المراجع الرئيسي | S29: تقرير رقابة | T29: يوم | U29: تحسين النظام | V29: تأخير | W29: % التقارير المسلمة
A30: 5 | B30: اختبار المعالجات بالحاسب | E30: اختبار الضوابط الإلكترونية والبرامج | F30: النظام المحاسبي | G30: فحص عملي | H30: اختبار مدخلات ومخرجات | I30: IAS 1 | J30: IFRS 7 | K30: ISA 330 | L30: سياسة أمن المعلومات | M30: ضمان دقة المعالجات الآلية | N30: ✔ نموذج اختبار ✔ سجل ضوابط | O30: تجربة إدخال بيانات – فحص سجلات الاستخدام | P30: اختراق إلكتروني | Q30: عالي | R30: فريق المراجعة + IT | S30: تقرير اختبار | T30: يوم | U30: ضمان موثوقية | V30: قصور سيبراني | W30: % الثغرات المكتشفة
A31: 5.1 | B31: اختبار مدخلات النظام | E31: فحص صحة المدخلات | F31: شاشات الإدخال | G31: تجريبي | H31: إدخال بيانات تجريبية | I31: IAS 1 | J31: IFRS 7 | K31: ISA 330 | L31: سياسة أمن المعلومات | M31: التحقق من سلامة الإدخال | N31: ✔ سجل اختبار | O31: إدخال بيانات مزيفة | P31: أخطاء إدخال | Q31: عالي | R31: فريق IT | S31: ورقة نتائج | T31: ساعات | U31: تحقق دقة | V31: إدخالات ناقصة | W31: % الإدخالات الصحيحة
A32: 5.1.1 | B32: اختبار مخرجات النظام | E32: فحص تقارير النظام | F32: تقارير النظام | G32: تحليل | H32: مخرجات النظام | I32: IAS 1 | J32: IFRS 7 | K32: ISA 330 | L32: سياسة أمن المعلومات | M32: التحقق من موثوقية التقارير | N32: ✔ سجل مقارنة | O32: مقارنة بالتقارير المالية | P32: تقارير غير دقيقة | Q32: عالي | R32: فريق IT | S32: ورقة مقارنة | T32: يوم | U32: توثيق | V32: فقد بيانات | W32: % دقة المخرجات
A33: 5.1.2 | B33: اختبار ضوابط الوصول | E33: فحص المستخدمين | F33: صلاحيات النظام | G33: ملاحظة | H33: قائمة مستخدمين | I33: IAS 1 | J33: IFRS 7 | K33: ISA 330 | L33: سياسة أمن المعلومات | M33: ضمان صلاحيات مناسبة | N33: ✔ سجل وصول | O33: مراجعة الصلاحيات | P33: صلاحيات زائدة | Q33: متوسط | R33: فريق IT | S33: تقرير صلاحيات | T33: يوم | U33: حماية البيانات | V33: تأخير تحديث الصلاحيات | W33: % المستخدمين المحدثين
A34: 5.2 | B34: توثيق نتائج الاختبار | E34: إدخال النتائج | F34: النظام الإلكتروني | G34: يدوي | H34: نموذج نتائج | I34: IAS 1 | J34: IFRS 7 | K34: ISA 330 | L34: سياسة أمن المعلومات | M34: حفظ نتائج الاختبار | N34: ✔ قائمة مرفقات | O34: إدخال في النظام | P34: فقد نتائج | Q34: منخفض | R34: مساعد إداري | S34: ملف نتائج | T34: ساعات | U34: سهولة الرجوع | V34: نسيان الإرفاق | W34: % الملفات المكتملة
A35: 5.2.1 | B35: مراجعة النتائج | E35: اعتماد من المراجع | F35: المراجع الرئيسي | G35: اعتماد | H35: نموذج توقيع | I35: IAS 1 | J35: IFRS 7 | K35: ISA 330 | L35: سياسة أمن المعلومات | M35: اعتماد رسمي | N35: ✔ نموذج توقيع | O35: توقيع إلكتروني | P35: غياب الاعتماد | Q35: منخفض | R35: المراجع الرئيسي | S35: اعتماد موقع | T35: ساعات | U35: توثيق | V35: نسيان التوقيع | W35: % النماذج المعتمدة
A36: 5.2.2 | B36: تقرير الاختبار | E36: تقرير موجز | F36: الإدارة | G36: إصدار | H36: نموذج تقرير | I36: IAS 1 | J36: IFRS 7 | K36: ISA 330 | L36: سياسة أمن المعلومات | M36: إبلاغ الإدارة بالنتائج | N36: ✔ تقرير اختبار | O36: إعداد التقرير النهائي | P36: عدم تسليم التقرير | Q36: منخفض | R36: فريق المراجعة | S36: تقرير اختبار | T36: يوم | U36: تحسين النظام | V36: تأخير | W36: % التقارير المسلمة
A37: 6 | B37: المراجعة التفصيلية | E37: فحص أرصدة العملاء | F37: الذمم المدينة | G37: اختيار عينات | H37: مطابقة كشوف العملاء | I37: IAS 32 | J37: IFRS 9 | K37: ISA 505 | L37: سياسة إدارة المديونيات | M37: التأكد من صحة الأرصدة | N37: ✔ خطابات تأكيد ✔ كشف أعمار الديون | O37: طلب تأكيدات خارجية – مراجعة أعمار الديون | P37: عدم صحة الأرصدة | Q37: عالي | R37: فريق المراجعة الميدانية | S37: خطابات تأكيد | T37: يوم | U37: دليل خارجي مستقل | V37: ضعف استجابة | W37: % التأكيدات المستلمة
A38: 6.1 | B38: تأكيد الأرصدة | E38: طلب تأكيدات خارجية | F38: العملاء | G38: اختيار عينة | H38: خطابات تأكيد | I38: IAS 32 | J38: IFRS 9 | K38: ISA 505 | L38: سياسة إدارة المديونيات | M38: الحصول على تأكيدات مباشرة | N38: ✔ خطابات تأكيد | O38: إرسال ومتابعة التأكيدات | P38: عدم استجابة | Q38: عالي | R38: فريق الميدان | S38: خطابات موقعة | T38: يوم | U38: دليل خارجي | V38: ضعف الردود | W38: % الردود المستلمة
A39: 6.1.1 | B39: تحليل الأعمار | E39: مراجعة أعمار الديون | F39: كشف العملاء | G39: تحليل | H39: كشف أعمار | I39: IAS 32 | J39: IFRS 9 | K39: ISA 505 | L39: سياسة إدارة المديونيات | M39: تقييم التحصيلية | N39: ✔ كشف أعمار | O39: تحليل الديون المتأخرة | P39: عدم تكوين مخصص | Q39: عالي | R39: المراجع الرئيسي | S39: ورقة تحليل | T39: يوم | U39: كشف الديون | V39: تقدير غير دقيق | W39: % الديون المتأخرة محللة
A40: 6.1.2 | B40: مراجعة المخصصات | E40: فحص تكوين المخصصات | F40: الديون المشكوك فيها | G40: تحليل | H40: سجلات مالية | I40: IAS 32 | J40: IFRS 9 | K40: ISA 505 | L40: سياسة إدارة المديونيات | M40: التأكد من كفاية المخصص | N40: ✔ ورقة مخصص | O40: تحليل مقارنة بالماضي | P40: عدم كفاية المخصص | Q40: متوسط | R40: المراجع الرئيسي | S40: ورقة مخصص | T40: يوم | U40: تحوط مالي | V40: ضعف تقدير | W40: % كفاية المخصصات
A41: 6.2 | B41: توثيق نتائج الفحص | E41: إدخال النتائج | F41: النظام الإلكتروني | G41: يدوي | H41: ورقة نتائج | I41: IAS 32 | J41: IFRS 9 | K41: ISA 505 | L41: سياسة إدارة المديونيات | M41: حفظ النتائج | N41: ✔ قائمة نتائج | O41: إدخال في النظام | P41: فقد نتائج | Q41: منخفض | R41: مساعد إداري | S41: ملف نتائج | T41: ساعات | U41: سهولة الرجوع | V41: نسيان الإرفاق | W41: % الملفات المكتملة
A42: 6.2.1 | B42: اعتماد النتائج | E42: اعتماد من المراجع | F42: المراجع الرئيسي | G42: اعتماد | H42: نموذج توقيع | I42: IAS 32 | J42: IFRS 9 | K42: ISA 505 | L42: سياسة إدارة المديونيات | M42: اعتماد رسمي | N42: ✔ نموذج توقيع | O42: توقيع إلكتروني | P42: غياب الاعتماد | Q42: منخفض | R42: المراجع الرئيسي | S42: اعتماد موقع | T42: ساعات | U42: توثيق | V42: نسيان التوقيع | W42: % النماذج المعتمدة
A43: 6.2.2 | B43: تقرير المراجعة التفصيلية | E43: إصدار التقرير | F43: الإدارة | G43: إصدار | H43: نموذج تقرير | I43: IAS 32 | J43: IFRS 9 | K43: ISA 505 | L43: سياسة إدارة المديونيات | M43: إبلاغ الإدارة بالنتائج | N43: ✔ تقرير تفصيلي | O43: إعداد التقرير النهائي | P43: عدم تسليم التقرير | Q43: منخفض | R43: فريق المراجعة | S43: تقرير مراجعة | T43: يوم | U43: تحسين القرارات | V43: تأخير | W43: % التقارير المسلمة
A44: 7 | B44: إعداد التقرير | E44: صياغة التقرير النهائي | F44: القوائم المالية | G44: مراجعة | H44: تقرير المراجع المستقل | I44: IAS 1 | J44: IFRS Presentation | K44: ISA 700 | L44: سياسة إعداد التقارير | M44: إبداء الرأي الفني المحايد | N44: ✔ مسودة التقرير ✔ نموذج التقرير النهائي | O44: إعداد مسودة – مناقشة مع الإدارة – إصدار التقرير النهائي | P44: إصدار تقرير غير ملائم | Q44: متوسط | R44: الشريك المسؤول | S44: تقرير نهائي | T44: يوم | U44: ثقة الأطراف | V44: صعوبة التواصل | W44: % التقارير في الوقت
A45: 7.1 | B45: إعداد المسودة | E45: صياغة مسودة التقرير | F45: ورقة عمل | G45: مراجعة | H45: نموذج تقرير | I45: IAS 1 | J45: IFRS Presentation | K45: ISA 700 | L45: سياسة إعداد التقارير | M45: إعداد مسودة للعرض | N45: ✔ مسودة تقرير | O45: صياغة التقرير | P45: تأخير | Q45: متوسط | R45: المراجع الرئيسي | S45: مسودة تقرير | T45: يوم | U45: تحضير جيد | V45: كثرة تعديلات | W45: % الملاحظات المغلقة
A46: 7.1.1 | B46: مناقشة المسودة | E46: مناقشة مع الإدارة | F46: الإدارة العليا | G46: اجتماع | H46: محضر اجتماع | I46: IAS 1 | J46: IFRS Presentation | K46: ISA 700 | L46: سياسة إعداد التقارير | M46: مناقشة النتائج والآثار | N46: ✔ محضر اجتماع | O46: عرض النقاط الرئيسية | P46: سوء الفهم | Q46: متوسط | R46: الشريك المسؤول | S46: محضر موقع | T46: يوم | U46: توحيد الفهم | V46: اختلافات كبيرة | W46: % نقاط الاتفاق
A47: 7.1.2 | B47: اعتماد التقرير | E47: اعتماد نهائي | F47: إدارة الجودة | G47: اعتماد | H47: نموذج توقيع | I47: IAS 1 | J47: IFRS Presentation | K47: ISA 700 | L47: سياسة إعداد التقارير | M47: اعتماد رسمي | N47: ✔ نموذج توقيع | O47: توقيع إلكتروني | P47: غياب الاعتماد | Q47: منخفض | R47: إدارة الجودة | S47: اعتماد موقع | T47: ساعات | U47: توثيق | V47: نسيان التوقيع | W47: % النماذج المعتمدة
A48: 7.2 | B48: إصدار التقرير | E48: إصدار النسخة النهائية | F48: الإدارة العليا | G48: إصدار | H48: نسخة PDF | I48: IAS 1 | J48: IFRS Presentation | K48: ISA 700 | L48: سياسة إعداد التقارير | M48: تسليم النسخة النهائية | N48: ✔ نسخة PDF | O48: إرسال النسخة النهائية | P48: عدم التسليم | Q48: منخفض | R48: المراجع الرئيسي | S48: نسخة تقرير | T48: ساعات | U48: الامتثال للمواعيد | V48: تأخير | W48: % النسخ المسلمة
A49: 7.2.1 | B49: إبلاغ الأطراف الخارجية | E49: إرسال التقرير | F49: الجهات الخارجية | G49: إرسال | H49: بريد إلكتروني | I49: IAS 1 | J49: IFRS Presentation | K49: ISA 700 | L49: سياسة إعداد التقارير | M49: إبلاغ الجهات المعنية | N49: ✔ قائمة مرسلين | O49: إرسال التقرير | P49: عدم الاستلام | Q49: منخفض | R49: مساعد إداري | S49: إثبات إرسال | T49: ساعات | U49: شفافية | V49: تغيير البريد | W49: % الإيصالات المؤكدة
A50: 7.2.2 | B50: أرشفة التقرير | E50: حفظ نسخة التقرير | F50: ملف المهمة | G50: حفظ إلكتروني | H50: ملف PDF | I50: IAS 1 | J50: IFRS Presentation | K50: ISA 700 | L50: سياسة حفظ التقارير | M50: سهولة الرجوع لاحقًا | N50: ✔ سجل حفظ | O50: حفظ في النظام | P50: ضياع التقرير | Q50: منخفض | R50: مساعد إداري | S50: ملف محفوظ | T50: ساعات | U50: سهولة الوصول | V50: نسيان الحفظ | W50: % التقارير المحفوظة
A51: 8 | B51: الإغلاق والأرشفة | E51: أرشفة ملف المراجعة | F51: ملف المراجعة | G51: حفظ ورقي وإلكتروني | H51: أرشيف داخلي | I51: — | J51: — | K51: ISA 230 | L51: سياسة حفظ السجلات | M51: الامتثال للتشريعات | N51: ✔ قائمة أوراق العمل ✔ سجل الحفظ الإلكتروني | O51: توقيع أوراق العمل – حفظ نسخ إلكترونية وورقية – مراجعة الجودة الداخلية | P51: فقد مستندات – ضعف سرية الملفات | Q51: متوسط | R51: إدارة الجودة + مسؤول المراجعة | S51: ملف مراجعة مؤرشف | T51: بعد إصدار التقرير | U51: سهولة الرجوع لاحقًا | V51: ضعف الالتزام بمواعيد الحفظ | W51: % الملفات المؤرشفة – % الأوراق الموقعة
A52: 8.1 | B52: مراجعة استكمال الملف | E52: التحقق من اكتمال أوراق العمل | F52: ملف المراجعة | G52: مراجعة | H52: قائمة مراجعة | I52: IAS 1 | J52: IFRS 7 | K52: ISA 230 | L52: سياسة حفظ السجلات | M52: التأكد من اكتمال الأوراق والتوقيعات | N52: ✔ قائمة مراجعة | O52: مراجعة المحتويات وإقفال الملاحظات | P52: فقد مستندات | Q52: متوسط | R52: فريق المراجعة | S52: قائمة تحقق موقعة | T52: يوم | U52: ضبط الجودة | V52: سهو في الإرفاق | W52: % اكتمال الملف
A53: 8.2 | B53: إغلاق المهمة | E53: إصدار قرار الإغلاق | F53: مهمة المراجعة | G53: اعتماد | H53: نموذج إغلاق | I53: IAS 1 | J53: IFRS 7 | K53: ISA 230 | L53: سياسة حفظ السجلات | M53: اعتماد قرار الإغلاق وحفظ الملف | N53: ✔ نموذج إغلاق | O53: توثيق قرار الإغلاق النهائي | P53: عدم التوثيق | Q53: منخفض | R53: الشريك المسؤول | S53: قرار إغلاق | T53: ساعات | U53: وضوح المسؤوليات | V53: تأخر الاعتماد | W53: % المهام المغلقة

Sheet دليل اهداف المراجعة
A1: ='دليل مراحل الملف'!A1 -> كود المرحلة | B1: ='دليل مراحل الملف'!B1 -> المرحلة | C1: أسماء الأهداف المجمعة | D1: الأكواد المجمعة في المرحلة | E1: عدد الأهداف المجمعة =(عدد الاكواد المجمعة في العامود d) | F1: مجموع الوزن النسبي (%) =( مجموع التغطية في كل مرحلة)=المستهدف | G1: الإلتزام الأخلاقي والنزاهة | H1: التخطيط المهني الفعال | I1: تقييم نظام الرقابة الداخلية | J1: الحصول علي ادلة كافية وملائمة | K1: التقييم وابداء الرأي | L1: التوثيق والجودة والاسترجاع | M1: حالة التنفيذ | N1: الفعلي | O1: الفجوة % =المستهدف % (عامود F) - (الفعلي) | P1: المعاير والسياسات ذات العلاقة
G2: مدي تغطية كل مرحلة من مراحل المراجعة لاهداف المراجعة المحددة
G3: E | H3: P | I3: C | J3: A | K3: R | L3: D
G4: 15 | H4: 15 | I4: 20 | J4: 20 | K4: 15 | L4: 15 | P4: مدونة قواعد اخلاقيات المحاسبين المهنيين ومعايير الاستقلالية الدولية | Q4: السياسات | R4: IFRS | S4: IAS
A5: ='دليل مراحل الملف'!A2 -> 1 | B5: ='دليل مراحل الملف'!B2 -> قبول العميل | C5: الالتزام الأخلاقي والنزاهة ؛ التخطيط المهني الفعّال ؛ التوثيق والجودة والاسترجاع | D5: E,P,D | E5: =IF(C5="","",LEN(C5)-LEN(SUBSTITUTE(C5,"؛",""))+1) -> 3 | F5: =G5+H5+I5+J5+K5+L5 -> 0.45 | G5: =_xlfn.LET(_xlpm.s,SUBSTITUTE(TRIM($D5),"،",","), IF(ISNUMBER(SEARCH(",E,", ","&_xlpm.s&",")), 15%, 0)) -> 0.15 | H5: =_xlfn.LET(_xlpm.s,SUBSTITUTE(TRIM($D5),"،",","), IF(ISNUMBER(SEARCH(",P,", ","&_xlpm.s&",")), 15%, 0)) -> 0.15 | I5: =_xlfn.LET(_xlpm.s,SUBSTITUTE(TRIM($D5),"،",","), IF(ISNUMBER(SEARCH(",C,", ","&_xlpm.s&",")), 20%, 0)) -> 0 | J5: =_xlfn.LET(_xlpm.s,SUBSTITUTE(TRIM($D5),"،",","), IF(ISNUMBER(SEARCH(",A,", ","&_xlpm.s&",")), 20%, 0)) -> 0 | K5: =_xlfn.LET(_xlpm.s,SUBSTITUTE(TRIM($D5),"،",","), IF(ISNUMBER(SEARCH(",R,", ","&_xlpm.s&",")), 15%, 0)) -> 0 | L5: =_xlfn.LET(_xlpm.s,SUBSTITUTE(TRIM($D5),"،",","), IF(ISNUMBER(SEARCH(",D,", ","&_xlpm.s&",")), 15%, 0)) -> 0.15 | P5: ISQM 1 ؛ IESBA Code ؛ AML/KYC | Q5: IFRS 10 | R5: IAS 1 | S5: ISA 210
A6: ='دليل مراحل الملف'!A3 -> 1.1 | B6: ='دليل مراحل الملف'!B3 -> تحليل خلفية العميل | C6: الالتزام الأخلاقي والنزاهة ؛ التخطيط المهني الفعّال ؛ التوثيق والجودة والاسترجاع | D6: E,P,D | E6: =IF(C6="","",LEN(C6)-LEN(SUBSTITUTE(C6,"؛",""))+1) -> 3 | F6: =G6+H6+I6+J6+K6+L6 -> 0.45 | G6: =_xlfn.LET(_xlpm.s,SUBSTITUTE(TRIM($D6),"،",","), IF(ISNUMBER(SEARCH(",E,", ","&_xlpm.s&",")), 15%, 0)) -> 0.15 | H6: =_xlfn.LET(_xlpm.s,SUBSTITUTE(TRIM($D6),"،",","), IF(ISNUMBER(SEARCH(",P,", ","&_xlpm.s&",")), 15%, 0)) -> 0.15 | I6: =_xlfn.LET(_xlpm.s,SUBSTITUTE(TRIM($D6),"،",","), IF(ISNUMBER(SEARCH(",C,", ","&_xlpm.s&",")), 20%, 0)) -> 0 | J6: =_xlfn.LET(_xlpm.s,SUBSTITUTE(TRIM($D6),"،",","), IF(ISNUMBER(SEARCH(",A,", ","&_xlpm.s&",")), 20%, 0)) -> 0 | K6: =_xlfn.LET(_xlpm.s,SUBSTITUTE(TRIM($D6),"،",","), IF(ISNUMBER(SEARCH(",R,", ","&_xlpm.s&",")), 15%, 0)) -> 0 | L6: =_xlfn.LET(_xlpm.s,SUBSTITUTE(TRIM($D6),"،",","), IF(ISNUMBER(SEARCH(",D,", ","&_xlpm.s&",")), 15%, 0)) -> 0.15 | P6: AML/KYC ؛ ISQM 1 | Q6: IFRS 10 | R6: IAS 1 | S6: ISA 210
A7: ='دليل مراحل الملف'!A4 -> 1.1.1 | B7: ='دليل مراحل الملف'!B4 -> فحص الوضع المالي | C7: الالتزام الأخلاقي والنزاهة ؛ التخطيط المهني الفعّال ؛ التوثيق والجودة والاسترجاع | D7: E,P,D | E7: =IF(C7="","",LEN(C7)-LEN(SUBSTITUTE(C7,"؛",""))+1) -> 3 | F7: =G7+H7+I7+J7+K7+L7 -> 0.45 | G7: =_xlfn.LET(_xlpm.s,SUBSTITUTE(TRIM($D7),"،",","), IF(ISNUMBER(SEARCH(",E,", ","&_xlpm.s&",")), 15%, 0)) -> 0.15 | H7: =_xlfn.LET(_xlpm.s,SUBSTITUTE(TRIM($D7),"،",","), IF(ISNUMBER(SEARCH(",P,", ","&_xlpm.s&",")), 15%, 0)) -> 0.15 | I7: =_xlfn.LET(_xlpm.s,SUBSTITUTE(TRIM($D7),"،",","), IF(ISNUMBER(SEARCH(",C,", ","&_xlpm.s&",")), 20%, 0)) -> 0 | J7: =_xlfn.LET(_xlpm.s,SUBSTITUTE(TRIM($D7),"،",","), IF(ISNUMBER(SEARCH(",A,", ","&_xlpm.s&",")), 20%, 0)) -> 0 | K7: =_xlfn.LET(_xlpm.s,SUBSTITUTE(TRIM($D7),"،",","), IF(ISNUMBER(SEARCH(",R,", ","&_xlpm.s&",")), 15%, 0)) -> 0 | L7: =_xlfn.LET(_xlpm.s,SUBSTITUTE(TRIM($D7),"،",","), IF(ISNUMBER(SEARCH(",D,", ","&_xlpm.s&",")), 15%, 0)) -> 0.15 | P7: ISQM 1 | Q7: IFRS 10 | R7: IAS 1 | S7: ISA 210
A8: ='دليل مراحل الملف'!A5 -> 1.1.2 | B8: ='دليل مراحل الملف'!B5 -> فحص السمعة | C8: الالتزام الأخلاقي والنزاهة ؛ التخطيط المهني الفعّال ؛ التوثيق والجودة والاسترجاع | D8: E,P,D | E8: =IF(C8="","",LEN(C8)-LEN(SUBSTITUTE(C8,"؛",""))+1) -> 3 | F8: =G8+H8+I8+J8+K8+L8 -> 0.45 | G8: =_xlfn.LET(_xlpm.s,SUBSTITUTE(TRIM($D8),"،",","), IF(ISNUMBER(SEARCH(",E,", ","&_xlpm.s&",")), 15%, 0)) -> 0.15 | H8: =_xlfn.LET(_xlpm.s,SUBSTITUTE(TRIM($D8),"،",","), IF(ISNUMBER(SEARCH(",P,", ","&_xlpm.s&",")), 15%, 0)) -> 0.15 | I8: =_xlfn.LET(_xlpm.s,SUBSTITUTE(TRIM($D8),"،",","), IF(ISNUMBER(SEARCH(",C,", ","&_xlpm.s&",")), 20%, 0)) -> 0 | J8: =_xlfn.LET(_xlpm.s,SUBSTITUTE(TRIM($D8),"،",","), IF(ISNUMBER(SEARCH(",A,", ","&_xlpm.s&",")), 20%, 0)) -> 0 | K8: =_xlfn.LET(_xlpm.s,SUBSTITUTE(TRIM($D8),"،",","), IF(ISNUMBER(SEARCH(",R,", ","&_xlpm.s&",")), 15%, 0)) -> 0 | L8: =_xlfn.LET(_xlpm.s,SUBSTITUTE(TRIM($D8),"،",","), IF(ISNUMBER(SEARCH(",D,", ","&_xlpm.s&",")), 15%, 0)) -> 0.15 | P8: IESBA Code ؛ AML/KYC | Q8: IFRS 10 | R8: IAS 1 | S8: ISA 210
A9: ='دليل مراحل الملف'!A6 -> 1.2 | B9: ='دليل مراحل الملف'!B6 -> توثيق قبول العميل | C9: الالتزام الأخلاقي والنزاهة ؛ التخطيط المهني الفعّال ؛ التوثيق والجودة والاسترجاع | D9: E,P,D | E9: =IF(C9="","",LEN(C9)-LEN(SUBSTITUTE(C9,"؛",""))+1) -> 3 | F9: =G9+H9+I9+J9+K9+L9 -> 0.45 | G9: =_xlfn.LET(_xlpm.s,SUBSTITUTE(TRIM($D9),"،",","), IF(ISNUMBER(SEARCH(",E,", ","&_xlpm.s&",")), 15%, 0)) -> 0.15 | H9: =_xlfn.LET(_xlpm.s,SUBSTITUTE(TRIM($D9),"،",","), IF(ISNUMBER(SEARCH(",P,", ","&_xlpm.s&",")), 15%, 0)) -> 0.15 | I9: =_xlfn.LET(_xlpm.s,SUBSTITUTE(TRIM($D9),"،",","), IF(ISNUMBER(SEARCH(",C,", ","&_xlpm.s&",")), 20%, 0)) -> 0 | J9: =_xlfn.LET(_xlpm.s,SUBSTITUTE(TRIM($D9),"،",","), IF(ISNUMBER(SEARCH(",A,", ","&_xlpm.s&",")), 20%, 0)) -> 0 | K9: =_xlfn.LET(_xlpm.s,SUBSTITUTE(TRIM($D9),"،",","), IF(ISNUMBER(SEARCH(",R,", ","&_xlpm.s&",")), 15%, 0)) -> 0 | L9: =_xlfn.LET(_xlpm.s,SUBSTITUTE(TRIM($D9),"،",","), IF(ISNUMBER(SEARCH(",D,", ","&_xlpm.s&",")), 15%, 0)) -> 0.15 | P9: ISQM 1 | S9: ISA 210
A10: ='دليل مراحل الملف'!A7 -> 1.2.1 | B10: ='دليل مراحل الملف'!B7 -> حفظ المستندات | C10: الالتزام الأخلاقي والنزاهة ؛ التخطيط المهني الفعّال ؛ التوثيق والجودة والاسترجاع | D10: E,P,D | E10: =IF(C10="","",LEN(C10)-LEN(SUBSTITUTE(C10,"؛",""))+1) -> 3 | F10: =G10+H10+I10+J10+K10+L10 -> 0.45 | G10: =_xlfn.LET(_xlpm.s,SUBSTITUTE(TRIM($D10),"،",","), IF(ISNUMBER(SEARCH(",E,", ","&_xlpm.s&",")), 15%, 0)) -> 0.15 | H10: =_xlfn.LET(_xlpm.s,SUBSTITUTE(TRIM($D10),"،",","), IF(ISNUMBER(SEARCH(",P,", ","&_xlpm.s&",")), 15%, 0)) -> 0.15 | I10: =_xlfn.LET(_xlpm.s,SUBSTITUTE(TRIM($D10),"،",","), IF(ISNUMBER(SEARCH(",C,", ","&_xlpm.s&",")), 20%, 0)) -> 0 | J10: =_xlfn.LET(_xlpm.s,SUBSTITUTE(TRIM($D10),"،",","), IF(ISNUMBER(SEARCH(",A,", ","&_xlpm.s&",")), 20%, 0)) -> 0 | K10: =_xlfn.LET(_xlpm.s,SUBSTITUTE(TRIM($D10),"،",","), IF(ISNUMBER(SEARCH(",R,", ","&_xlpm.s&",")), 15%, 0)) -> 0 | L10: =_xlfn.LET(_xlpm.s,SUBSTITUTE(TRIM($D10),"،",","), IF(ISNUMBER(SEARCH(",D,", ","&_xlpm.s&",")), 15%, 0)) -> 0.15 | P10: ISQM 1 ؛ AML/KYC | S10: ISA 210
A11: ='دليل مراحل الملف'!A8 -> 1.2.2 | B11: ='دليل مراحل الملف'!B8 -> التأكيد مع العميل | C11: الالتزام الأخلاقي والنزاهة ؛ التخطيط المهني الفعّال ؛ التوثيق والجودة والاسترجاع | D11: E,P,D | E11: =IF(C11="","",LEN(C11)-LEN(SUBSTITUTE(C11,"؛",""))+1) -> 3 | F11: =G11+H11+I11+J11+K11+L11 -> 0.45 | G11: =_xlfn.LET(_xlpm.s,SUBSTITUTE(TRIM($D11),"،",","), IF(ISNUMBER(SEARCH(",E,", ","&_xlpm.s&",")), 15%, 0)) -> 0.15 | H11: =_xlfn.LET(_xlpm.s,SUBSTITUTE(TRIM($D11),"،",","), IF(ISNUMBER(SEARCH(",P,", ","&_xlpm.s&",")), 15%, 0)) -> 0.15 | I11: =_xlfn.LET(_xlpm.s,SUBSTITUTE(TRIM($D11),"،",","), IF(ISNUMBER(SEARCH(",C,", ","&_xlpm.s&",")), 20%, 0)) -> 0 | J11: =_xlfn.LET(_xlpm.s,SUBSTITUTE(TRIM($D11),"،",","), IF(ISNUMBER(SEARCH(",A,", ","&_xlpm.s&",")), 20%, 0)) -> 0 | K11: =_xlfn.LET(_xlpm.s,SUBSTITUTE(TRIM($D11),"،",","), IF(ISNUMBER(SEARCH(",R,", ","&_xlpm.s&",")), 15%, 0)) -> 0 | L11: =_xlfn.LET(_xlpm.s,SUBSTITUTE(TRIM($D11),"،",","), IF(ISNUMBER(SEARCH(",D,", ","&_xlpm.s&",")), 15%, 0)) -> 0.15 | P11: ISQM 1 | S11: ISA 210
A12: ='دليل مراحل الملف'!A9 -> 2 | B12: ='دليل مراحل الملف'!B9 -> الاستقلالية | C12: الالتزام الأخلاقي والنزاهة ؛ التوثيق والجودة والاسترجاع | D12: E,D | E12: =IF(C12="","",LEN(C12)-LEN(SUBSTITUTE(C12,"؛",""))+1) -> 2 | F12: =G12+H12+I12+J12+K12+L12 -> 0.3 | G12: =_xlfn.LET(_xlpm.s,SUBSTITUTE(TRIM($D12),"،",","), IF(ISNUMBER(SEARCH(",E,", ","&_xlpm.s&",")), 15%, 0)) -> 0.15 | H12: =_xlfn.LET(_xlpm.s,SUBSTITUTE(TRIM($D12),"،",","), IF(ISNUMBER(SEARCH(",P,", ","&_xlpm.s&",")), 15%, 0)) -> 0 | I12: =_xlfn.LET(_xlpm.s,SUBSTITUTE(TRIM($D12),"،",","), IF(ISNUMBER(SEARCH(",C,", ","&_xlpm.s&",")), 20%, 0)) -> 0 | J12: =_xlfn.LET(_xlpm.s,SUBSTITUTE(TRIM($D12),"،",","), IF(ISNUMBER(SEARCH(",A,", ","&_xlpm.s&",")), 20%, 0)) -> 0 | K12: =_xlfn.LET(_xlpm.s,SUBSTITUTE(TRIM($D12),"،",","), IF(ISNUMBER(SEARCH(",R,", ","&_xlpm.s&",")), 15%, 0)) -> 0 | L12: =_xlfn.LET(_xlpm.s,SUBSTITUTE(TRIM($D12),"،",","), IF(ISNUMBER(SEARCH(",D,", ","&_xlpm.s&",")), 15%, 0)) -> 0.15 | P12: ISQM 1 ؛ IESBA Code | S12: ISA 220
A13: ='دليل مراحل الملف'!A10 -> 2.1 | B13: ='دليل مراحل الملف'!B10 -> فحص تضارب المصالح | C13: الالتزام الأخلاقي والنزاهة ؛ التوثيق والجودة والاسترجاع | D13: E,D | E13: =IF(C13="","",LEN(C13)-LEN(SUBSTITUTE(C13,"؛",""))+1) -> 2 | F13: =G13+H13+I13+J13+K13+L13 -> 0.3 | G13: =_xlfn.LET(_xlpm.s,SUBSTITUTE(TRIM($D13),"،",","), IF(ISNUMBER(SEARCH(",E,", ","&_xlpm.s&",")), 15%, 0)) -> 0.15 | H13: =_xlfn.LET(_xlpm.s,SUBSTITUTE(TRIM($D13),"،",","), IF(ISNUMBER(SEARCH(",P,", ","&_xlpm.s&",")), 15%, 0)) -> 0 | I13: =_xlfn.LET(_xlpm.s,SUBSTITUTE(TRIM($D13),"،",","), IF(ISNUMBER(SEARCH(",C,", ","&_xlpm.s&",")), 20%, 0)) -> 0 | J13: =_xlfn.LET(_xlpm.s,SUBSTITUTE(TRIM($D13),"،",","), IF(ISNUMBER(SEARCH(",A,", ","&_xlpm.s&",")), 20%, 0)) -> 0 | K13: =_xlfn.LET(_xlpm.s,SUBSTITUTE(TRIM($D13),"،",","), IF(ISNUMBER(SEARCH(",R,", ","&_xlpm.s&",")), 15%, 0)) -> 0 | L13: =_xlfn.LET(_xlpm.s,SUBSTITUTE(TRIM($D13),"،",","), IF(ISNUMBER(SEARCH(",D,", ","&_xlpm.s&",")), 15%, 0)) -> 0.15 | P13: IESBA Code | S13: ISA 220
A14: ='دليل مراحل الملف'!A11 -> 2.1.1 | B14: ='دليل مراحل الملف'!B11 -> مراجعة التعيينات السابقة | C14: الالتزام الأخلاقي والنزاهة ؛ التوثيق والجودة والاسترجاع | D14: E,D | E14: =IF(C14="","",LEN(C14)-LEN(SUBSTITUTE(C14,"؛",""))+1) -> 2 | F14: =G14+H14+I14+J14+K14+L14 -> 0.3 | G14: =_xlfn.LET(_xlpm.s,SUBSTITUTE(TRIM($D14),"،",","), IF(ISNUMBER(SEARCH(",E,", ","&_xlpm.s&",")), 15%, 0)) -> 0.15 | H14: =_xlfn.LET(_xlpm.s,SUBSTITUTE(TRIM($D14),"،",","), IF(ISNUMBER(SEARCH(",P,", ","&_xlpm.s&",")), 15%, 0)) -> 0 | I14: =_xlfn.LET(_xlpm.s,SUBSTITUTE(TRIM($D14),"،",","), IF(ISNUMBER(SEARCH(",C,", ","&_xlpm.s&",")), 20%, 0)) -> 0 | J14: =_xlfn.LET(_xlpm.s,SUBSTITUTE(TRIM($D14),"،",","), IF(ISNUMBER(SEARCH(",A,", ","&_xlpm.s&",")), 20%, 0)) -> 0 | K14: =_xlfn.LET(_xlpm.s,SUBSTITUTE(TRIM($D14),"،",","), IF(ISNUMBER(SEARCH(",R,", ","&_xlpm.s&",")), 15%, 0)) -> 0 | L14: =_xlfn.LET(_xlpm.s,SUBSTITUTE(TRIM($D14),"،",","), IF(ISNUMBER(SEARCH(",D,", ","&_xlpm.s&",")), 15%, 0)) -> 0.15 | P14: IESBA Code | S14: ISA 220
A15: ='دليل مراحل الملف'!A12 -> 2.1.2 | B15: ='دليل مراحل الملف'!B12 -> مراجعة العلاقات الشخصية | C15: الالتزام الأخلاقي والنزاهة ؛ التوثيق والجودة والاسترجاع | D15: E,D | E15: =IF(C15="","",LEN(C15)-LEN(SUBSTITUTE(C15,"؛",""))+1) -> 2 | F15: =G15+H15+I15+J15+K15+L15 -> 0.3 | G15: =_xlfn.LET(_xlpm.s,SUBSTITUTE(TRIM($D15),"،",","), IF(ISNUMBER(SEARCH(",E,", ","&_xlpm.s&",")), 15%, 0)) -> 0.15 | H15: =_xlfn.LET(_xlpm.s,SUBSTITUTE(TRIM($D15),"،",","), IF(ISNUMBER(SEARCH(",P,", ","&_xlpm.s&",")), 15%, 0)) -> 0 | I15: =_xlfn.LET(_xlpm.s,SUBSTITUTE(TRIM($D15),"،",","), IF(ISNUMBER(SEARCH(",C,", ","&_xlpm.s&",")), 20%, 0)) -> 0 | J15: =_xlfn.LET(_xlpm.s,SUBSTITUTE(TRIM($D15),"،",","), IF(ISNUMBER(SEARCH(",A,", ","&_xlpm.s&",")), 20%, 0)) -> 0 | K15: =_xlfn.LET(_xlpm.s,SUBSTITUTE(TRIM($D15),"،",","), IF(ISNUMBER(SEARCH(",R,", ","&_xlpm.s&",")), 15%, 0)) -> 0 | L15: =_xlfn.LET(_xlpm.s,SUBSTITUTE(TRIM($D15),"،",","), IF(ISNUMBER(SEARCH(",D,", ","&_xlpm.s&",")), 15%, 0)) -> 0.15 | P15: IESBA Code | S15: ISA 220
A16: ='دليل مراحل الملف'!A13 -> 2.2 | B16: ='دليل مراحل الملف'!B13 -> اعتماد الاستقلالية | C16: الالتزام الأخلاقي والنزاهة ؛ التوثيق والجودة والاسترجاع | D16: E,D | E16: =IF(C16="","",LEN(C16)-LEN(SUBSTITUTE(C16,"؛",""))+1) -> 2 | F16: =G16+H16+I16+J16+K16+L16 -> 0.3 | G16: =_xlfn.LET(_xlpm.s,SUBSTITUTE(TRIM($D16),"،",","), IF(ISNUMBER(SEARCH(",E,", ","&_xlpm.s&",")), 15%, 0)) -> 0.15 | H16: =_xlfn.LET(_xlpm.s,SUBSTITUTE(TRIM($D16),"،",","), IF(ISNUMBER(SEARCH(",P,", ","&_xlpm.s&",")), 15%, 0)) -> 0 | I16: =_xlfn.LET(_xlpm.s,SUBSTITUTE(TRIM($D16),"،",","), IF(ISNUMBER(SEARCH(",C,", ","&_xlpm.s&",")), 20%, 0)) -> 0 | J16: =_xlfn.LET(_xlpm.s,SUBSTITUTE(TRIM($D16),"،",","), IF(ISNUMBER(SEARCH(",A,", ","&_xlpm.s&",")), 20%, 0)) -> 0 | K16: =_xlfn.LET(_xlpm.s,SUBSTITUTE(TRIM($D16),"،",","), IF(ISNUMBER(SEARCH(",R,", ","&_xlpm.s&",")), 15%, 0)) -> 0 | L16: =_xlfn.LET(_xlpm.s,SUBSTITUTE(TRIM($D16),"،",","), IF(ISNUMBER(SEARCH(",D,", ","&_xlpm.s&",")), 15%, 0)) -> 0.15 | P16: ISQM 1 | S16: ISA 220
A17: ='دليل مراحل الملف'!A14 -> 2.2.1 | B17: ='دليل مراحل الملف'!B14 -> حفظ النماذج | C17: الالتزام الأخلاقي والنزاهة ؛ التوثيق والجودة والاسترجاع | D17: E,D | E17: =IF(C17="","",LEN(C17)-LEN(SUBSTITUTE(C17,"؛",""))+1) -> 2 | F17: =G17+H17+I17+J17+K17+L17 -> 0.3 | G17: =_xlfn.LET(_xlpm.s,SUBSTITUTE(TRIM($D17),"،",","), IF(ISNUMBER(SEARCH(",E,", ","&_xlpm.s&",")), 15%, 0)) -> 0.15 | H17: =_xlfn.LET(_xlpm.s,SUBSTITUTE(TRIM($D17),"،",","), IF(ISNUMBER(SEARCH(",P,", ","&_xlpm.s&",")), 15%, 0)) -> 0 | I17: =_xlfn.LET(_xlpm.s,SUBSTITUTE(TRIM($D17),"،",","), IF(ISNUMBER(SEARCH(",C,", ","&_xlpm.s&",")), 20%, 0)) -> 0 | J17: =_xlfn.LET(_xlpm.s,SUBSTITUTE(TRIM($D17),"،",","), IF(ISNUMBER(SEARCH(",A,", ","&_xlpm.s&",")), 20%, 0)) -> 0 | K17: =_xlfn.LET(_xlpm.s,SUBSTITUTE(TRIM($D17),"،",","), IF(ISNUMBER(SEARCH(",R,", ","&_xlpm.s&",")), 15%, 0)) -> 0 | L17: =_xlfn.LET(_xlpm.s,SUBSTITUTE(TRIM($D17),"،",","), IF(ISNUMBER(SEARCH(",D,", ","&_xlpm.s&",")), 15%, 0)) -> 0.15 | P17: ISQM 1 | S17: ISA 220
A18: ='دليل مراحل الملف'!A15 -> 2.2.2 | B18: ='دليل مراحل الملف'!B15 -> مراجعة دورية | C18: الالتزام الأخلاقي والنزاهة ؛ التوثيق والجودة والاسترجاع | D18: E,D | E18: =IF(C18="","",LEN(C18)-LEN(SUBSTITUTE(C18,"؛",""))+1) -> 2 | F18: =G18+H18+I18+J18+K18+L18 -> 0.3 | G18: =_xlfn.LET(_xlpm.s,SUBSTITUTE(TRIM($D18),"،",","), IF(ISNUMBER(SEARCH(",E,", ","&_xlpm.s&",")), 15%, 0)) -> 0.15 | H18: =_xlfn.LET(_xlpm.s,SUBSTITUTE(TRIM($D18),"،",","), IF(ISNUMBER(SEARCH(",P,", ","&_xlpm.s&",")), 15%, 0)) -> 0 | I18: =_xlfn.LET(_xlpm.s,SUBSTITUTE(TRIM($D18),"،",","), IF(ISNUMBER(SEARCH(",C,", ","&_xlpm.s&",")), 20%, 0)) -> 0 | J18: =_xlfn.LET(_xlpm.s,SUBSTITUTE(TRIM($D18),"،",","), IF(ISNUMBER(SEARCH(",A,", ","&_xlpm.s&",")), 20%, 0)) -> 0 | K18: =_xlfn.LET(_xlpm.s,SUBSTITUTE(TRIM($D18),"،",","), IF(ISNUMBER(SEARCH(",R,", ","&_xlpm.s&",")), 15%, 0)) -> 0 | L18: =_xlfn.LET(_xlpm.s,SUBSTITUTE(TRIM($D18),"،",","), IF(ISNUMBER(SEARCH(",D,", ","&_xlpm.s&",")), 15%, 0)) -> 0.15 | P18: ISQM 1 | S18: ISA 220
A19: ='دليل مراحل الملف'!A16 -> 3 | B19: ='دليل مراحل الملف'!B16 -> الأهمية النسبية | C19: التخطيط المهني الفعّال ؛ التوثيق والجودة والاسترجاع | D19: P,D | E19: =IF(C19="","",LEN(C19)-LEN(SUBSTITUTE(C19,"؛",""))+1) -> 2 | F19: =G19+H19+I19+J19+K19+L19 -> 0.3 | G19: =_xlfn.LET(_xlpm.s,SUBSTITUTE(TRIM($D19),"،",","), IF(ISNUMBER(SEARCH(",E,", ","&_xlpm.s&",")), 15%, 0)) -> 0 | H19: =_xlfn.LET(_xlpm.s,SUBSTITUTE(TRIM($D19),"،",","), IF(ISNUMBER(SEARCH(",P,", ","&_xlpm.s&",")), 15%, 0)) -> 0.15 | I19: =_xlfn.LET(_xlpm.s,SUBSTITUTE(TRIM($D19),"،",","), IF(ISNUMBER(SEARCH(",C,", ","&_xlpm.s&",")), 20%, 0)) -> 0 | J19: =_xlfn.LET(_xlpm.s,SUBSTITUTE(TRIM($D19),"،",","), IF(ISNUMBER(SEARCH(",A,", ","&_xlpm.s&",")), 20%, 0)) -> 0 | K19: =_xlfn.LET(_xlpm.s,SUBSTITUTE(TRIM($D19),"،",","), IF(ISNUMBER(SEARCH(",R,", ","&_xlpm.s&",")), 15%, 0)) -> 0 | L19: =_xlfn.LET(_xlpm.s,SUBSTITUTE(TRIM($D19),"،",","), IF(ISNUMBER(SEARCH(",D,", ","&_xlpm.s&",")), 15%, 0)) -> 0.15 | P19: ISQM 1 | Q19: IFRS 8 | R19: IAS 8 | S19: ISA 320
A20: ='دليل مراحل الملف'!A17 -> 3.1 | B20: ='دليل مراحل الملف'!B17 -> تحديد العتبات | C20: التخطيط المهني الفعّال ؛ التوثيق والجودة والاسترجاع | D20: P,D | E20: =IF(C20="","",LEN(C20)-LEN(SUBSTITUTE(C20,"؛",""))+1) -> 2 | F20: =G20+H20+I20+J20+K20+L20 -> 0.3 | G20: =_xlfn.LET(_xlpm.s,SUBSTITUTE(TRIM($D20),"،",","), IF(ISNUMBER(SEARCH(",E,", ","&_xlpm.s&",")), 15%, 0)) -> 0 | H20: =_xlfn.LET(_xlpm.s,SUBSTITUTE(TRIM($D20),"،",","), IF(ISNUMBER(SEARCH(",P,", ","&_xlpm.s&",")), 15%, 0)) -> 0.15 | I20: =_xlfn.LET(_xlpm.s,SUBSTITUTE(TRIM($D20),"،",","), IF(ISNUMBER(SEARCH(",C,", ","&_xlpm.s&",")), 20%, 0)) -> 0 | J20: =_xlfn.LET(_xlpm.s,SUBSTITUTE(TRIM($D20),"،",","), IF(ISNUMBER(SEARCH(",A,", ","&_xlpm.s&",")), 20%, 0)) -> 0 | K20: =_xlfn.LET(_xlpm.s,SUBSTITUTE(TRIM($D20),"،",","), IF(ISNUMBER(SEARCH(",R,", ","&_xlpm.s&",")), 15%, 0)) -> 0 | L20: =_xlfn.LET(_xlpm.s,SUBSTITUTE(TRIM($D20),"،",","), IF(ISNUMBER(SEARCH(",D,", ","&_xlpm.s&",")), 15%, 0)) -> 0.15 | Q20: IFRS 8 | R20: IAS 8 | S20: ISA 320
A21: ='دليل مراحل الملف'!A18 -> 3.1.1 | B21: ='دليل مراحل الملف'!B18 -> تحليل المخاطر | C21: التخطيط المهني الفعّال ؛ التوثيق والجودة والاسترجاع | D21: P,D | E21: =IF(C21="","",LEN(C21)-LEN(SUBSTITUTE(C21,"؛",""))+1) -> 2 | F21: =G21+H21+I21+J21+K21+L21 -> 0.3 | G21: =_xlfn.LET(_xlpm.s,SUBSTITUTE(TRIM($D21),"،",","), IF(ISNUMBER(SEARCH(",E,", ","&_xlpm.s&",")), 15%, 0)) -> 0 | H21: =_xlfn.LET(_xlpm.s,SUBSTITUTE(TRIM($D21),"،",","), IF(ISNUMBER(SEARCH(",P,", ","&_xlpm.s&",")), 15%, 0)) -> 0.15 | I21: =_xlfn.LET(_xlpm.s,SUBSTITUTE(TRIM($D21),"،",","), IF(ISNUMBER(SEARCH(",C,", ","&_xlpm.s&",")), 20%, 0)) -> 0 | J21: =_xlfn.LET(_xlpm.s,SUBSTITUTE(TRIM($D21),"،",","), IF(ISNUMBER(SEARCH(",A,", ","&_xlpm.s&",")), 20%, 0)) -> 0 | K21: =_xlfn.LET(_xlpm.s,SUBSTITUTE(TRIM($D21),"،",","), IF(ISNUMBER(SEARCH(",R,", ","&_xlpm.s&",")), 15%, 0)) -> 0 | L21: =_xlfn.LET(_xlpm.s,SUBSTITUTE(TRIM($D21),"،",","), IF(ISNUMBER(SEARCH(",D,", ","&_xlpm.s&",")), 15%, 0)) -> 0.15 | P21: COSO | S21: ISA 315 ؛ ISA 320
A22: ='دليل مراحل الملف'!A19 -> 3.1.2 | B22: ='دليل مراحل الملف'!B19 -> توثيق الأحكام المهنية | C22: التخطيط المهني الفعّال ؛ التوثيق والجودة والاسترجاع | D22: P,D | E22: =IF(C22="","",LEN(C22)-LEN(SUBSTITUTE(C22,"؛",""))+1) -> 2 | F22: =G22+H22+I22+J22+K22+L22 -> 0.3 | G22: =_xlfn.LET(_xlpm.s,SUBSTITUTE(TRIM($D22),"،",","), IF(ISNUMBER(SEARCH(",E,", ","&_xlpm.s&",")), 15%, 0)) -> 0 | H22: =_xlfn.LET(_xlpm.s,SUBSTITUTE(TRIM($D22),"،",","), IF(ISNUMBER(SEARCH(",P,", ","&_xlpm.s&",")), 15%, 0)) -> 0.15 | I22: =_xlfn.LET(_xlpm.s,SUBSTITUTE(TRIM($D22),"،",","), IF(ISNUMBER(SEARCH(",C,", ","&_xlpm.s&",")), 20%, 0)) -> 0 | J22: =_xlfn.LET(_xlpm.s,SUBSTITUTE(TRIM($D22),"،",","), IF(ISNUMBER(SEARCH(",A,", ","&_xlpm.s&",")), 20%, 0)) -> 0 | K22: =_xlfn.LET(_xlpm.s,SUBSTITUTE(TRIM($D22),"،",","), IF(ISNUMBER(SEARCH(",R,", ","&_xlpm.s&",")), 15%, 0)) -> 0 | L22: =_xlfn.LET(_xlpm.s,SUBSTITUTE(TRIM($D22),"،",","), IF(ISNUMBER(SEARCH(",D,", ","&_xlpm.s&",")), 15%, 0)) -> 0.15 | P22: ISQM 1 | S22: ISA 320
A23: ='دليل مراحل الملف'!A20 -> 3.2 | B23: ='دليل مراحل الملف'!B20 -> اعتماد الأهمية | C23: التخطيط المهني الفعّال ؛ التوثيق والجودة والاسترجاع | D23: P,D | E23: =IF(C23="","",LEN(C23)-LEN(SUBSTITUTE(C23,"؛",""))+1) -> 2 | F23: =G23+H23+I23+J23+K23+L23 -> 0.3 | G23: =_xlfn.LET(_xlpm.s,SUBSTITUTE(TRIM($D23),"،",","), IF(ISNUMBER(SEARCH(",E,", ","&_xlpm.s&",")), 15%, 0)) -> 0 | H23: =_xlfn.LET(_xlpm.s,SUBSTITUTE(TRIM($D23),"،",","), IF(ISNUMBER(SEARCH(",P,", ","&_xlpm.s&",")), 15%, 0)) -> 0.15 | I23: =_xlfn.LET(_xlpm.s,SUBSTITUTE(TRIM($D23),"،",","), IF(ISNUMBER(SEARCH(",C,", ","&_xlpm.s&",")), 20%, 0)) -> 0 | J23: =_xlfn.LET(_xlpm.s,SUBSTITUTE(TRIM($D23),"،",","), IF(ISNUMBER(SEARCH(",A,", ","&_xlpm.s&",")), 20%, 0)) -> 0 | K23: =_xlfn.LET(_xlpm.s,SUBSTITUTE(TRIM($D23),"،",","), IF(ISNUMBER(SEARCH(",R,", ","&_xlpm.s&",")), 15%, 0)) -> 0 | L23: =_xlfn.LET(_xlpm.s,SUBSTITUTE(TRIM($D23),"،",","), IF(ISNUMBER(SEARCH(",D,", ","&_xlpm.s&",")), 15%, 0)) -> 0.15 | P23: ISQM 2 | S23: ISA 320
A24: ='دليل مراحل الملف'!A21 -> 3.2.1 | B24: ='دليل مراحل الملف'!B21 -> مراجعة دورية | C24: التخطيط المهني الفعّال ؛ التوثيق والجودة والاسترجاع | D24: P,D | E24: =IF(C24="","",LEN(C24)-LEN(SUBSTITUTE(C24,"؛",""))+1) -> 2 | F24: =G24+H24+I24+J24+K24+L24 -> 0.3 | G24: =_xlfn.LET(_xlpm.s,SUBSTITUTE(TRIM($D24),"،",","), IF(ISNUMBER(SEARCH(",E,", ","&_xlpm.s&",")), 15%, 0)) -> 0 | H24: =_xlfn.LET(_xlpm.s,SUBSTITUTE(TRIM($D24),"،",","), IF(ISNUMBER(SEARCH(",P,", ","&_xlpm.s&",")), 15%, 0)) -> 0.15 | I24: =_xlfn.LET(_xlpm.s,SUBSTITUTE(TRIM($D24),"،",","), IF(ISNUMBER(SEARCH(",C,", ","&_xlpm.s&",")), 20%, 0)) -> 0 | J24: =_xlfn.LET(_xlpm.s,SUBSTITUTE(TRIM($D24),"،",","), IF(ISNUMBER(SEARCH(",A,", ","&_xlpm.s&",")), 20%, 0)) -> 0 | K24: =_xlfn.LET(_xlpm.s,SUBSTITUTE(TRIM($D24),"،",","), IF(ISNUMBER(SEARCH(",R,", ","&_xlpm.s&",")), 15%, 0)) -> 0 | L24: =_xlfn.LET(_xlpm.s,SUBSTITUTE(TRIM($D24),"،",","), IF(ISNUMBER(SEARCH(",D,", ","&_xlpm.s&",")), 15%, 0)) -> 0.15 | S24: ISA 320
A25: ='دليل مراحل الملف'!A22 -> 3.2.2 | B25: ='دليل مراحل الملف'!B22 -> مشاركة الفريق | C25: التخطيط المهني الفعّال ؛ التوثيق والجودة والاسترجاع | D25: P,D | E25: =IF(C25="","",LEN(C25)-LEN(SUBSTITUTE(C25,"؛",""))+1) -> 2 | F25: =G25+H25+I25+J25+K25+L25 -> 0.3 | G25: =_xlfn.LET(_xlpm.s,SUBSTITUTE(TRIM($D25),"،",","), IF(ISNUMBER(SEARCH(",E,", ","&_xlpm.s&",")), 15%, 0)) -> 0 | H25: =_xlfn.LET(_xlpm.s,SUBSTITUTE(TRIM($D25),"،",","), IF(ISNUMBER(SEARCH(",P,", ","&_xlpm.s&",")), 15%, 0)) -> 0.15 | I25: =_xlfn.LET(_xlpm.s,SUBSTITUTE(TRIM($D25),"،",","), IF(ISNUMBER(SEARCH(",C,", ","&_xlpm.s&",")), 20%, 0)) -> 0 | J25: =_xlfn.LET(_xlpm.s,SUBSTITUTE(TRIM($D25),"،",","), IF(ISNUMBER(SEARCH(",A,", ","&_xlpm.s&",")), 20%, 0)) -> 0 | K25: =_xlfn.LET(_xlpm.s,SUBSTITUTE(TRIM($D25),"،",","), IF(ISNUMBER(SEARCH(",R,", ","&_xlpm.s&",")), 15%, 0)) -> 0 | L25: =_xlfn.LET(_xlpm.s,SUBSTITUTE(TRIM($D25),"،",","), IF(ISNUMBER(SEARCH(",D,", ","&_xlpm.s&",")), 15%, 0)) -> 0.15 | S25: ISA 320
A26: ='دليل مراحل الملف'!A23 -> 4 | B26: ='دليل مراحل الملف'!B23 -> تقييم الرقابة الداخلية | C26: تقييم نظام الرقابة الداخلية ؛ التخطيط المهني الفعّال ؛ التوثيق والجودة والاسترجاع | D26: C,P,D | E26: =IF(C26="","",LEN(C26)-LEN(SUBSTITUTE(C26,"؛",""))+1) -> 3 | F26: =G26+H26+I26+J26+K26+L26 -> 0.5 | G26: =_xlfn.LET(_xlpm.s,SUBSTITUTE(TRIM($D26),"،",","), IF(ISNUMBER(SEARCH(",E,", ","&_xlpm.s&",")), 15%, 0)) -> 0 | H26: =_xlfn.LET(_xlpm.s,SUBSTITUTE(TRIM($D26),"،",","), IF(ISNUMBER(SEARCH(",P,", ","&_xlpm.s&",")), 15%, 0)) -> 0.15 | I26: =_xlfn.LET(_xlpm.s,SUBSTITUTE(TRIM($D26),"،",","), IF(ISNUMBER(SEARCH(",C,", ","&_xlpm.s&",")), 20%, 0)) -> 0.2 | J26: =_xlfn.LET(_xlpm.s,SUBSTITUTE(TRIM($D26),"،",","), IF(ISNUMBER(SEARCH(",A,", ","&_xlpm.s&",")), 20%, 0)) -> 0 | K26: =_xlfn.LET(_xlpm.s,SUBSTITUTE(TRIM($D26),"،",","), IF(ISNUMBER(SEARCH(",R,", ","&_xlpm.s&",")), 15%, 0)) -> 0 | L26: =_xlfn.LET(_xlpm.s,SUBSTITUTE(TRIM($D26),"،",","), IF(ISNUMBER(SEARCH(",D,", ","&_xlpm.s&",")), 15%, 0)) -> 0.15 | P26: COSO Framework | Q26: IFRS 9 | R26: IAS 7 | S26: ISA 315
A27: ='دليل مراحل الملف'!A24 -> 4.1 | B27: ='دليل مراحل الملف'!B24 -> تقييم التصميم | C27: تقييم نظام الرقابة الداخلية ؛ التخطيط المهني الفعّال ؛ التوثيق والجودة والاسترجاع | D27: C,P,D | E27: =IF(C27="","",LEN(C27)-LEN(SUBSTITUTE(C27,"؛",""))+1) -> 3 | F27: =G27+H27+I27+J27+K27+L27 -> 0.5 | G27: =_xlfn.LET(_xlpm.s,SUBSTITUTE(TRIM($D27),"،",","), IF(ISNUMBER(SEARCH(",E,", ","&_xlpm.s&",")), 15%, 0)) -> 0 | H27: =_xlfn.LET(_xlpm.s,SUBSTITUTE(TRIM($D27),"،",","), IF(ISNUMBER(SEARCH(",P,", ","&_xlpm.s&",")), 15%, 0)) -> 0.15 | I27: =_xlfn.LET(_xlpm.s,SUBSTITUTE(TRIM($D27),"،",","), IF(ISNUMBER(SEARCH(",C,", ","&_xlpm.s&",")), 20%, 0)) -> 0.2 | J27: =_xlfn.LET(_xlpm.s,SUBSTITUTE(TRIM($D27),"،",","), IF(ISNUMBER(SEARCH(",A,", ","&_xlpm.s&",")), 20%, 0)) -> 0 | K27: =_xlfn.LET(_xlpm.s,SUBSTITUTE(TRIM($D27),"،",","), IF(ISNUMBER(SEARCH(",R,", ","&_xlpm.s&",")), 15%, 0)) -> 0 | L27: =_xlfn.LET(_xlpm.s,SUBSTITUTE(TRIM($D27),"،",","), IF(ISNUMBER(SEARCH(",D,", ","&_xlpm.s&",")), 15%, 0)) -> 0.15 | P27: COSO | S27: ISA 315
A28: ='دليل مراحل الملف'!A25 -> 4.1.1 | B28: ='دليل مراحل الملف'!B25 -> اختبار التنفيذ | C28: تقييم نظام الرقابة الداخلية ؛ التخطيط المهني الفعّال ؛ الحصول على أدلة كافية وملائمة ؛ التوثيق والجودة والاسترجاع | D28: C,P,A,D | E28: =IF(C28="","",LEN(C28)-LEN(SUBSTITUTE(C28,"؛",""))+1) -> 4 | F28: =G28+H28+I28+J28+K28+L28 -> 0.7 | G28: =_xlfn.LET(_xlpm.s,SUBSTITUTE(TRIM($D28),"،",","), IF(ISNUMBER(SEARCH(",E,", ","&_xlpm.s&",")), 15%, 0)) -> 0 | H28: =_xlfn.LET(_xlpm.s,SUBSTITUTE(TRIM($D28),"،",","), IF(ISNUMBER(SEARCH(",P,", ","&_xlpm.s&",")), 15%, 0)) -> 0.15 | I28: =_xlfn.LET(_xlpm.s,SUBSTITUTE(TRIM($D28),"،",","), IF(ISNUMBER(SEARCH(",C,", ","&_xlpm.s&",")), 20%, 0)) -> 0.2 | J28: =_xlfn.LET(_xlpm.s,SUBSTITUTE(TRIM($D28),"،",","), IF(ISNUMBER(SEARCH(",A,", ","&_xlpm.s&",")), 20%, 0)) -> 0.2 | K28: =_xlfn.LET(_xlpm.s,SUBSTITUTE(TRIM($D28),"،",","), IF(ISNUMBER(SEARCH(",R,", ","&_xlpm.s&",")), 15%, 0)) -> 0 | L28: =_xlfn.LET(_xlpm.s,SUBSTITUTE(TRIM($D28),"،",","), IF(ISNUMBER(SEARCH(",D,", ","&_xlpm.s&",")), 15%, 0)) -> 0.15 | P28: COSO ؛ ITGCs | S28: ISA 315 ؛ ISA 330
A29: ='دليل مراحل الملف'!A26 -> 4.1.2 | B29: ='دليل مراحل الملف'!B26 -> تقييم فعالية الرقابة | C29: تقييم نظام الرقابة الداخلية ؛ التخطيط المهني الفعّال ؛ التوثيق والجودة والاسترجاع | D29: C,P,D | E29: =IF(C29="","",LEN(C29)-LEN(SUBSTITUTE(C29,"؛",""))+1) -> 3 | F29: =G29+H29+I29+J29+K29+L29 -> 0.5 | G29: =_xlfn.LET(_xlpm.s,SUBSTITUTE(TRIM($D29),"،",","), IF(ISNUMBER(SEARCH(",E,", ","&_xlpm.s&",")), 15%, 0)) -> 0 | H29: =_xlfn.LET(_xlpm.s,SUBSTITUTE(TRIM($D29),"،",","), IF(ISNUMBER(SEARCH(",P,", ","&_xlpm.s&",")), 15%, 0)) -> 0.15 | I29: =_xlfn.LET(_xlpm.s,SUBSTITUTE(TRIM($D29),"،",","), IF(ISNUMBER(SEARCH(",C,", ","&_xlpm.s&",")), 20%, 0)) -> 0.2 | J29: =_xlfn.LET(_xlpm.s,SUBSTITUTE(TRIM($D29),"،",","), IF(ISNUMBER(SEARCH(",A,", ","&_xlpm.s&",")), 20%, 0)) -> 0 | K29: =_xlfn.LET(_xlpm.s,SUBSTITUTE(TRIM($D29),"،",","), IF(ISNUMBER(SEARCH(",R,", ","&_xlpm.s&",")), 15%, 0)) -> 0 | L29: =_xlfn.LET(_xlpm.s,SUBSTITUTE(TRIM($D29),"،",","), IF(ISNUMBER(SEARCH(",D,", ","&_xlpm.s&",")), 15%, 0)) -> 0.15 | P29: COSO | S29: ISA 315
A30: ='دليل مراحل الملف'!A27 -> 4.2 | B30: ='دليل مراحل الملف'!B27 -> توثيق النتائج | C30: تقييم نظام الرقابة الداخلية ؛ التوثيق والجودة والاسترجاع | D30: C,D | E30: =IF(C30="","",LEN(C30)-LEN(SUBSTITUTE(C30,"؛",""))+1) -> 2 | F30: =G30+H30+I30+J30+K30+L30 -> 0.35 | G30: =_xlfn.LET(_xlpm.s,SUBSTITUTE(TRIM($D30),"،",","), IF(ISNUMBER(SEARCH(",E,", ","&_xlpm.s&",")), 15%, 0)) -> 0 | H30: =_xlfn.LET(_xlpm.s,SUBSTITUTE(TRIM($D30),"،",","), IF(ISNUMBER(SEARCH(",P,", ","&_xlpm.s&",")), 15%, 0)) -> 0 | I30: =_xlfn.LET(_xlpm.s,SUBSTITUTE(TRIM($D30),"،",","), IF(ISNUMBER(SEARCH(",C,", ","&_xlpm.s&",")), 20%, 0)) -> 0.2 | J30: =_xlfn.LET(_xlpm.s,SUBSTITUTE(TRIM($D30),"،",","), IF(ISNUMBER(SEARCH(",A,", ","&_xlpm.s&",")), 20%, 0)) -> 0 | K30: =_xlfn.LET(_xlpm.s,SUBSTITUTE(TRIM($D30),"،",","), IF(ISNUMBER(SEARCH(",R,", ","&_xlpm.s&",")), 15%, 0)) -> 0 | L30: =_xlfn.LET(_xlpm.s,SUBSTITUTE(TRIM($D30),"،",","), IF(ISNUMBER(SEARCH(",D,", ","&_xlpm.s&",")), 15%, 0)) -> 0.15 | P30: ISQM 1 | S30: ISA 315
A31: ='دليل مراحل الملف'!A28 -> 4.2.1 | B31: ='دليل مراحل الملف'!B28 -> اعتماد النتائج | C31: تقييم نظام الرقابة الداخلية ؛ التوثيق والجودة والاسترجاع | D31: C,D | E31: =IF(C31="","",LEN(C31)-LEN(SUBSTITUTE(C31,"؛",""))+1) -> 2 | F31: =G31+H31+I31+J31+K31+L31 -> 0.35 | G31: =_xlfn.LET(_xlpm.s,SUBSTITUTE(TRIM($D31),"،",","), IF(ISNUMBER(SEARCH(",E,", ","&_xlpm.s&",")), 15%, 0)) -> 0 | H31: =_xlfn.LET(_xlpm.s,SUBSTITUTE(TRIM($D31),"،",","), IF(ISNUMBER(SEARCH(",P,", ","&_xlpm.s&",")), 15%, 0)) -> 0 | I31: =_xlfn.LET(_xlpm.s,SUBSTITUTE(TRIM($D31),"،",","), IF(ISNUMBER(SEARCH(",C,", ","&_xlpm.s&",")), 20%, 0)) -> 0.2 | J31: =_xlfn.LET(_xlpm.s,SUBSTITUTE(TRIM($D31),"،",","), IF(ISNUMBER(SEARCH(",A,", ","&_xlpm.s&",")), 20%, 0)) -> 0 | K31: =_xlfn.LET(_xlpm.s,SUBSTITUTE(TRIM($D31),"،",","), IF(ISNUMBER(SEARCH(",R,", ","&_xlpm.s&",")), 15%, 0)) -> 0 | L31: =_xlfn.LET(_xlpm.s,SUBSTITUTE(TRIM($D31),"،",","), IF(ISNUMBER(SEARCH(",D,", ","&_xlpm.s&",")), 15%, 0)) -> 0.15 | P31: ISQM 2 | S31: ISA 315
A32: ='دليل مراحل الملف'!A29 -> 4.2.2 | B32: ='دليل مراحل الملف'!B29 -> إعداد تقرير الضوابط | C32: تقييم نظام الرقابة الداخلية ؛ الحصول على أدلة كافية وملائمة ؛ التوثيق والجودة والاسترجاع | D32: C,A,D | E32: =IF(C32="","",LEN(C32)-LEN(SUBSTITUTE(C32,"؛",""))+1) -> 3 | F32: =G32+H32+I32+J32+K32+L32 -> 0.55 | G32: =_xlfn.LET(_xlpm.s,SUBSTITUTE(TRIM($D32),"،",","), IF(ISNUMBER(SEARCH(",E,", ","&_xlpm.s&",")), 15%, 0)) -> 0 | H32: =_xlfn.LET(_xlpm.s,SUBSTITUTE(TRIM($D32),"،",","), IF(ISNUMBER(SEARCH(",P,", ","&_xlpm.s&",")), 15%, 0)) -> 0 | I32: =_xlfn.LET(_xlpm.s,SUBSTITUTE(TRIM($D32),"،",","), IF(ISNUMBER(SEARCH(",C,", ","&_xlpm.s&",")), 20%, 0)) -> 0.2 | J32: =_xlfn.LET(_xlpm.s,SUBSTITUTE(TRIM($D32),"،",","), IF(ISNUMBER(SEARCH(",A,", ","&_xlpm.s&",")), 20%, 0)) -> 0.2 | K32: =_xlfn.LET(_xlpm.s,SUBSTITUTE(TRIM($D32),"،",","), IF(ISNUMBER(SEARCH(",R,", ","&_xlpm.s&",")), 15%, 0)) -> 0 | L32: =_xlfn.LET(_xlpm.s,SUBSTITUTE(TRIM($D32),"،",","), IF(ISNUMBER(SEARCH(",D,", ","&_xlpm.s&",")), 15%, 0)) -> 0.15 | P32: COSO | S32: ISA 315 ؛ ISA 330
A33: ='دليل مراحل الملف'!A30 -> 5 | B33: ='دليل مراحل الملف'!B30 -> اختبار المعالجات بالحاسب | C33: تقييم نظام الرقابة الداخلية ؛ الحصول على أدلة كافية وملائمة ؛ التوثيق والجودة والاسترجاع | D33: C,A,D | E33: =IF(C33="","",LEN(C33)-LEN(SUBSTITUTE(C33,"؛",""))+1) -> 3 | F33: =G33+H33+I33+J33+K33+L33 -> 0.55 | G33: =_xlfn.LET(_xlpm.s,SUBSTITUTE(TRIM($D33),"،",","), IF(ISNUMBER(SEARCH(",E,", ","&_xlpm.s&",")), 15%, 0)) -> 0 | H33: =_xlfn.LET(_xlpm.s,SUBSTITUTE(TRIM($D33),"،",","), IF(ISNUMBER(SEARCH(",P,", ","&_xlpm.s&",")), 15%, 0)) -> 0 | I33: =_xlfn.LET(_xlpm.s,SUBSTITUTE(TRIM($D33),"،",","), IF(ISNUMBER(SEARCH(",C,", ","&_xlpm.s&",")), 20%, 0)) -> 0.2 | J33: =_xlfn.LET(_xlpm.s,SUBSTITUTE(TRIM($D33),"،",","), IF(ISNUMBER(SEARCH(",A,", ","&_xlpm.s&",")), 20%, 0)) -> 0.2 | K33: =_xlfn.LET(_xlpm.s,SUBSTITUTE(TRIM($D33),"،",","), IF(ISNUMBER(SEARCH(",R,", ","&_xlpm.s&",")), 15%, 0)) -> 0 | L33: =_xlfn.LET(_xlpm.s,SUBSTITUTE(TRIM($D33),"،",","), IF(ISNUMBER(SEARCH(",D,", ","&_xlpm.s&",")), 15%, 0)) -> 0.15 | P33: COSO ؛ ITGCs ؛ SOX | Q33: IFRS 7 | R33: IAS 1 | S33: ISA 330
A34: ='دليل مراحل الملف'!A31 -> 5.1 | B34: ='دليل مراحل الملف'!B31 -> اختبار مدخلات النظام | C34: تقييم نظام الرقابة الداخلية ؛ الحصول على أدلة كافية وملائمة ؛ التوثيق والجودة والاسترجاع | D34: C,A,D | E34: =IF(C34="","",LEN(C34)-LEN(SUBSTITUTE(C34,"؛",""))+1) -> 3 | F34: =G34+H34+I34+J34+K34+L34 -> 0.55 | G34: =_xlfn.LET(_xlpm.s,SUBSTITUTE(TRIM($D34),"،",","), IF(ISNUMBER(SEARCH(",E,", ","&_xlpm.s&",")), 15%, 0)) -> 0 | H34: =_xlfn.LET(_xlpm.s,SUBSTITUTE(TRIM($D34),"،",","), IF(ISNUMBER(SEARCH(",P,", ","&_xlpm.s&",")), 15%, 0)) -> 0 | I34: =_xlfn.LET(_xlpm.s,SUBSTITUTE(TRIM($D34),"،",","), IF(ISNUMBER(SEARCH(",C,", ","&_xlpm.s&",")), 20%, 0)) -> 0.2 | J34: =_xlfn.LET(_xlpm.s,SUBSTITUTE(TRIM($D34),"،",","), IF(ISNUMBER(SEARCH(",A,", ","&_xlpm.s&",")), 20%, 0)) -> 0.2 | K34: =_xlfn.LET(_xlpm.s,SUBSTITUTE(TRIM($D34),"،",","), IF(ISNUMBER(SEARCH(",R,", ","&_xlpm.s&",")), 15%, 0)) -> 0 | L34: =_xlfn.LET(_xlpm.s,SUBSTITUTE(TRIM($D34),"،",","), IF(ISNUMBER(SEARCH(",D,", ","&_xlpm.s&",")), 15%, 0)) -> 0.15 | P34: ITGCs | S34: ISA 330
A35: ='دليل مراحل الملف'!A32 -> 5.1.1 | B35: ='دليل مراحل الملف'!B32 -> اختبار مخرجات النظام | C35: تقييم نظام الرقابة الداخلية ؛ الحصول على أدلة كافية وملائمة ؛ التوثيق والجودة والاسترجاع | D35: C,A,D | E35: =IF(C35="","",LEN(C35)-LEN(SUBSTITUTE(C35,"؛",""))+1) -> 3 | F35: =G35+H35+I35+J35+K35+L35 -> 0.55 | G35: =_xlfn.LET(_xlpm.s,SUBSTITUTE(TRIM($D35),"،",","), IF(ISNUMBER(SEARCH(",E,", ","&_xlpm.s&",")), 15%, 0)) -> 0 | H35: =_xlfn.LET(_xlpm.s,SUBSTITUTE(TRIM($D35),"،",","), IF(ISNUMBER(SEARCH(",P,", ","&_xlpm.s&",")), 15%, 0)) -> 0 | I35: =_xlfn.LET(_xlpm.s,SUBSTITUTE(TRIM($D35),"،",","), IF(ISNUMBER(SEARCH(",C,", ","&_xlpm.s&",")), 20%, 0)) -> 0.2 | J35: =_xlfn.LET(_xlpm.s,SUBSTITUTE(TRIM($D35),"،",","), IF(ISNUMBER(SEARCH(",A,", ","&_xlpm.s&",")), 20%, 0)) -> 0.2 | K35: =_xlfn.LET(_xlpm.s,SUBSTITUTE(TRIM($D35),"،",","), IF(ISNUMBER(SEARCH(",R,", ","&_xlpm.s&",")), 15%, 0)) -> 0 | L35: =_xlfn.LET(_xlpm.s,SUBSTITUTE(TRIM($D35),"،",","), IF(ISNUMBER(SEARCH(",D,", ","&_xlpm.s&",")), 15%, 0)) -> 0.15 | P35: ITGCs | S35: ISA 330
A36: ='دليل مراحل الملف'!A33 -> 5.1.2 | B36: ='دليل مراحل الملف'!B33 -> اختبار ضوابط الوصول | C36: تقييم نظام الرقابة الداخلية ؛ الحصول على أدلة كافية وملائمة ؛ التوثيق والجودة والاسترجاع | D36: C,A,D | E36: =IF(C36="","",LEN(C36)-LEN(SUBSTITUTE(C36,"؛",""))+1) -> 3 | F36: =G36+H36+I36+J36+K36+L36 -> 0.55 | G36: =_xlfn.LET(_xlpm.s,SUBSTITUTE(TRIM($D36),"،",","), IF(ISNUMBER(SEARCH(",E,", ","&_xlpm.s&",")), 15%, 0)) -> 0 | H36: =_xlfn.LET(_xlpm.s,SUBSTITUTE(TRIM($D36),"،",","), IF(ISNUMBER(SEARCH(",P,", ","&_xlpm.s&",")), 15%, 0)) -> 0 | I36: =_xlfn.LET(_xlpm.s,SUBSTITUTE(TRIM($D36),"،",","), IF(ISNUMBER(SEARCH(",C,", ","&_xlpm.s&",")), 20%, 0)) -> 0.2 | J36: =_xlfn.LET(_xlpm.s,SUBSTITUTE(TRIM($D36),"،",","), IF(ISNUMBER(SEARCH(",A,", ","&_xlpm.s&",")), 20%, 0)) -> 0.2 | K36: =_xlfn.LET(_xlpm.s,SUBSTITUTE(TRIM($D36),"،",","), IF(ISNUMBER(SEARCH(",R,", ","&_xlpm.s&",")), 15%, 0)) -> 0 | L36: =_xlfn.LET(_xlpm.s,SUBSTITUTE(TRIM($D36),"،",","), IF(ISNUMBER(SEARCH(",D,", ","&_xlpm.s&",")), 15%, 0)) -> 0.15 | P36: ITGCs ؛ SOX | S36: ISA 330
A37: ='دليل مراحل الملف'!A34 -> 5.2 | B37: ='دليل مراحل الملف'!B34 -> توثيق نتائج الاختبار | C37: تقييم نظام الرقابة الداخلية ؛ الحصول على أدلة كافية وملائمة ؛ التوثيق والجودة والاسترجاع | D37: C,A,D | E37: =IF(C37="","",LEN(C37)-LEN(SUBSTITUTE(C37,"؛",""))+1) -> 3 | F37: =G37+H37+I37+J37+K37+L37 -> 0.55 | G37: =_xlfn.LET(_xlpm.s,SUBSTITUTE(TRIM($D37),"،",","), IF(ISNUMBER(SEARCH(",E,", ","&_xlpm.s&",")), 15%, 0)) -> 0 | H37: =_xlfn.LET(_xlpm.s,SUBSTITUTE(TRIM($D37),"،",","), IF(ISNUMBER(SEARCH(",P,", ","&_xlpm.s&",")), 15%, 0)) -> 0 | I37: =_xlfn.LET(_xlpm.s,SUBSTITUTE(TRIM($D37),"،",","), IF(ISNUMBER(SEARCH(",C,", ","&_xlpm.s&",")), 20%, 0)) -> 0.2 | J37: =_xlfn.LET(_xlpm.s,SUBSTITUTE(TRIM($D37),"،",","), IF(ISNUMBER(SEARCH(",A,", ","&_xlpm.s&",")), 20%, 0)) -> 0.2 | K37: =_xlfn.LET(_xlpm.s,SUBSTITUTE(TRIM($D37),"،",","), IF(ISNUMBER(SEARCH(",R,", ","&_xlpm.s&",")), 15%, 0)) -> 0 | L37: =_xlfn.LET(_xlpm.s,SUBSTITUTE(TRIM($D37),"،",","), IF(ISNUMBER(SEARCH(",D,", ","&_xlpm.s&",")), 15%, 0)) -> 0.15 | P37: ISQM 1 | S37: ISA 330
A38: ='دليل مراحل الملف'!A35 -> 5.2.1 | B38: ='دليل مراحل الملف'!B35 -> مراجعة النتائج | C38: تقييم نظام الرقابة الداخلية ؛ الحصول على أدلة كافية وملائمة ؛ التوثيق والجودة والاسترجاع | D38: C,A,D | E38: =IF(C38="","",LEN(C38)-LEN(SUBSTITUTE(C38,"؛",""))+1) -> 3 | F38: =G38+H38+I38+J38+K38+L38 -> 0.55 | G38: =_xlfn.LET(_xlpm.s,SUBSTITUTE(TRIM($D38),"،",","), IF(ISNUMBER(SEARCH(",E,", ","&_xlpm.s&",")), 15%, 0)) -> 0 | H38: =_xlfn.LET(_xlpm.s,SUBSTITUTE(TRIM($D38),"،",","), IF(ISNUMBER(SEARCH(",P,", ","&_xlpm.s&",")), 15%, 0)) -> 0 | I38: =_xlfn.LET(_xlpm.s,SUBSTITUTE(TRIM($D38),"،",","), IF(ISNUMBER(SEARCH(",C,", ","&_xlpm.s&",")), 20%, 0)) -> 0.2 | J38: =_xlfn.LET(_xlpm.s,SUBSTITUTE(TRIM($D38),"،",","), IF(ISNUMBER(SEARCH(",A,", ","&_xlpm.s&",")), 20%, 0)) -> 0.2 | K38: =_xlfn.LET(_xlpm.s,SUBSTITUTE(TRIM($D38),"،",","), IF(ISNUMBER(SEARCH(",R,", ","&_xlpm.s&",")), 15%, 0)) -> 0 | L38: =_xlfn.LET(_xlpm.s,SUBSTITUTE(TRIM($D38),"،",","), IF(ISNUMBER(SEARCH(",D,", ","&_xlpm.s&",")), 15%, 0)) -> 0.15 | P38: ISQM 2 | S38: ISA 330
A39: ='دليل مراحل الملف'!A36 -> 5.2.2 | B39: ='دليل مراحل الملف'!B36 -> تقرير الاختبار | C39: تقييم نظام الرقابة الداخلية ؛ الحصول على أدلة كافية وملائمة ؛ التوثيق والجودة والاسترجاع | D39: C,A,D | E39: =IF(C39="","",LEN(C39)-LEN(SUBSTITUTE(C39,"؛",""))+1) -> 3 | F39: =G39+H39+I39+J39+K39+L39 -> 0.55 | G39: =_xlfn.LET(_xlpm.s,SUBSTITUTE(TRIM($D39),"،",","), IF(ISNUMBER(SEARCH(",E,", ","&_xlpm.s&",")), 15%, 0)) -> 0 | H39: =_xlfn.LET(_xlpm.s,SUBSTITUTE(TRIM($D39),"،",","), IF(ISNUMBER(SEARCH(",P,", ","&_xlpm.s&",")), 15%, 0)) -> 0 | I39: =_xlfn.LET(_xlpm.s,SUBSTITUTE(TRIM($D39),"،",","), IF(ISNUMBER(SEARCH(",C,", ","&_xlpm.s&",")), 20%, 0)) -> 0.2 | J39: =_xlfn.LET(_xlpm.s,SUBSTITUTE(TRIM($D39),"،",","), IF(ISNUMBER(SEARCH(",A,", ","&_xlpm.s&",")), 20%, 0)) -> 0.2 | K39: =_xlfn.LET(_xlpm.s,SUBSTITUTE(TRIM($D39),"،",","), IF(ISNUMBER(SEARCH(",R,", ","&_xlpm.s&",")), 15%, 0)) -> 0 | L39: =_xlfn.LET(_xlpm.s,SUBSTITUTE(TRIM($D39),"،",","), IF(ISNUMBER(SEARCH(",D,", ","&_xlpm.s&",")), 15%, 0)) -> 0.15 | P39: COSO | S39: ISA 330
A40: ='دليل مراحل الملف'!A37 -> 6 | B40: ='دليل مراحل الملف'!B37 -> المراجعة التفصيلية | C40: الحصول على أدلة كافية وملائمة ؛ تقييم نظام الرقابة الداخلية ؛ التوثيق والجودة والاسترجاع | D40: A,C,D | E40: =IF(C40="","",LEN(C40)-LEN(SUBSTITUTE(C40,"؛",""))+1) -> 3 | F40: =G40+H40+I40+J40+K40+L40 -> 0.55 | G40: =_xlfn.LET(_xlpm.s,SUBSTITUTE(TRIM($D40),"،",","), IF(ISNUMBER(SEARCH(",E,", ","&_xlpm.s&",")), 15%, 0)) -> 0 | H40: =_xlfn.LET(_xlpm.s,SUBSTITUTE(TRIM($D40),"،",","), IF(ISNUMBER(SEARCH(",P,", ","&_xlpm.s&",")), 15%, 0)) -> 0 | I40: =_xlfn.LET(_xlpm.s,SUBSTITUTE(TRIM($D40),"،",","), IF(ISNUMBER(SEARCH(",C,", ","&_xlpm.s&",")), 20%, 0)) -> 0.2 | J40: =_xlfn.LET(_xlpm.s,SUBSTITUTE(TRIM($D40),"،",","), IF(ISNUMBER(SEARCH(",A,", ","&_xlpm.s&",")), 20%, 0)) -> 0.2 | K40: =_xlfn.LET(_xlpm.s,SUBSTITUTE(TRIM($D40),"،",","), IF(ISNUMBER(SEARCH(",R,", ","&_xlpm.s&",")), 15%, 0)) -> 0 | L40: =_xlfn.LET(_xlpm.s,SUBSTITUTE(TRIM($D40),"،",","), IF(ISNUMBER(SEARCH(",D,", ","&_xlpm.s&",")), 15%, 0)) -> 0.15 | P40: COSO | Q40: IFRS 9 | R40: IAS 32 | S40: ISA 500 ؛ ISA 505
A41: ='دليل مراحل الملف'!A38 -> 6.1 | B41: ='دليل مراحل الملف'!B38 -> تأكيد الأرصدة | C41: الحصول على أدلة كافية وملائمة ؛ تقييم نظام الرقابة الداخلية ؛ التوثيق والجودة والاسترجاع | D41: A,C,D | E41: =IF(C41="","",LEN(C41)-LEN(SUBSTITUTE(C41,"؛",""))+1) -> 3 | F41: =G41+H41+I41+J41+K41+L41 -> 0.55 | G41: =_xlfn.LET(_xlpm.s,SUBSTITUTE(TRIM($D41),"،",","), IF(ISNUMBER(SEARCH(",E,", ","&_xlpm.s&",")), 15%, 0)) -> 0 | H41: =_xlfn.LET(_xlpm.s,SUBSTITUTE(TRIM($D41),"،",","), IF(ISNUMBER(SEARCH(",P,", ","&_xlpm.s&",")), 15%, 0)) -> 0 | I41: =_xlfn.LET(_xlpm.s,SUBSTITUTE(TRIM($D41),"،",","), IF(ISNUMBER(SEARCH(",C,", ","&_xlpm.s&",")), 20%, 0)) -> 0.2 | J41: =_xlfn.LET(_xlpm.s,SUBSTITUTE(TRIM($D41),"،",","), IF(ISNUMBER(SEARCH(",A,", ","&_xlpm.s&",")), 20%, 0)) -> 0.2 | K41: =_xlfn.LET(_xlpm.s,SUBSTITUTE(TRIM($D41),"،",","), IF(ISNUMBER(SEARCH(",R,", ","&_xlpm.s&",")), 15%, 0)) -> 0 | L41: =_xlfn.LET(_xlpm.s,SUBSTITUTE(TRIM($D41),"،",","), IF(ISNUMBER(SEARCH(",D,", ","&_xlpm.s&",")), 15%, 0)) -> 0.15 | S41: ISA 505 ؛ ISA 500
A42: ='دليل مراحل الملف'!A39 -> 6.1.1 | B42: ='دليل مراحل الملف'!B39 -> تحليل الأعمار | C42: الحصول على أدلة كافية وملائمة ؛ تقييم نظام الرقابة الداخلية ؛ التوثيق والجودة والاسترجاع | D42: A,C,D | E42: =IF(C42="","",LEN(C42)-LEN(SUBSTITUTE(C42,"؛",""))+1) -> 3 | F42: =G42+H42+I42+J42+K42+L42 -> 0.55 | G42: =_xlfn.LET(_xlpm.s,SUBSTITUTE(TRIM($D42),"،",","), IF(ISNUMBER(SEARCH(",E,", ","&_xlpm.s&",")), 15%, 0)) -> 0 | H42: =_xlfn.LET(_xlpm.s,SUBSTITUTE(TRIM($D42),"،",","), IF(ISNUMBER(SEARCH(",P,", ","&_xlpm.s&",")), 15%, 0)) -> 0 | I42: =_xlfn.LET(_xlpm.s,SUBSTITUTE(TRIM($D42),"،",","), IF(ISNUMBER(SEARCH(",C,", ","&_xlpm.s&",")), 20%, 0)) -> 0.2 | J42: =_xlfn.LET(_xlpm.s,SUBSTITUTE(TRIM($D42),"،",","), IF(ISNUMBER(SEARCH(",A,", ","&_xlpm.s&",")), 20%, 0)) -> 0.2 | K42: =_xlfn.LET(_xlpm.s,SUBSTITUTE(TRIM($D42),"،",","), IF(ISNUMBER(SEARCH(",R,", ","&_xlpm.s&",")), 15%, 0)) -> 0 | L42: =_xlfn.LET(_xlpm.s,SUBSTITUTE(TRIM($D42),"،",","), IF(ISNUMBER(SEARCH(",D,", ","&_xlpm.s&",")), 15%, 0)) -> 0.15 | Q42: IFRS 9 | S42: ISA 520
A43: ='دليل مراحل الملف'!A40 -> 6.1.2 | B43: ='دليل مراحل الملف'!B40 -> مراجعة المخصصات | C43: الحصول على أدلة كافية وملائمة ؛ تقييم نظام الرقابة الداخلية ؛ التوثيق والجودة والاسترجاع | D43: A,C,D | E43: =IF(C43="","",LEN(C43)-LEN(SUBSTITUTE(C43,"؛",""))+1) -> 3 | F43: =G43+H43+I43+J43+K43+L43 -> 0.55 | G43: =_xlfn.LET(_xlpm.s,SUBSTITUTE(TRIM($D43),"،",","), IF(ISNUMBER(SEARCH(",E,", ","&_xlpm.s&",")), 15%, 0)) -> 0 | H43: =_xlfn.LET(_xlpm.s,SUBSTITUTE(TRIM($D43),"،",","), IF(ISNUMBER(SEARCH(",P,", ","&_xlpm.s&",")), 15%, 0)) -> 0 | I43: =_xlfn.LET(_xlpm.s,SUBSTITUTE(TRIM($D43),"،",","), IF(ISNUMBER(SEARCH(",C,", ","&_xlpm.s&",")), 20%, 0)) -> 0.2 | J43: =_xlfn.LET(_xlpm.s,SUBSTITUTE(TRIM($D43),"،",","), IF(ISNUMBER(SEARCH(",A,", ","&_xlpm.s&",")), 20%, 0)) -> 0.2 | K43: =_xlfn.LET(_xlpm.s,SUBSTITUTE(TRIM($D43),"،",","), IF(ISNUMBER(SEARCH(",R,", ","&_xlpm.s&",")), 15%, 0)) -> 0 | L43: =_xlfn.LET(_xlpm.s,SUBSTITUTE(TRIM($D43),"،",","), IF(ISNUMBER(SEARCH(",D,", ","&_xlpm.s&",")), 15%, 0)) -> 0.15 | Q43: IFRS 9 | R43: IAS 37 | S43: ISA 540
A44: ='دليل مراحل الملف'!A41 -> 6.2 | B44: ='دليل مراحل الملف'!B41 -> توثيق نتائج الفحص | C44: الحصول على أدلة كافية وملائمة ؛ تقييم نظام الرقابة الداخلية ؛ التوثيق والجودة والاسترجاع | D44: A,C,D | E44: =IF(C44="","",LEN(C44)-LEN(SUBSTITUTE(C44,"؛",""))+1) -> 3 | F44: =G44+H44+I44+J44+K44+L44 -> 0.55 | G44: =_xlfn.LET(_xlpm.s,SUBSTITUTE(TRIM($D44),"،",","), IF(ISNUMBER(SEARCH(",E,", ","&_xlpm.s&",")), 15%, 0)) -> 0 | H44: =_xlfn.LET(_xlpm.s,SUBSTITUTE(TRIM($D44),"،",","), IF(ISNUMBER(SEARCH(",P,", ","&_xlpm.s&",")), 15%, 0)) -> 0 | I44: =_xlfn.LET(_xlpm.s,SUBSTITUTE(TRIM($D44),"،",","), IF(ISNUMBER(SEARCH(",C,", ","&_xlpm.s&",")), 20%, 0)) -> 0.2 | J44: =_xlfn.LET(_xlpm.s,SUBSTITUTE(TRIM($D44),"،",","), IF(ISNUMBER(SEARCH(",A,", ","&_xlpm.s&",")), 20%, 0)) -> 0.2 | K44: =_xlfn.LET(_xlpm.s,SUBSTITUTE(TRIM($D44),"،",","), IF(ISNUMBER(SEARCH(",R,", ","&_xlpm.s&",")), 15%, 0)) -> 0 | L44: =_xlfn.LET(_xlpm.s,SUBSTITUTE(TRIM($D44),"،",","), IF(ISNUMBER(SEARCH(",D,", ","&_xlpm.s&",")), 15%, 0)) -> 0.15 | P44: ISQM 1 | S44: ISA 230 ؛ ISA 500
A45: ='دليل مراحل الملف'!A42 -> 6.2.1 | B45: ='دليل مراحل الملف'!B42 -> اعتماد النتائج | C45: الحصول على أدلة كافية وملائمة ؛ تقييم نظام الرقابة الداخلية ؛ التوثيق والجودة والاسترجاع | D45: A,C,D | E45: =IF(C45="","",LEN(C45)-LEN(SUBSTITUTE(C45,"؛",""))+1) -> 3 | F45: =G45+H45+I45+J45+K45+L45 -> 0.55 | G45: =_xlfn.LET(_xlpm.s,SUBSTITUTE(TRIM($D45),"،",","), IF(ISNUMBER(SEARCH(",E,", ","&_xlpm.s&",")), 15%, 0)) -> 0 | H45: =_xlfn.LET(_xlpm.s,SUBSTITUTE(TRIM($D45),"،",","), IF(ISNUMBER(SEARCH(",P,", ","&_xlpm.s&",")), 15%, 0)) -> 0 | I45: =_xlfn.LET(_xlpm.s,SUBSTITUTE(TRIM($D45),"،",","), IF(ISNUMBER(SEARCH(",C,", ","&_xlpm.s&",")), 20%, 0)) -> 0.2 | J45: =_xlfn.LET(_xlpm.s,SUBSTITUTE(TRIM($D45),"،",","), IF(ISNUMBER(SEARCH(",A,", ","&_xlpm.s&",")), 20%, 0)) -> 0.2 | K45: =_xlfn.LET(_xlpm.s,SUBSTITUTE(TRIM($D45),"،",","), IF(ISNUMBER(SEARCH(",R,", ","&_xlpm.s&",")), 15%, 0)) -> 0 | L45: =_xlfn.LET(_xlpm.s,SUBSTITUTE(TRIM($D45),"،",","), IF(ISNUMBER(SEARCH(",D,", ","&_xlpm.s&",")), 15%, 0)) -> 0.15 | P45: ISQM 2 | S45: ISA 500
A46: ='دليل مراحل الملف'!A43 -> 6.2.2 | B46: ='دليل مراحل الملف'!B43 -> تقرير المراجعة التفصيلية | C46: الحصول على أدلة كافية وملائمة ؛ التقييم وإبداء الرأي ؛ التوثيق والجودة والاسترجاع | D46: A,R,D | E46: =IF(C46="","",LEN(C46)-LEN(SUBSTITUTE(C46,"؛",""))+1) -> 3 | F46: =G46+H46+I46+J46+K46+L46 -> 0.5 | G46: =_xlfn.LET(_xlpm.s,SUBSTITUTE(TRIM($D46),"،",","), IF(ISNUMBER(SEARCH(",E,", ","&_xlpm.s&",")), 15%, 0)) -> 0 | H46: =_xlfn.LET(_xlpm.s,SUBSTITUTE(TRIM($D46),"،",","), IF(ISNUMBER(SEARCH(",P,", ","&_xlpm.s&",")), 15%, 0)) -> 0 | I46: =_xlfn.LET(_xlpm.s,SUBSTITUTE(TRIM($D46),"،",","), IF(ISNUMBER(SEARCH(",C,", ","&_xlpm.s&",")), 20%, 0)) -> 0 | J46: =_xlfn.LET(_xlpm.s,SUBSTITUTE(TRIM($D46),"،",","), IF(ISNUMBER(SEARCH(",A,", ","&_xlpm.s&",")), 20%, 0)) -> 0.2 | K46: =_xlfn.LET(_xlpm.s,SUBSTITUTE(TRIM($D46),"،",","), IF(ISNUMBER(SEARCH(",R,", ","&_xlpm.s&",")), 15%, 0)) -> 0.15 | L46: =_xlfn.LET(_xlpm.s,SUBSTITUTE(TRIM($D46),"،",","), IF(ISNUMBER(SEARCH(",D,", ","&_xlpm.s&",")), 15%, 0)) -> 0.15 | S46: ISA 700 ؛ ISA 705 ؛ ISA 706
A47: ='دليل مراحل الملف'!A44 -> 7 | B47: ='دليل مراحل الملف'!B44 -> إعداد التقرير | C47: التقييم وإبداء الرأي ؛ التوثيق والجودة والاسترجاع | D47: R,D | E47: =IF(C47="","",LEN(C47)-LEN(SUBSTITUTE(C47,"؛",""))+1) -> 2 | F47: =G47+H47+I47+J47+K47+L47 -> 0.3 | G47: =_xlfn.LET(_xlpm.s,SUBSTITUTE(TRIM($D47),"،",","), IF(ISNUMBER(SEARCH(",E,", ","&_xlpm.s&",")), 15%, 0)) -> 0 | H47: =_xlfn.LET(_xlpm.s,SUBSTITUTE(TRIM($D47),"،",","), IF(ISNUMBER(SEARCH(",P,", ","&_xlpm.s&",")), 15%, 0)) -> 0 | I47: =_xlfn.LET(_xlpm.s,SUBSTITUTE(TRIM($D47),"،",","), IF(ISNUMBER(SEARCH(",C,", ","&_xlpm.s&",")), 20%, 0)) -> 0 | J47: =_xlfn.LET(_xlpm.s,SUBSTITUTE(TRIM($D47),"،",","), IF(ISNUMBER(SEARCH(",A,", ","&_xlpm.s&",")), 20%, 0)) -> 0 | K47: =_xlfn.LET(_xlpm.s,SUBSTITUTE(TRIM($D47),"،",","), IF(ISNUMBER(SEARCH(",R,", ","&_xlpm.s&",")), 15%, 0)) -> 0.15 | L47: =_xlfn.LET(_xlpm.s,SUBSTITUTE(TRIM($D47),"،",","), IF(ISNUMBER(SEARCH(",D,", ","&_xlpm.s&",")), 15%, 0)) -> 0.15 | P47: ISQM 1 | R47: IAS 1 | S47: ISA 700 ؛ ISA 705 ؛ ISA 706
A48: ='دليل مراحل الملف'!A45 -> 7.1 | B48: ='دليل مراحل الملف'!B45 -> إعداد المسودة | C48: التقييم وإبداء الرأي ؛ التوثيق والجودة والاسترجاع | D48: R,D | E48: =IF(C48="","",LEN(C48)-LEN(SUBSTITUTE(C48,"؛",""))+1) -> 2 | F48: =G48+H48+I48+J48+K48+L48 -> 0.3 | G48: =_xlfn.LET(_xlpm.s,SUBSTITUTE(TRIM($D48),"،",","), IF(ISNUMBER(SEARCH(",E,", ","&_xlpm.s&",")), 15%, 0)) -> 0 | H48: =_xlfn.LET(_xlpm.s,SUBSTITUTE(TRIM($D48),"،",","), IF(ISNUMBER(SEARCH(",P,", ","&_xlpm.s&",")), 15%, 0)) -> 0 | I48: =_xlfn.LET(_xlpm.s,SUBSTITUTE(TRIM($D48),"،",","), IF(ISNUMBER(SEARCH(",C,", ","&_xlpm.s&",")), 20%, 0)) -> 0 | J48: =_xlfn.LET(_xlpm.s,SUBSTITUTE(TRIM($D48),"،",","), IF(ISNUMBER(SEARCH(",A,", ","&_xlpm.s&",")), 20%, 0)) -> 0 | K48: =_xlfn.LET(_xlpm.s,SUBSTITUTE(TRIM($D48),"،",","), IF(ISNUMBER(SEARCH(",R,", ","&_xlpm.s&",")), 15%, 0)) -> 0.15 | L48: =_xlfn.LET(_xlpm.s,SUBSTITUTE(TRIM($D48),"،",","), IF(ISNUMBER(SEARCH(",D,", ","&_xlpm.s&",")), 15%, 0)) -> 0.15 | S48: ISA 700 ؛ ISA 705
A49: ='دليل مراحل الملف'!A46 -> 7.1.1 | B49: ='دليل مراحل الملف'!B46 -> مناقشة المسودة | C49: التقييم وإبداء الرأي ؛ التوثيق والجودة والاسترجاع | D49: R,D | E49: =IF(C49="","",LEN(C49)-LEN(SUBSTITUTE(C49,"؛",""))+1) -> 2 | F49: =G49+H49+I49+J49+K49+L49 -> 0.3 | G49: =_xlfn.LET(_xlpm.s,SUBSTITUTE(TRIM($D49),"،",","), IF(ISNUMBER(SEARCH(",E,", ","&_xlpm.s&",")), 15%, 0)) -> 0 | H49: =_xlfn.LET(_xlpm.s,SUBSTITUTE(TRIM($D49),"،",","), IF(ISNUMBER(SEARCH(",P,", ","&_xlpm.s&",")), 15%, 0)) -> 0 | I49: =_xlfn.LET(_xlpm.s,SUBSTITUTE(TRIM($D49),"،",","), IF(ISNUMBER(SEARCH(",C,", ","&_xlpm.s&",")), 20%, 0)) -> 0 | J49: =_xlfn.LET(_xlpm.s,SUBSTITUTE(TRIM($D49),"،",","), IF(ISNUMBER(SEARCH(",A,", ","&_xlpm.s&",")), 20%, 0)) -> 0 | K49: =_xlfn.LET(_xlpm.s,SUBSTITUTE(TRIM($D49),"،",","), IF(ISNUMBER(SEARCH(",R,", ","&_xlpm.s&",")), 15%, 0)) -> 0.15 | L49: =_xlfn.LET(_xlpm.s,SUBSTITUTE(TRIM($D49),"،",","), IF(ISNUMBER(SEARCH(",D,", ","&_xlpm.s&",")), 15%, 0)) -> 0.15 | S49: ISA 260 ؛ ISA 265
A50: ='دليل مراحل الملف'!A47 -> 7.1.2 | B50: ='دليل مراحل الملف'!B47 -> اعتماد التقرير | C50: التقييم وإبداء الرأي ؛ التوثيق والجودة والاسترجاع | D50: R,D | E50: =IF(C50="","",LEN(C50)-LEN(SUBSTITUTE(C50,"؛",""))+1) -> 2 | F50: =G50+H50+I50+J50+K50+L50 -> 0.3 | G50: =_xlfn.LET(_xlpm.s,SUBSTITUTE(TRIM($D50),"،",","), IF(ISNUMBER(SEARCH(",E,", ","&_xlpm.s&",")), 15%, 0)) -> 0 | H50: =_xlfn.LET(_xlpm.s,SUBSTITUTE(TRIM($D50),"،",","), IF(ISNUMBER(SEARCH(",P,", ","&_xlpm.s&",")), 15%, 0)) -> 0 | I50: =_xlfn.LET(_xlpm.s,SUBSTITUTE(TRIM($D50),"،",","), IF(ISNUMBER(SEARCH(",C,", ","&_xlpm.s&",")), 20%, 0)) -> 0 | J50: =_xlfn.LET(_xlpm.s,SUBSTITUTE(TRIM($D50),"،",","), IF(ISNUMBER(SEARCH(",A,", ","&_xlpm.s&",")), 20%, 0)) -> 0 | K50: =_xlfn.LET(_xlpm.s,SUBSTITUTE(TRIM($D50),"،",","), IF(ISNUMBER(SEARCH(",R,", ","&_xlpm.s&",")), 15%, 0)) -> 0.15 | L50: =_xlfn.LET(_xlpm.s,SUBSTITUTE(TRIM($D50),"،",","), IF(ISNUMBER(SEARCH(",D,", ","&_xlpm.s&",")), 15%, 0)) -> 0.15 | P50: ISQM 2 | S50: ISA 700
A51: ='دليل مراحل الملف'!A48 -> 7.2 | B51: ='دليل مراحل الملف'!B48 -> إصدار التقرير | C51: التقييم وإبداء الرأي ؛ التوثيق والجودة والاسترجاع | D51: R,D | E51: =IF(C51="","",LEN(C51)-LEN(SUBSTITUTE(C51,"؛",""))+1) -> 2 | F51: =G51+H51+I51+J51+K51+L51 -> 0.3 | G51: =_xlfn.LET(_xlpm.s,SUBSTITUTE(TRIM($D51),"،",","), IF(ISNUMBER(SEARCH(",E,", ","&_xlpm.s&",")), 15%, 0)) -> 0 | H51: =_xlfn.LET(_xlpm.s,SUBSTITUTE(TRIM($D51),"،",","), IF(ISNUMBER(SEARCH(",P,", ","&_xlpm.s&",")), 15%, 0)) -> 0 | I51: =_xlfn.LET(_xlpm.s,SUBSTITUTE(TRIM($D51),"،",","), IF(ISNUMBER(SEARCH(",C,", ","&_xlpm.s&",")), 20%, 0)) -> 0 | J51: =_xlfn.LET(_xlpm.s,SUBSTITUTE(TRIM($D51),"،",","), IF(ISNUMBER(SEARCH(",A,", ","&_xlpm.s&",")), 20%, 0)) -> 0 | K51: =_xlfn.LET(_xlpm.s,SUBSTITUTE(TRIM($D51),"،",","), IF(ISNUMBER(SEARCH(",R,", ","&_xlpm.s&",")), 15%, 0)) -> 0.15 | L51: =_xlfn.LET(_xlpm.s,SUBSTITUTE(TRIM($D51),"،",","), IF(ISNUMBER(SEARCH(",D,", ","&_xlpm.s&",")), 15%, 0)) -> 0.15 | S51: ISA 700 ؛ ISA 706
A52: ='دليل مراحل الملف'!A49 -> 7.2.1 | B52: ='دليل مراحل الملف'!B49 -> إبلاغ الأطراف الخارجية | C52: التقييم وإبداء الرأي ؛ التوثيق والجودة والاسترجاع | D52: R,D | E52: =IF(C52="","",LEN(C52)-LEN(SUBSTITUTE(C52,"؛",""))+1) -> 2 | F52: =G52+H52+I52+J52+K52+L52 -> 0.3 | G52: =_xlfn.LET(_xlpm.s,SUBSTITUTE(TRIM($D52),"،",","), IF(ISNUMBER(SEARCH(",E,", ","&_xlpm.s&",")), 15%, 0)) -> 0 | H52: =_xlfn.LET(_xlpm.s,SUBSTITUTE(TRIM($D52),"،",","), IF(ISNUMBER(SEARCH(",P,", ","&_xlpm.s&",")), 15%, 0)) -> 0 | I52: =_xlfn.LET(_xlpm.s,SUBSTITUTE(TRIM($D52),"،",","), IF(ISNUMBER(SEARCH(",C,", ","&_xlpm.s&",")), 20%, 0)) -> 0 | J52: =_xlfn.LET(_xlpm.s,SUBSTITUTE(TRIM($D52),"،",","), IF(ISNUMBER(SEARCH(",A,", ","&_xlpm.s&",")), 20%, 0)) -> 0 | K52: =_xlfn.LET(_xlpm.s,SUBSTITUTE(TRIM($D52),"،",","), IF(ISNUMBER(SEARCH(",R,", ","&_xlpm.s&",")), 15%, 0)) -> 0.15 | L52: =_xlfn.LET(_xlpm.s,SUBSTITUTE(TRIM($D52),"،",","), IF(ISNUMBER(SEARCH(",D,", ","&_xlpm.s&",")), 15%, 0)) -> 0.15 | P52: IESBA Code of Ethics | S52: ISA 700
A53: ='دليل مراحل الملف'!A50 -> 7.2.2 | B53: ='دليل مراحل الملف'!B50 -> أرشفة التقرير | C53: التوثيق والجودة والاسترجاع | D53: D | E53: =IF(C53="","",LEN(C53)-LEN(SUBSTITUTE(C53,"؛",""))+1) -> 1 | F53: =G53+H53+I53+J53+K53+L53 -> 0.15 | G53: =_xlfn.LET(_xlpm.s,SUBSTITUTE(TRIM($D53),"،",","), IF(ISNUMBER(SEARCH(",E,", ","&_xlpm.s&",")), 15%, 0)) -> 0 | H53: =_xlfn.LET(_xlpm.s,SUBSTITUTE(TRIM($D53),"،",","), IF(ISNUMBER(SEARCH(",P,", ","&_xlpm.s&",")), 15%, 0)) -> 0 | I53: =_xlfn.LET(_xlpm.s,SUBSTITUTE(TRIM($D53),"،",","), IF(ISNUMBER(SEARCH(",C,", ","&_xlpm.s&",")), 20%, 0)) -> 0 | J53: =_xlfn.LET(_xlpm.s,SUBSTITUTE(TRIM($D53),"،",","), IF(ISNUMBER(SEARCH(",A,", ","&_xlpm.s&",")), 20%, 0)) -> 0 | K53: =_xlfn.LET(_xlpm.s,SUBSTITUTE(TRIM($D53),"،",","), IF(ISNUMBER(SEARCH(",R,", ","&_xlpm.s&",")), 15%, 0)) -> 0 | L53: =_xlfn.LET(_xlpm.s,SUBSTITUTE(TRIM($D53),"،",","), IF(ISNUMBER(SEARCH(",D,", ","&_xlpm.s&",")), 15%, 0)) -> 0.15 | P53: ISQM 1 | S53: ISA 230
A54: ='دليل مراحل الملف'!A51 -> 8 | B54: ='دليل مراحل الملف'!B51 -> الإغلاق والأرشفة | C54: التوثيق والجودة والاسترجاع ؛ الالتزام الأخلاقي والنزاهة | D54: D,E | E54: =IF(C54="","",LEN(C54)-LEN(SUBSTITUTE(C54,"؛",""))+1) -> 2 | F54: =G54+H54+I54+J54+K54+L54 -> 0.3 | G54: =_xlfn.LET(_xlpm.s,SUBSTITUTE(TRIM($D54),"،",","), IF(ISNUMBER(SEARCH(",E,", ","&_xlpm.s&",")), 15%, 0)) -> 0.15 | H54: =_xlfn.LET(_xlpm.s,SUBSTITUTE(TRIM($D54),"،",","), IF(ISNUMBER(SEARCH(",P,", ","&_xlpm.s&",")), 15%, 0)) -> 0 | I54: =_xlfn.LET(_xlpm.s,SUBSTITUTE(TRIM($D54),"،",","), IF(ISNUMBER(SEARCH(",C,", ","&_xlpm.s&",")), 20%, 0)) -> 0 | J54: =_xlfn.LET(_xlpm.s,SUBSTITUTE(TRIM($D54),"،",","), IF(ISNUMBER(SEARCH(",A,", ","&_xlpm.s&",")), 20%, 0)) -> 0 | K54: =_xlfn.LET(_xlpm.s,SUBSTITUTE(TRIM($D54),"،",","), IF(ISNUMBER(SEARCH(",R,", ","&_xlpm.s&",")), 15%, 0)) -> 0 | L54: =_xlfn.LET(_xlpm.s,SUBSTITUTE(TRIM($D54),"،",","), IF(ISNUMBER(SEARCH(",D,", ","&_xlpm.s&",")), 15%, 0)) -> 0.15
A55: ='دليل مراحل الملف'!A52 -> 8.1 | B55: ='دليل مراحل الملف'!B52 -> مراجعة استكمال الملف | E55: =IF(C55="","",LEN(C55)-LEN(SUBSTITUTE(C55,"؛",""))+1) | F55: =G55+H55+I55+J55+K55+L55 -> 0 | G55: =_xlfn.LET(_xlpm.s,SUBSTITUTE(TRIM($D55),"،",","), IF(ISNUMBER(SEARCH(",E,", ","&_xlpm.s&",")), 15%, 0)) -> 0 | H55: =_xlfn.LET(_xlpm.s,SUBSTITUTE(TRIM($D55),"،",","), IF(ISNUMBER(SEARCH(",P,", ","&_xlpm.s&",")), 15%, 0)) -> 0 | I55: =_xlfn.LET(_xlpm.s,SUBSTITUTE(TRIM($D55),"،",","), IF(ISNUMBER(SEARCH(",C,", ","&_xlpm.s&",")), 20%, 0)) -> 0 | J55: =_xlfn.LET(_xlpm.s,SUBSTITUTE(TRIM($D55),"،",","), IF(ISNUMBER(SEARCH(",A,", ","&_xlpm.s&",")), 20%, 0)) -> 0 | K55: =_xlfn.LET(_xlpm.s,SUBSTITUTE(TRIM($D55),"،",","), IF(ISNUMBER(SEARCH(",R,", ","&_xlpm.s&",")), 15%, 0)) -> 0 | L55: =_xlfn.LET(_xlpm.s,SUBSTITUTE(TRIM($D55),"،",","), IF(ISNUMBER(SEARCH(",D,", ","&_xlpm.s&",")), 15%, 0)) -> 0
E56: =IF(C56="","",LEN(C56)-LEN(SUBSTITUTE(C56,"؛",""))+1) | F56: =G56+H56+I56+J56+K56+L56 -> 0 | G56: =_xlfn.LET(_xlpm.s,SUBSTITUTE(TRIM($D56),"،",","), IF(ISNUMBER(SEARCH(",E,", ","&_xlpm.s&",")), 15%, 0)) -> 0 | H56: =_xlfn.LET(_xlpm.s,SUBSTITUTE(TRIM($D56),"،",","), IF(ISNUMBER(SEARCH(",P,", ","&_xlpm.s&",")), 15%, 0)) -> 0 | I56: =_xlfn.LET(_xlpm.s,SUBSTITUTE(TRIM($D56),"،",","), IF(ISNUMBER(SEARCH(",C,", ","&_xlpm.s&",")), 20%, 0)) -> 0 | J56: =_xlfn.LET(_xlpm.s,SUBSTITUTE(TRIM($D56),"،",","), IF(ISNUMBER(SEARCH(",A,", ","&_xlpm.s&",")), 20%, 0)) -> 0 | K56: =_xlfn.LET(_xlpm.s,SUBSTITUTE(TRIM($D56),"،",","), IF(ISNUMBER(SEARCH(",R,", ","&_xlpm.s&",")), 15%, 0)) -> 0 | L56: =_xlfn.LET(_xlpm.s,SUBSTITUTE(TRIM($D56),"،",","), IF(ISNUMBER(SEARCH(",D,", ","&_xlpm.s&",")), 15%, 0)) -> 0
E57: =IF(C57="","",LEN(C57)-LEN(SUBSTITUTE(C57,"؛",""))+1) | F57: =G57+H57+I57+J57+K57+L57 -> 0 | G57: =_xlfn.LET(_xlpm.s,SUBSTITUTE(TRIM($D57),"،",","), IF(ISNUMBER(SEARCH(",E,", ","&_xlpm.s&",")), 15%, 0)) -> 0 | H57: =_xlfn.LET(_xlpm.s,SUBSTITUTE(TRIM($D57),"،",","), IF(ISNUMBER(SEARCH(",P,", ","&_xlpm.s&",")), 15%, 0)) -> 0 | I57: =_xlfn.LET(_xlpm.s,SUBSTITUTE(TRIM($D57),"،",","), IF(ISNUMBER(SEARCH(",C,", ","&_xlpm.s&",")), 20%, 0)) -> 0 | J57: =_xlfn.LET(_xlpm.s,SUBSTITUTE(TRIM($D57),"،",","), IF(ISNUMBER(SEARCH(",A,", ","&_xlpm.s&",")), 20%, 0)) -> 0 | K57: =_xlfn.LET(_xlpm.s,SUBSTITUTE(TRIM($D57),"،",","), IF(ISNUMBER(SEARCH(",R,", ","&_xlpm.s&",")), 15%, 0)) -> 0 | L57: =_xlfn.LET(_xlpm.s,SUBSTITUTE(TRIM($D57),"،",","), IF(ISNUMBER(SEARCH(",D,", ","&_xlpm.s&",")), 15%, 0)) -> 0
E58: =IF(C58="","",LEN(C58)-LEN(SUBSTITUTE(C58,"؛",""))+1) | F58: =G58+H58+I58+J58+K58+L58 -> 0 | G58: =_xlfn.LET(_xlpm.s,SUBSTITUTE(TRIM($D58),"،",","), IF(ISNUMBER(SEARCH(",E,", ","&_xlpm.s&",")), 15%, 0)) -> 0 | H58: =_xlfn.LET(_xlpm.s,SUBSTITUTE(TRIM($D58),"،",","), IF(ISNUMBER(SEARCH(",P,", ","&_xlpm.s&",")), 15%, 0)) -> 0 | I58: =_xlfn.LET(_xlpm.s,SUBSTITUTE(TRIM($D58),"،",","), IF(ISNUMBER(SEARCH(",C,", ","&_xlpm.s&",")), 20%, 0)) -> 0 | J58: =_xlfn.LET(_xlpm.s,SUBSTITUTE(TRIM($D58),"،",","), IF(ISNUMBER(SEARCH(",A,", ","&_xlpm.s&",")), 20%, 0)) -> 0 | K58: =_xlfn.LET(_xlpm.s,SUBSTITUTE(TRIM($D58),"،",","), IF(ISNUMBER(SEARCH(",R,", ","&_xlpm.s&",")), 15%, 0)) -> 0 | L58: =_xlfn.LET(_xlpm.s,SUBSTITUTE(TRIM($D58),"،",","), IF(ISNUMBER(SEARCH(",D,", ","&_xlpm.s&",")), 15%, 0)) -> 0
E59: =IF(C59="","",LEN(C59)-LEN(SUBSTITUTE(C59,"؛",""))+1) | F59: =G59+H59+I59+J59+K59+L59 -> 0 | G59: =_xlfn.LET(_xlpm.s,SUBSTITUTE(TRIM($D59),"،",","), IF(ISNUMBER(SEARCH(",E,", ","&_xlpm.s&",")), 15%, 0)) -> 0 | H59: =_xlfn.LET(_xlpm.s,SUBSTITUTE(TRIM($D59),"،",","), IF(ISNUMBER(SEARCH(",P,", ","&_xlpm.s&",")), 15%, 0)) -> 0 | I59: =_xlfn.LET(_xlpm.s,SUBSTITUTE(TRIM($D59),"،",","), IF(ISNUMBER(SEARCH(",C,", ","&_xlpm.s&",")), 20%, 0)) -> 0 | J59: =_xlfn.LET(_xlpm.s,SUBSTITUTE(TRIM($D59),"،",","), IF(ISNUMBER(SEARCH(",A,", ","&_xlpm.s&",")), 20%, 0)) -> 0 | K59: =_xlfn.LET(_xlpm.s,SUBSTITUTE(TRIM($D59),"،",","), IF(ISNUMBER(SEARCH(",R,", ","&_xlpm.s&",")), 15%, 0)) -> 0 | L59: =_xlfn.LET(_xlpm.s,SUBSTITUTE(TRIM($D59),"،",","), IF(ISNUMBER(SEARCH(",D,", ","&_xlpm.s&",")), 15%, 0)) -> 0
E60: =IF(C60="","",LEN(C60)-LEN(SUBSTITUTE(C60,"؛",""))+1) | F60: =G60+H60+I60+J60+K60+L60 -> 0 | G60: =_xlfn.LET(_xlpm.s,SUBSTITUTE(TRIM($D60),"،",","), IF(ISNUMBER(SEARCH(",E,", ","&_xlpm.s&",")), 15%, 0)) -> 0 | H60: =_xlfn.LET(_xlpm.s,SUBSTITUTE(TRIM($D60),"،",","), IF(ISNUMBER(SEARCH(",P,", ","&_xlpm.s&",")), 15%, 0)) -> 0 | I60: =_xlfn.LET(_xlpm.s,SUBSTITUTE(TRIM($D60),"،",","), IF(ISNUMBER(SEARCH(",C,", ","&_xlpm.s&",")), 20%, 0)) -> 0 | J60: =_xlfn.LET(_xlpm.s,SUBSTITUTE(TRIM($D60),"،",","), IF(ISNUMBER(SEARCH(",A,", ","&_xlpm.s&",")), 20%, 0)) -> 0 | K60: =_xlfn.LET(_xlpm.s,SUBSTITUTE(TRIM($D60),"،",","), IF(ISNUMBER(SEARCH(",R,", ","&_xlpm.s&",")), 15%, 0)) -> 0 | L60: =_xlfn.LET(_xlpm.s,SUBSTITUTE(TRIM($D60),"،",","), IF(ISNUMBER(SEARCH(",D,", ","&_xlpm.s&",")), 15%, 0)) -> 0
A61: ='دليل مراحل الملف'!A58 -> 0 | B61: ='دليل مراحل الملف'!B58 -> 0 | E61: =IF(C61="","",LEN(C61)-LEN(SUBSTITUTE(C61,"؛",""))+1) | F61: =G61+H61+I61+J61+K61+L61 -> 0 | G61: =_xlfn.LET(_xlpm.s,SUBSTITUTE(TRIM($D61),"،",","), IF(ISNUMBER(SEARCH(",E,", ","&_xlpm.s&",")), 15%, 0)) -> 0 | H61: =_xlfn.LET(_xlpm.s,SUBSTITUTE(TRIM($D61),"،",","), IF(ISNUMBER(SEARCH(",P,", ","&_xlpm.s&",")), 15%, 0)) -> 0 | I61: =_xlfn.LET(_xlpm.s,SUBSTITUTE(TRIM($D61),"،",","), IF(ISNUMBER(SEARCH(",C,", ","&_xlpm.s&",")), 20%, 0)) -> 0 | J61: =_xlfn.LET(_xlpm.s,SUBSTITUTE(TRIM($D61),"،",","), IF(ISNUMBER(SEARCH(",A,", ","&_xlpm.s&",")), 20%, 0)) -> 0 | K61: =_xlfn.LET(_xlpm.s,SUBSTITUTE(TRIM($D61),"،",","), IF(ISNUMBER(SEARCH(",R,", ","&_xlpm.s&",")), 15%, 0)) -> 0 | L61: =_xlfn.LET(_xlpm.s,SUBSTITUTE(TRIM($D61),"،",","), IF(ISNUMBER(SEARCH(",D,", ","&_xlpm.s&",")), 15%, 0)) -> 0

Sheet المستخدمين
A2: الإجراء \ الدور | B2: الإدارات | C2: سكرتارية | D2: مدير المراجعة | E2: المدقق الفني | F2: المدقق الميداني | G2: مساعد المدقق الفني | H2: ضابط اتصال الشركة | I2: ضبط الجودة | J2: الشريك الإداري | K2: مواقع ذات علاقة | L2: الأرشيف | M2: الإدارات بالبرنامج
B3: ترجمة اسم الإدارة | C3: Secretary | D3: Audit Manager | E3: Technical Auditor | F3: Field Auditor | G3: Assistant Technical Auditor | H3: CONTACT PERSON | I3: Quality Control | J3: Managing Partner | K3: Regulatory Filings Officer | L3: Archive
B4: رمز الإدارة | C4: SC | D4: AM | E4: TA | F4: FA | G4: AT | H4: CO | I4: QC | J4: MP | K4: RF | L4: AR
B5: المهمة | C5: مركز الخدمات الإدارية والدعم اللوجستي للمكتب. | D5: تخطيط وتنفيذ ومتابعة مهام المراجعة وضمان الالتزام بالمعايير. | E5: الإسناد الفني المتخصص وحل القضايا المعقدة في المعايير المحاسبية والمراجعية. | F5: تنفيذ إجراءات المراجعة في مواقع العملاء وجمع الأدلة الكافية والملائمة. | G5: مساندة الإدارة الفنية بالبحوث والإعداد الفني الأولي. | H5: قناة الاتصال المركزية وتنسيق التسليمات بين المكتب والعميل. | I5: الإشراف على نظام إدارة الجودة والامتثال للاستقلالية. | J5: القيادة الاستراتيجية والتشغيلية والحوكمة الشاملة للمكتب. | K5: إدارة تقديم القوائم والتقارير عبر منصات الجهات الحكومية ذات العلاقة. | L5: حفظ وأمن واسترجاع ملفات المهام والمراسلات وسجلات الجودة.
B6: المسؤوليات | C6: استقبال الاتصالات، تنظيم المواعيد والزيارات، إعداد المحاضر والمراسلات، تنسيق السفر، متابعة المهام. | D6: خطة المراجعة السنوية، توزيع الفرق، الإشراف على التنفيذ، مراجعة أوراق العمل، التواصل مع العملاء، اعتماد التقارير. | E6: مذكرات فنية، آراء فنية في المجالات عالية المخاطر، مراجعة الإفصاحات، تدريب فني. | F6: اختبارات ضوابط وإجراءات تفصيلية، توثيق نتائج، رفع الاستفسارات، سجلات أخطاء. | G6: بحوث معيارية، مسودات مذكرات، إعداد جداول إفصاح، تنسيق بيانات فنية. | H6: إستلام وتحويل الطلبات، إدارة الجداول الزمنية، توثيق المراسلات، ترتيب الاجتماعات، تصعيد العقبات. | I6: مراجعات جودة المشاركة (عند اللزوم)، فحوصات ما قبل/ما بعد الإصدار، مراقبة الاستقلالية، تحديث السياسات والتدريب. | J6: استراتيجية وأهداف، إدارة المخاطر والجودة، اعتماد التعيينات والميزانيات، تنمية الأعمال، التمثيل الخارجي. | K6: إعداد وجدولة الرفع (وزارة التجارة، زاتكا/ZATCA…)، فحص المتطلبات الشكلية والفنية، متابعة الحالات ومعالجة الرفض، حفظ الإيصالات. | L6: فهرسة وهيكلة الحفظ، إدارة صلاحيات الوصول والنسخ الاحتياطي، تلبية طلبات الاسترجاع، الإتلاف الآمن بعد مدة الاحتفاظ.
B7: المسؤولية ببرنامج المدقق | C7: اعداد خطاب الارتباط وارفاق المستندات حسب متطلبات دليل المراجعة من العميل | D7: الموافقة علي استمرارية العلاقة والارتباط بالعميل واعتماد النماذج المكلف بها نظاما في دليل المراجعة | E7: استيراد ميزان المراجعة واعداد القوائم المالية واوراق العمل ضمن التخطيط بالبرنامج واعتماد النماذج المكلف بها نظاما في دليل المراجعة | F7: استلام عقود الارتباط المراد تسجيل زيارات لها والقيام بالاعمال الخاصة بتلك الزيارة | G7: أداء الاعمال الموكلة له من المدقق الفني واعداد النماذج الكلف بها نظاما ضمن دليل المراجعة | H7: توفير المتطلبات ضمن دليل المراجعة ودليل المحاسبة والتي تظهر في البوابة الخاصة بة عند انشاء عقد الارتباط | I7: مراجعة ملف عقد الارتباط بالكامل ضمن ضوابط دليل ضبط الجودة | J7: مراجعة ملف عقد الارتباط ضمن متطلبات التوقيع | K7: مواقع الزكاة ومواقع وزارة التجارة قوائم واي مواقع اخري تظهر لاحقا | L7: تقفيل الملف وسحب عقود الارتباط المنتهية من كل الادارت ويصبح غير متوفر الا بطلب رسمي من الجهة
B8: المخرجات | C8: تقويم مُحدّث، محاضر واجتماعات منظمة، مراسلات مؤرشفة. | D8: خطط مهمات، تقارير مراجعة معتمدة، جداول تقدم. | E8: أوراق موقف فني، إرشادات تطبيقية، تحديثات معيارية. | F8: أوراق عمل مكتملة، جداول ملاحظات وأخطاء. | G8: مسودات فنية مُراجعة، قوائم تحقق إفصاحات. | H8: سجل مراسلات، خطة تسليمات، محاضر تنسيق. | I8: تقارير فحص جودة، سجلات استقلالية، إجراءات مُحدّثة. | J8: خطط وأهداف سنوية، قرارات وسياسات مُعتمدة. | K8: إيصالات تقديم، سجل التزام بالمواعيد، تقارير حالة. | L8: قاعدة أرشيف مُحدّثة، سجل حركة ملفات، تقارير امتثال خصوصية.
A9: إضافة مستخدم | B9: واجهات العمل | C9: جميع الإدارات، العملاء، المورّدون. | D9: المدققون، الجودة، الشريك الإداري، العميل. | E9: إدارة المراجعة، مساعدو الفني، الجودة | F9: إدارة المراجعة، العميل، الإدارة الفنية. | G9: الإدارة الفنية، إدارة المراجعة. | H9: العميل، إدارة المراجعة، السكرتارية، الإدارات الداعمة | I9: جميع إدارات المراجعة، الشريك الإداري. | J9: جميع الإدارات، جهات مهنية ورقابية رئيسية | K9: العميل، إدارة المراجعة، الاتصال، السكرتارية | L9: جميع الإدارات، الجودة، تقنية المعلومات (إن وجدت).
A10: من قائمة منسدلة يجب اختيار رئيسي / فرع | C10: رئيسي / فرع / | D10: رئيسي / فرع / | E10: رئيسي / فرع / | F10: رئيسي / فرع / | G10: رئيسي / فرع / | H10: رئيسي / فرع / | I10: رئيسي / فرع / | J10: المكتب الرئيسي وكل الفروع | L10: الرئيسي وكل الفروع
A11: من قائمة منسدلة يجب اختيار الإدارة
A12: البيانات الأساسية (إلزامية)
A13: 1. الاسم الكامل (Full Name)
A14: 2. المسمّى الوظيفي/الإدارة (Job Title / Department) | B14: =B3 -> ترجمة اسم الإدارة | C14: =C2 -> سكرتارية | D14: =D2 -> مدير المراجعة | E14: =E2 -> المدقق الفني | F14: =F2 -> المدقق الميداني | G14: =G2 -> مساعد المدقق الفني | H14: =H2 -> ضابط اتصال الشركة | I14: =I2 -> ضبط الجودة | J14: =J2 -> الشريك الإداري | ... L14: =L2 -> الأرشيف
A15: 3. البريد الإلكتروني الوظيفي (Work Email) | C15: يتم الادخال | D15: يتم الادخال | E15: يتم الادخال | F15: يتم الادخال | G15: يتم الادخال | H15: يتم الادخال | I15: يتم الادخال | J15: يتم الادخال | K15: يتم الادخال | L15: يتم الادخال
A16: 4. رقم الجوال للعمل أو وسيلة تواصل موثوقة (Work Mobile / Contact) | C16: يتم الادخال | D16: يتم الادخال | E16: يتم الادخال | F16: يتم الادخال | G16: يتم الادخال | H16: يتم الادخال | I16: يتم الادخال | J16: يتم الادخال | K16: يتم الادخال | L16: يتم الادخال
A17: 5. اسم المستخدم المقترح (Username) | C17: يتم الادخال رمز الإدارة وثلاثة حروف من الاسم | D17: يتم الادخال رمز الإدارة وثلاثة حروف من الاسم | E17: يتم الادخال رمز الإدارة وثلاثة حروف من الاسم | F17: يتم الادخال رمز الإدارة وثلاثة حروف من الاسم | G17: يتم الادخال رمز الإدارة وثلاثة حروف من الاسم | H17: يتم الادخال رمز الإدارة وثلاثة حروف من الاسم | I17: يتم الادخال رمز الإدارة وثلاثة حروف من الاسم | J17: يتم الادخال رمز الإدارة وثلاثة حروف من الاسم | K17: يتم الادخال رمز الإدارة وثلاثة حروف من الاسم | L17: يتم الادخال رمز الإدارة وثلاثة حروف من الاسم
A18: 6. مستوى الصلاحيات ودور النظام (Access Role/Permissions) | C18: حسب المسؤولية المعطاه ببرنامج المدقق
A19: 7. المدير المباشر (Direct Manager) | B19: كل إدارة لها مدير ويتمثل في المرحلة السابقة | C19: =_xlfn.CONCAT(D2,"و ",E2) -> مدير المراجعة و المدقق الفني | D19: =J2 -> الشريك الإداري | E19: =D2 -> مدير المراجعة | F19: =E2 -> المدقق الفني | G19: =E2 -> المدقق الفني | H19: =_xlfn.CONCAT(C2,"و ",E2) -> سكرتارية و المدقق الفني | I19: =J2 -> الشريك الإداري | J19: =J2 -> الشريك الإداري
A20: 8. تاريخ بدء العمل (Start Date) | B20: يتم الادخال | C20: يتم الادخال | D20: يتم الادخال | E20: يتم الادخال | F20: يتم الادخال | G20: يتم الادخال | H20: يتم الادخال | I20: يتم الادخال | J20: يتم الادخال | K20: يتم الادخال | L20: يتم الادخال
A21: بيانات مساعدة (مستحسنة)
A22: رقم الموظف الداخلي (Employee ID) | B22: حين توفير إدارة لشؤون الموظفين في موديولات التطوير لاحقا | C22: حين توفير إدارة لشؤون الموظفين في موديولات التطوير لاحقا | D22: حين توفير إدارة لشؤون الموظفين في موديولات التطوير لاحقا | E22: حين توفير إدارة لشؤون الموظفين في موديولات التطوير لاحقا | F22: حين توفير إدارة لشؤون الموظفين في موديولات التطوير لاحقا | G22: حين توفير إدارة لشؤون الموظفين في موديولات التطوير لاحقا | H22: حين توفير إدارة لشؤون الموظفين في موديولات التطوير لاحقا | I22: حين توفير إدارة لشؤون الموظفين في موديولات التطوير لاحقا | J22: حين توفير إدارة لشؤون الموظفين في موديولات التطوير لاحقا | K22: حين توفير إدارة لشؤون الموظفين في موديولات التطوير لاحقا | L22: حين توفير إدارة لشؤون الموظفين في موديولات التطوير لاحقا
A23: اللغة المفضلة والمنطقة الزمنية (Preferred Language & Time Zone) | B23: اختيار من قائمة منسلدة من بين اللغات المكونة | C23: اختيار من قائمة منسلدة من بين اللغات المكونة | D23: اختيار من قائمة منسلدة من بين اللغات المكونة | E23: اختيار من قائمة منسلدة من بين اللغات المكونة | F23: اختيار من قائمة منسلدة من بين اللغات المكونة | G23: اختيار من قائمة منسلدة من بين اللغات المكونة | H23: اختيار من قائمة منسلدة من بين اللغات المكونة | I23: اختيار من قائمة منسلدة من بين اللغات المكونة | J23: اختيار من قائمة منسلدة من بين اللغات المكونة | K23: اختيار من قائمة منسلدة من بين اللغات المكونة | L23: اختيار من قائمة منسلدة من بين اللغات المكونة
A24: مكان العمل (Work Location: مدينة/مكتب/عن بُعد) | B24: اختيار الفرع من قائمة منسدلة | C24: اختيار الفرع من قائمة منسدلة | D24: اختيار الفرع من قائمة منسدلة | E24: اختيار الفرع من قائمة منسدلة | F24: اختيار الفرع من قائمة منسدلة | G24: اختيار الفرع من قائمة منسدلة | H24: اختيار الفرع من قائمة منسدلة | I24: اختيار الفرع من قائمة منسدلة | J24: اختيار الفرع من قائمة منسدلة | K24: اختيار الفرع من قائمة منسدلة | L24: اختيار الفرع من قائمة منسدلة
A25: صورة شخصية مهنية (Profile Photo) | B25: يتم الادخال | C25: يتم الادخال | D25: يتم الادخال | E25: يتم الادخال | F25: يتم الادخال | G25: يتم الادخال | H25: يتم الادخال | I25: يتم الادخال | J25: يتم الادخال | K25: يتم الادخال | L25: يتم الادخال
A26: توقيع إلكتروني للاستخدام في المراسلات (Email Signature) | B26: يتم الادخال | C26: يتم الادخال | D26: يتم الادخال | E26: يتم الادخال | F26: يتم الادخال | G26: يتم الادخال | H26: يتم الادخال | I26: يتم الادخال | J26: يتم الادخال | K26: يتم الادخال | L26: يتم الادخال
A27: بيانات الطوارئ (Emergency Contact) | B27: يتم الادخال | C27: يتم الادخال | D27: يتم الادخال | E27: يتم الادخال | F27: يتم الادخال | G27: يتم الادخال | H27: يتم الادخال | I27: يتم الادخال | J27: يتم الادخال | K27: يتم الادخال | L27: يتم الادخال
A28: الأجهزة المخصصة ورقمها التسلسلي إن وُجد (Assigned Devices & Serials) | B28: يتم الادخال | C28: يتم الادخال | D28: يتم الادخال | E28: يتم الادخال | F28: يتم الادخال | G28: يتم الادخال | H28: يتم الادخال | I28: يتم الادخال | J28: يتم الادخال | K28: يتم الادخال | L28: يتم الادخال
A29: متطلبات أمنية عند الإنشاء
A30: بريد/هاتف استرداد لحالات فقدان الوصول (Recovery Email/Phone). | B30: يتم الادخال | C30: يتم الادخال | D30: يتم الادخال | E30: يتم الادخال | F30: يتم الادخال | G30: يتم الادخال | H30: يتم الادخال | I30: يتم الادخال | J30: يتم الادخال | K30: يتم الادخال | L30: يتم الادخال
A31: سياسة كلمة المرور: لا تُحفظ كلمات مرور بنص صريح؛ أرسل رابط تفعيل لتعيينها ذاتيًا. | B31: يتم التحديد مسبقا من صفحة المشترك وتقرأ هنا فقط للاطلاع | C31: يتم التحديد مسبقا من صفحة المشترك وتقرأ هنا فقط للاطلاع | D31: يتم التحديد مسبقا من صفحة المشترك وتقرأ هنا فقط للاطلاع | E31: يتم التحديد مسبقا من صفحة المشترك وتقرأ هنا فقط للاطلاع | F31: يتم التحديد مسبقا من صفحة المشترك وتقرأ هنا فقط للاطلاع | G31: يتم التحديد مسبقا من صفحة المشترك وتقرأ هنا فقط للاطلاع | H31: يتم التحديد مسبقا من صفحة المشترك وتقرأ هنا فقط للاطلاع | I31: يتم التحديد مسبقا من صفحة المشترك وتقرأ هنا فقط للاطلاع | J31: يتم التحديد مسبقا من صفحة المشترك وتقرأ هنا فقط للاطلاع | K31: يتم التحديد مسبقا من صفحة المشترك وتقرأ هنا فقط للاطلاع | L31: يتم التحديد مسبقا من صفحة المشترك وتقرأ هنا فقط للاطلاع
A32: تعيين سياسات الوصول (مجموعات، قنوات، مجلدات، تطبيقات) حسب دور المستخدم ومبدأ أقل صلاحية. | B32: يتم التحديد مسبقا من صفحة المشترك وتقرأ هنا فقط للاطلاع | C32: يتم التحديد مسبقا من صفحة المشترك وتقرأ هنا فقط للاطلاع | D32: يتم التحديد مسبقا من صفحة المشترك وتقرأ هنا فقط للاطلاع | E32: يتم التحديد مسبقا من صفحة المشترك وتقرأ هنا فقط للاطلاع | F32: يتم التحديد مسبقا من صفحة المشترك وتقرأ هنا فقط للاطلاع | G32: يتم التحديد مسبقا من صفحة المشترك وتقرأ هنا فقط للاطلاع | H32: يتم التحديد مسبقا من صفحة المشترك وتقرأ هنا فقط للاطلاع | I32: يتم التحديد مسبقا من صفحة المشترك وتقرأ هنا فقط للاطلاع | J32: يتم التحديد مسبقا من صفحة المشترك وتقرأ هنا فقط للاطلاع | K32: يتم التحديد مسبقا من صفحة المشترك وتقرأ هنا فقط للاطلاع | L32: يتم التحديد مسبقا من صفحة المشترك وتقرأ هنا فقط للاطلاع
A33: المهام لكل إدارة
A34: إضافة عقود الارتباط الجديدة | C34: إضافة عقد ارتباط | D34: الموافقة علي نماذج الاستمرارية والاستقلالية او ارجاع العقد للعميل لاستكمال النواقص او التعديل | E34: ظهور عقد الارتباط في نافذتة لاستكمال الاعمال المحددة لة وفق ضوابط برنامج المدقق | F34: ظهور عقد الارتباط في نافذتة لاستكمال الاعمال المحددة لة وفق ضوابط برنامج المدقق | G34: ظهور عقد الارتباط في نافذتة لاستكمال الاعمال المحددة لة وفق ضوابط برنامج المدقق | H34: ظهور عقد الارتباط في نافذتة لاستكمال الاعمال المحددة لة وفق ضوابط برنامج المدقق | I34: ظهور عقد الارتباط في نافذتة لاستكمال الاعمال المحددة لة وفق ضوابط برنامج المدقق | J34: ظهور عقد الارتباط في نافذتة لاستكمال الاعمال المحددة لة وفق ضوابط برنامج المدقق | K34: ظهور عقد الارتباط في نافذتة لاستكمال الاعمال المحددة لة وفق ضوابط برنامج المدقق | L34: ظهور عقد الارتباط في نافذتة لاستكمال الاعمال المحددة لة وفق ضوابط برنامج المدقق
A35: تعديل بيانات الملف الأساسية (قبل التخطيط) | C35: ✔︎ | D35: ✔︎ (النطاق/الخطة) | E35: ◐ | F35: ✖︎ | G35: ✖︎ | H35: ◐ (بيانات جهة الاتصال فقط) | I35: ◐ | J35: ◐ | L35: ✖︎
A36: رفع أدلة الإثبات وأوراق العمل | C36: حسب المحدد بدليل المراجعة | D36: حسب المحدد بدليل المراجعة | E36: حسب المحدد بدليل المراجعة ودليل الحسابات | F36: حسب المحدد بدليل المراجعة ودليل الحسابات | G36: حسب المحدد بدليل المراجعة ودليل الحسابات | H36: حسب المحدد بدليل المراجعة ودليل الحسابات | I36: حسب المحدد بدليل المراجعة ودليل الحسابات | J36: حسب المحدد بدليل المراجعة | L36: ✖︎
